Workbook

Sheet Janeiro2023
A2: EXTRATO DE MOVIMENTAÇÃO
A4: Banco | B4: LEPTA BANK (274) | C4: Agência | D4: 1 | E4: Conta | F4: 08198095-5
A5: Empresa | B5: TRANSP. TURISTICA BENFICA S.A | C5: Saldo Anterior | D5: 0 | F5: Saldo Disponível
A6: CNPJ | B6: 59.275.289/0001-02 | C6: Totais (Entradas/Saídas) | D6: =SUM(D9:D609) -> 3471533.7 | E6: =SUM(E9:E609) -> 248957.67 | F6: =F609 -> 3222576
A8: Data | B8: Histórico | C8: Complemento | D8: Créditos | E8: Débitos | F8: Saldo
A9: 44938 | B9: Crédito em conta | C9: TRANSPORTADORA TURISTICA BENFICA S.A | D9: 1000 | F9: =D9-E9+D5 -> 1000
A10: 44938 | B10: Gestão de caixa | E10: =(D9*0.005)+10 -> 15 | F10: =D10-E10+F9 -> 985
A11: 44939 | B11: Transferência entre contas | C11: TRANSPORTADORA TURISTICA BENFICA S.A | E11: 450 | F11: =D11-E11+F10 -> 535
A12: 44944 | B12: Crédito em conta | C12: TRANSPORTADORA TURISTICA BENFICA S.A | D12: 3445000 | F12: =D12-E12+F11 -> 3445535
A13: 44944 | B13: Gestão de caixa | E13: =(D12*0.005)+10 -> 17235 | F13: =D13-E13+F12 -> 3428300
A14: 44946 | B14: Transferência entre contas | C14: TRANSPORTADORA TURISTICA BENFICA S.A | E14: 111500 | F14: =D14-E14+F13 -> 3316800
A15: 44946 | B15: Transferência entre contas | C15: TRANSPORTADORA TURISTICA BENFICA S.A | E15: 35000 | F15: =D15-E15+F14 -> 3281800
A16: 44950 | B16: Transferência entre contas | C16: TRANSPORTADORA TURISTICA BENFICA S.A | E16: 75600 | F16: =D16-E16+F15 -> 3206200
A17: 44953 | B17: Transferência entre contas | C17: TRANSPORTADORA TURISTICA BENFICA S.A | E17: 9000 | F17: =D17-E17+F16 -> 3197200
A18: 44953 | B18: Crédito em conta | C18: TRANSPORTADORA TURISTICA BENFICA S.A | D18: 6556.11 | F18: =D18-E18+F17 -> 3203756.1
A19: 44953 | B19: Gestão de caixa | E19: =(D18*0.005)+10 -> 42.78055 | F19: =D19-E19+F18 -> 3203713.3
A20: 44956 | B20: Crédito em conta | C20: TRANSPORTADORA TURISTICA BENFICA S.A | D20: 14727.55 | F20: =D20-E20+F19 -> 3218440.9
A21: 44956 | B21: Gestão de caixa | E21: =(D20*0.005)+10 -> 83.63775 | F21: =D21-E21+F20 -> 3218357.2
A22: 44957 | B22: Crédito em conta | C22: TRANSPORTADORA TURISTICA BENFICA S.A | D22: 4250 | F22: =D22-E22+F21 -> 3222607.2
A23: 44957 | B23: Gestão de caixa | E23: =(D22*0.005)+10 -> 31.25 | F23: =D23-E23+F22 -> 3222576
F24: =D24-E24+F23 -> 3222576
F25: =D25-E25+F24 -> 3222576
F26: =D26-E26+F25 -> 3222576
F27: =D27-E27+F26 -> 3222576
F28: =D28-E28+F27 -> 3222576
F29: =D29-E29+F28 -> 3222576
F30: =D30-E30+F29 -> 3222576
F31: =D31-E31+F30 -> 3222576
F32: =D32-E32+F31 -> 3222576
F33: =D33-E33+F32 -> 3222576
F34: =D34-E34+F33 -> 3222576
F35: =D35-E35+F34 -> 3222576
... F609: =D609-E609+F608 -> 3222576

Sheet Fevereiro2023
A2: EXTRATO DE MOVIMENTAÇÃO
A4: Banco | B4: LEPTA BANK (274) | C4: Agência | D4: 1 | E4: Conta | F4: 08198095-5
A5: Empresa | B5: TRANSP. TURISTICA BENFICA S.A | C5: Saldo Anterior | D5: =Janeiro2023!F6 -> 3222576 | F5: Saldo Disponível
A6: CNPJ | B6: 59.275.289/0001-02 | C6: Totais (Entradas/Saídas) | D6: =SUM(D9:D609) -> 655663.83 | E6: =SUM(E9:E609) -> 897524.44 | F6: =F609 -> 2980715.4
A8: Data | B8: Histórico | C8: Complemento | D8: Créditos | E8: Débitos | F8: Saldo
A9: 44958 | B9: Crédito em conta | C9: BENFICA CARGAS E LOGISTICA S.A | D9: 12000 | F9: =D9-E9+D5 -> 3234576
A10: 44958 | B10: Gestão de caixa | E10: =(D9*0.005)+10 -> 70 | F10: =D10-E10+F9 -> 3234506
A11: 44958 | B11: Transferência entre contas | C11: TRANSPORTADORA TURISTICA BENFICA S.A | E11: 112000 | F11: =D11-E11+F10 -> 3122506
A12: 44958 | B12: Crédito em conta | C12: TRANSPORTADORA TURISTICA BENFICA AS | D12: 20000 | F12: =D12-E12+F11 -> 3142506
A13: 44958 | B13: Gestão de caixa | E13: =(D12*0.005)+10 -> 110 | F13: =D13-E13+F12 -> 3142396
A14: 44959 | B14: Transferência entre contas | C14: TRANSPORTADORA TURISTICA BENFICA S.A | E14: 12000 | F14: =D14-E14+F13 -> 3130396
A15: 44960 | B15: Tarifa de manutenção de conta | C15: TRANSPORTADORA TURISTICA BENFICA S.A | E15: 1358.06 | F15: =D15-E15+F14 -> 3129037.9
A16: 44960 | B16: Transferência entre contas | C16: TRANSPORTADORA TURISTICA BENFICA S.A | E16: 14000 | F16: =D16-E16+F15 -> 3115037.9
A17: 44963 | B17: Crédito em conta | C17: UNIVERSAL TURISMO LTDA-EPP | D17: 18000 | F17: =D17-E17+F16 -> 3133037.9
A18: 44963 | B18: Gestão de caixa | E18: =(D17*0.005)+10 -> 100 | F18: =D18-E18+F17 -> 3132937.9
A19: 44963 | B19: Transferência entre contas | C19: TRANSPORTADORA TURISTICA BENFICA S.A | E19: 261000 | F19: =D19-E19+F18 -> 2871937.9
A20: 44963 | B20: Transferência entre contas | C20: TRANSPORTADORA TURISTICA BENFICA S.A | E20: 16000 | F20: =D20-E20+F19 -> 2855937.9
A21: 44964 | B21: Transferência entre contas | C21: TRANSPORTADORA TURISTICA BENFICA S.A | E21: 50000 | F21: =D21-E21+F20 -> 2805937.9
A22: 44965 | B22: Crédito em conta | C22: PATRIMONY ADMINISTRADORA DE BENS AS | D22: 180030.83 | F22: =D22-E22+F21 -> 2985968.8
A23: 44965 | B23: Gestão de caixa | E23: =(D22*0.005)+10 -> 910.15415 | F23: =D23-E23+F22 -> 2985058.6
A24: 44965 | B24: Crédito em conta | C24: TRANSPORTADORA TURISTICA BENFICA AS | D24: 90000 | F24: =D24-E24+F23 -> 3075058.6
A25: 44965 | B25: Gestão de caixa | E25: =(D24*0.005)+10 -> 460 | F25: =D25-E25+F24 -> 3074598.6
A26: 44965 | B26: Transferência entre contas | C26: TRANSPORTADORA TURISTICA BENFICA S.A | E26: 3000 | F26: =D26-E26+F25 -> 3071598.6
A27: 44965 | B27: Tarifa de manutenção de conta | C27: TRANSPORTADORA TURISTICA BENFICA S.A - (Empresa) | E27: 1258.06 | F27: =D27-E27+F26 -> 3070340.5
A28: 44965 | B28: Crédito em conta | C28: MENDES FERREIRA AGRICOLA LTDA | D28: 4050 | F28: =D28-E28+F27 -> 3074390.5
A29: 44965 | B29: Gestão de caixa | E29: =(D28*0.005)+10 -> 30.25 | F29: =D29-E29+F28 -> 3074360.3
A30: 44966 | B30: Crédito em conta | C30: TRANSPORTADORA TURISTICA BENFICA AS | D30: 255000 | F30: =D30-E30+F29 -> 3329360.3
A31: 44966 | B31: Gestão de caixa | E31: =(D30*0.005)+10 -> 1285 | F31: =D31-E31+F30 -> 3328075.3
A32: 44967 | B32: Transferência entre contas | C32: TRANSPORTADORA TURISTICA BENFICA S.A | E32: 14000 | F32: =D32-E32+F31 -> 3314075.3
A33: 44967 | B33: Crédito em conta | C33: AGROCANA A N H LTDA. | D33: 8000 | F33: =D33-E33+F32 -> 3322075.3
A34: 44967 | B34: Gestão de caixa | E34: =(D33*0.005)+10 -> 50 | F34: =D34-E34+F33 -> 3322025.3
A35: 44967 | B35: Crédito em conta | C35: AGROCANA A N H LTDA. | D35: 1333 | F35: =D35-E35+F34 -> 3323358.3
A36: 44967 | B36: Gestão de caixa | E36: =(D35*0.005)+10 -> 16.665 | F36: =D36-E36+F35 -> 3323341.6
A37: 44967 | B37: Crédito em conta | C37: AGROCANA A N H LTDA. | D37: 8000 | F37: =D37-E37+F36 -> 3331341.6
A38: 44967 | B38: Gestão de caixa | E38: =(D37*0.005)+10 -> 50 | F38: =D38-E38+F37 -> 3331291.6
A39: 44972 | B39: Transferência entre contas | C39: TRANSPORTADORA TURISTICA BENFICA S.A | E39: 58000 | F39: =D39-E39+F38 -> 3273291.6
A40: 44973 | B40: Transferência entre contas | C40: TRANSPORTADORA TURISTICA BENFICA S.A | E40: 35500 | F40: =D40-E40+F39 -> 3237791.6
A41: 44974 | B41: Transferência entre contas | C41: TRANSPORTADORA TURISTICA BENFICA S.A | E41: 182000 | F41: =D41-E41+F40 -> 3055791.6
A42: 44980 | B42: Crédito em conta | C42: JOSE AILTON F CONCEICAO | D42: 1250 | F42: =D42-E42+F41 -> 3057041.6
A43: 44980 | B43: Gestão de caixa | E43: =(D42*0.005)+10 -> 16.25 | F43: =D43-E43+F42 -> 3057025.4
A44: 44980 | B44: Crédito em conta | C44: TRANSPORTADORA TURISTICA BENFICA S.A | D44: 25500 | F44: =D44-E44+F43 -> 3082525.4
A45: 44980 | B45: Gestão de caixa | E45: =(D44*0.005)+10 -> 137.5 | F45: =D45-E45+F44 -> 3082387.9
A46: 44981 | B46: Transferência entre contas | C46: TRANSPORTADORA TURISTICA BENFICA S.A | E46: 51000 | F46: =D46-E46+F45 -> 3031387.9
A47: 44981 | B47: Crédito em conta | C47: SILVA & BEGHINI COMERCIO DE ONIBUS LTDA | D47: 32500 | F47: =D47-E47+F46 -> 3063887.9
A48: 44981 | B48: Gestão de caixa | E48: =(D47*0.005)+10 -> 172.5 | F48: =D48-E48+F47 -> 3063715.4
A49: 44984 | B49: Transferência entre contas | C49: TRANSPORTADORA TURISTICA BENFICA S.A | E49: 11000 | F49: =D49-E49+F48 -> 3052715.4
A50: 44985 | B50: Transferência entre contas | C50: TRANSPORTADORA TURISTICA BENFICA S.A | E50: 72000 | F50: =D50-E50+F49 -> 2980715.4
F51: =D51-E51+F50 -> 2980715.4
F52: =D52-E52+F51 -> 2980715.4
F53: =D53-E53+F52 -> 2980715.4
F54: =D54-E54+F53 -> 2980715.4
F55: =D55-E55+F54 -> 2980715.4
F56: =D56-E56+F55 -> 2980715.4
F57: =D57-E57+F56 -> 2980715.4
F58: =D58-E58+F57 -> 2980715.4
F59: =D59-E59+F58 -> 2980715.4
F60: =D60-E60+F59 -> 2980715.4
F61: =D61-E61+F60 -> 2980715.4
F62: =D62-E62+F61 -> 2980715.4
... F609: =D609-E609+F608 -> 2980715.4

Sheet Março2023
A2: EXTRATO DE MOVIMENTAÇÃO
A4: Banco | B4: LEPTA BANK (274) | C4: Agência | D4: 1 | E4: Conta | F4: 08198095-5
A5: Empresa | B5: TRANSP. TURISTICA BENFICA S.A | C5: Saldo Anterior | D5: =Fevereiro2023!F6 -> 2980715.4 | F5: Saldo Disponível
A6: CNPJ | B6: 59.275.289/0001-02 | C6: Totais (Entradas/Saídas) | D6: =SUM(D9:D609) -> 854448.93 | E6: =SUM(E9:E609) -> 1094712.3 | F6: =F609 -> 2740452.1
A8: Data | B8: Histórico | C8: Complemento | D8: Créditos | E8: Débitos | F8: Saldo
A9: 44986 | B9: Transferência entre contas | C9: TRANSPORTADORA TURISTICA BENFICA S.A | E9: 45000 | F9: =D9-E9+D5 -> 2935715.4
A10: 44986 | B10: Crédito em conta | C10: PERFFICE DO BRASIL SERVICOS DE TRANSPORTE E LOGISTICA | D10: 20430 | F10: =D10-E10+F9 -> 2956145.4
A11: 44986 | B11: Gestão de caixa | E11: =(D10*0.005)+10 -> 112.15 | F11: =D11-E11+F10 -> 2956033.2
A12: 44987 | B12: Crédito em conta | C12: BENFICA CARGAS E LOGISTICA S.A | D12: 13000 | F12: =D12-E12+F11 -> 2969033.2
A13: 44987 | B13: Gestão de caixa | E13: =(D12*0.005)+10 -> 75 | F13: =D13-E13+F12 -> 2968958.2
A14: 44988 | B14: Tarifa de manutenção de conta | C14: TRANSPORTADORA TURISTICA BENFICA S.A - (Vinculada) | E14: 1500 | F14: =D14-E14+F13 -> 2967458.2
A15: 44988 | B15: Tarifa de manutenção da conta | C15: TED's, PIX e demais | E15: 280 | F15: =D15-E15+F14 -> 2967178.2
A16: 44988 | B16: Transferência entre contas | C16: TRANSPORTADORA TURISTICA BENFICA S.A | E16: 193000 | F16: =D16-E16+F15 -> 2774178.2
A17: 44991 | B17: Transferência entre contas | C17: TRANSPORTADORA TURISTICA BENFICA S.A | E17: 122000 | F17: =D17-E17+F16 -> 2652178.2
A18: 44992 | B18: Crédito em conta | C18: BY BUS TRANSPORTES LTDA | D18: 22483.31 | F18: =D18-E18+F17 -> 2674661.5
A19: 44992 | B19: Gestão de caixa | E19: =(D18*0.005)+10 -> 122.41655 | F19: =D19-E19+F18 -> 2674539.1
A20: 44992 | B20: Crédito em conta | C20: TRANSPORTADORA TURISTICA BENFICA AS | D20: 51000 | F20: =D20-E20+F19 -> 2725539.1
A21: 44992 | B21: Gestão de caixa | E21: =(D20*0.005)+10 -> 265 | F21: =D21-E21+F20 -> 2725274.1
A22: 44992 | B22: Tarifa de manutenção de conta | C22: TRANSPORTADORA TURISTICA BENFICA S.A - (Empresa) | E22: 1500 | F22: =D22-E22+F21 -> 2723774.1
A23: 44993 | B23: Transferência entre contas | C23: TRANSPORTADORA TURISTICA BENFICA S.A | E23: 8000 | F23: =D23-E23+F22 -> 2715774.1
A24: 44993 | B24: Crédito em conta | C24: PATRIMONY ADMINISTRADORA DE BENS AS | D24: 180030.83 | F24: =D24-E24+F23 -> 2895805
A25: 44993 | B25: Gestão de caixa | E25: =(D24*0.005)+10 -> 910.15415 | F25: =D25-E25+F24 -> 2894894.8
A26: 44994 | B26: Transferência entre contas | C26: TRANSPORTADORA TURISTICA BENFICA S.A | E26: 3000 | F26: =D26-E26+F25 -> 2891894.8
A27: 44994 | B27: Crédito em conta | C27: OUROESTE BIOENERGIA LTDA | D27: 19958.92 | F27: =D27-E27+F26 -> 2911853.7
A28: 44994 | B28: Gestão de caixa | E28: =(D27*0.005)+10 -> 109.7946 | F28: =D28-E28+F27 -> 2911743.9
A29: 44995 | B29: Transferência entre contas | C29: TRANSPORTADORA TURISTICA BENFICA S.A | E29: 97000 | F29: =D29-E29+F28 -> 2814743.9
A30: 44995 | B30: Crédito em conta | C30: TRANSPORTADORA TURISTICA BENFICA S.A | D30: 18330 | F30: =D30-E30+F29 -> 2833073.9
A31: 44995 | B31: Gestão de caixa | E31: =(D30*0.005)+10 -> 101.65 | F31: =D31-E31+F30 -> 2832972.3
A32: 44995 | B32: Crédito em conta | C32: GUARIROBA BIOENERGIA LTDA | D32: 124486.37 | F32: =D32-E32+F31 -> 2957458.6
A33: 44995 | B33: Gestão de caixa | E33: =(D32*0.005)+10 -> 632.43185 | F33: =D33-E33+F32 -> 2956826.2
A34: 44995 | B34: Crédito em conta | C34: MOEMA BIOENERGIA S A | D34: 260234.27 | F34: =D34-E34+F33 -> 3217060.5
A35: 44995 | B35: Gestão de caixa | E35: =(D34*0.005)+10 -> 1311.1714 | F35: =D35-E35+F34 -> 3215749.3
A36: 44995 | B36: Transferência entre contas | C36: TRANSPORTADORA TURISTICA BENFICA S.A | E36: 14000 | F36: =D36-E36+F35 -> 3201749.3
A37: 44995 | B37: Ajuste de Saldo | D37: 0.01 | F37: =D37-E37+F36 -> 3201749.3
A38: 44999 | B38: Transferência entre contas | C38: TRANSPORTADORA TURISTICA BENFICA S.A | E38: 48000 | F38: =D38-E38+F37 -> 3153749.3
A39: 45000 | B39: Transferência entre contas | C39: TRANSPORTADORA TURISTICA BENFICA S.A | E39: 53000 | F39: =D39-E39+F38 -> 3100749.3
A40: 45000 | B40: Crédito em conta | C40: BY BUS TRANSPORTES LTDA | D40: 18000 | F40: =D40-E40+F39 -> 3118749.3
A41: 45000 | B41: Gestão de caixa | E41: =(D40*0.005)+10 -> 100 | F41: =D41-E41+F40 -> 3118649.3
A42: 45001 | B42: Crédito em conta | C42: TRANSPORTADORA TURISTICA BENFICA AS | D42: 26000 | F42: =D42-E42+F41 -> 3144649.3
A43: 45001 | B43: Gestão de caixa | E43: =(D42*0.005)+10 -> 140 | F43: =D43-E43+F42 -> 3144509.3
A44: 45001 | B44: Transferência entre contas | C44: TRANSPORTADORA TURISTICA BENFICA S.A | E44: 75500 | F44: =D44-E44+F43 -> 3069009.3
A45: 45002 | B45: Transferência entre contas | C45: TRANSPORTADORA TURISTICA BENFICA S.A | E45: 11000 | F45: =D45-E45+F44 -> 3058009.3
A46: 45005 | B46: Transferência entre contas | C46: TRANSPORTADORA TURISTICA BENFICA S.A | E46: 110500 | F46: =D46-E46+F45 -> 2947509.3
A47: 45005 | B47: Transferência entre contas | C47: TRANSPORTADORA TURISTICA BENFICA S.A | E47: 4000 | F47: =D47-E47+F46 -> 2943509.3
A48: 45005 | B48: Crédito em conta | C48: MENDES FERREIRA AGRICOLA LTDA | D48: 16635.93 | F48: =D48-E48+F47 -> 2960145.3
A49: 45005 | B49: Gestão de caixa | E49: =(D48*0.005)+10 -> 93.17965 | F49: =D49-E49+F48 -> 2960052.1
A50: 45006 | B50: Transferência entre contas | C50: TRANSPORTADORA TURISTICA BENFICA S.A | E50: 12000 | F50: =D50-E50+F49 -> 2948052.1
A51: 45007 | B51: Transferência entre contas | C51: TRANSPORTADORA TURISTICA BENFICA S.A | E51: 2000 | F51: =D51-E51+F50 -> 2946052.1
A52: 45008 | B52: Transferência entre contas | C52: TRANSPORTADORA TURISTICA BENFICA S.A | E52: 30000 | F52: =D52-E52+F51 -> 2916052.1
A53: 45009 | B53: Transferência entre contas | C53: TRANSPORTADORA TURISTICA BENFICA S.A | E53: 78000 | F53: =D53-E53+F52 -> 2838052.1
A54: 45012 | B54: Transferência entre contas | C54: TRANSPORTADORA TURISTICA BENFICA S.A | E54: 20000 | F54: =D54-E54+F53 -> 2818052.1
A55: 45013 | B55: Crédito em conta | C55: TRANSPORTADORA TUR BENFICA S A | D55: 28199.29 | F55: =D55-E55+F54 -> 2846251.4
A56: 45013 | B56: Gestão de caixa | E56: =(D55*0.005)+10 -> 150.99645 | F56: =D56-E56+F55 -> 2846100.4
A57: 45013 | B57: Crédito em conta | C57: TRANSPORTADORA TUR BENFICA S A | D57: 1980 | F57: =D57-E57+F56 -> 2848080.4
A58: 45013 | B58: Gestão de caixa | E58: =(D57*0.005)+10 -> 19.9 | F58: =D58-E58+F57 -> 2848060.5
A59: 45013 | B59: Transferência entre contas | C59: TRANSPORTADORA TURISTICA BENFICA S.A | E59: 4000 | F59: =D59-E59+F58 -> 2844060.5
A60: 45013 | B60: Ajuste de Saldo | E60: 0.01 | F60: =D60-E60+F59 -> 2844060.5
A61: 45014 | B61: Transferência entre contas | C61: TRANSPORTADORA TURISTICA BENFICA S.A | E61: 2000 | F61: =D61-E61+F60 -> 2842060.5
A62: 45015 | B62: Transferência entre contas | C62: TRANSPORTADORA TURISTICA BENFICA S.A | E62: 50000 | F62: =D62-E62+F61 -> 2792060.5
A63: 45015 | B63: Crédito em conta | C63: PERFICE DO BRASIL SERVICOS DE | D63: 20430 | F63: =D63-E63+F62 -> 2812490.5
A64: 45015 | B64: Gestão de caixa | E64: =(D63*0.005)+10 -> 112.15 | F64: =D64-E64+F63 -> 2812378.3
A65: 45016 | B65: Transferência entre contas | C65: TRANSPORTADORA TURISTICA BENFICA S.A | E65: 70000 | F65: =D65-E65+F64 -> 2742378.3
A66: 45016 | B66: Crédito em conta | C66: BENFICA CARGAS E LOGISTICA S.A | D66: 33250 | F66: =D66-E66+F65 -> 2775628.3
A67: 45016 | B67: Gestão de caixa | E67: =(D66*0.005)+10 -> 176.25 | F67: =D67-E67+F66 -> 2775452.1
A68: 45016 | B68: Transferência entre contas | C68: TRANSPORTADORA TURISTICA BENFICA S.A | E68: 35000 | F68: =D68-E68+F67 -> 2740452.1
F69: =D69-E69+F68 -> 2740452.1
F70: =D70-E70+F69 -> 2740452.1
F71: =D71-E71+F70 -> 2740452.1
F72: =D72-E72+F71 -> 2740452.1
F73: =D73-E73+F72 -> 2740452.1
F74: =D74-E74+F73 -> 2740452.1
F75: =D75-E75+F74 -> 2740452.1
F76: =D76-E76+F75 -> 2740452.1
F77: =D77-E77+F76 -> 2740452.1
F78: =D78-E78+F77 -> 2740452.1
F79: =D79-E79+F78 -> 2740452.1
F80: =D80-E80+F79 -> 2740452.1
... F609: =D609-E609+F608 -> 2740452.1

Sheet Abril2023
A2: EXTRATO DE MOVIMENTAÇÃO
A4: Banco | B4: LEPTA BANK (274) | C4: Agência | D4: 1 | E4: Conta | F4: 08198095-5
A5: Empresa | B5: TRANSP. TURISTICA BENFICA S.A | C5: Saldo Anterior | D5: =Março2023!F6 -> 2740452.1 | F5: Saldo Disponível
A6: CNPJ | B6: 59.275.289/0001-02 | C6: Totais (Entradas/Saídas) | D6: =SUM(D9:D609) -> 1005404.5 | E6: =SUM(E9:E609) -> 968667.03 | F6: =F609 -> 2777189.5
A8: Data | B8: Histórico | C8: Complemento | D8: Créditos | E8: Débitos | F8: Saldo
A9: 45019 | B9: Tarifa de manutenção de conta | C9: TRANSPORTADORA TURISTICA BENFICA S.A - (Vinculada) | E9: 1500 | F9: =D9-E9+D5 -> 2738952.1
A10: 45019 | B10: Tarifa de manutenção da conta | C10: TED's, PIX e demais | E10: 460 | F10: =D10-E10+F9 -> 2738492.1
A11: 45021 | B11: Crédito em conta | C11: BB TRANSPORTE E TURISMO LTDA | D11: 90000 | F11: =D11-E11+F10 -> 2828492.1
A12: 45021 | B12: Gestão de caixa | E12: =(D11*0.005)+10 -> 460 | F12: =D12-E12+F11 -> 2828032.1
A13: 45021 | B13: Transferência entre contas | C13: TRANSPORTADORA TURISTICA BENFICA S.A | E13: 188000 | F13: =D13-E13+F12 -> 2640032.1
A14: 45021 | B14: Tarifa de manutenção de conta | C14: TRANSPORTADORA TURISTICA BENFICA S.A - (Empresa) | E14: 1500 | F14: =D14-E14+F13 -> 2638532.1
A15: 45022 | B15: Transferência entre contas | C15: TRANSPORTADORA TURISTICA BENFICA S.A | E15: 163500 | F15: =D15-E15+F14 -> 2475032.1
A16: 45022 | B16: Crédito em conta | C16: TRANSPORTADORA TURISTICA BENFICA S.A | D16: 18000 | F16: =D16-E16+F15 -> 2493032.1
A17: 45022 | B17: Gestão de caixa | E17: =(D16*0.005)+10 -> 100 | F17: =D17-E17+F16 -> 2492932.1
A18: 45022 | B18: Crédito em conta | C18: BY BUS TRANSPORTES LTDA | D18: 22483.31 | F18: =D18-E18+F17 -> 2515415.4
A19: 45022 | B19: Gestão de caixa | E19: =(D18*0.005)+10 -> 122.41655 | F19: =D19-E19+F18 -> 2515293
A20: 45026 | B20: Crédito em conta | C20: PATRIMONY ADMINISTRADORA DE BENS AS | D20: 180030.83 | F20: =D20-E20+F19 -> 2695323.8
A21: 45026 | B21: Gestão de caixa | E21: =(D20*0.005)+10 -> 910.15415 | F21: =D21-E21+F20 -> 2694413.6
A22: 45026 | B22: Crédito em conta | C22: AGROCANA A N H LTDA. | D22: 26000 | F22: =D22-E22+F21 -> 2720413.6
A23: 45026 | B23: Gestão de caixa | E23: =(D22*0.005)+10 -> 140 | F23: =D23-E23+F22 -> 2720273.6
A24: 45026 | B24: Crédito em conta | C24: GUARIROBA BIOENERGIA LTDA | D24: 133564.29 | F24: =D24-E24+F23 -> 2853837.9
A25: 45026 | B25: Gestão de caixa | E25: =(D24*0.005)+10 -> 677.82145 | F25: =D25-E25+F24 -> 2853160.1
A26: 45026 | B26: Crédito em conta | C26: OUROESTE BIOENERGIA LTDA | D26: 20411.96 | F26: =D26-E26+F25 -> 2873572.1
A27: 45026 | B27: Gestão de caixa | E27: =(D26*0.005)+10 -> 112.0598 | F27: =D27-E27+F26 -> 2873460
A28: 45026 | B28: Transferência entre contas | C28: TRANSPORTADORA TURISTICA BENFICA S.A | E28: 123500 | F28: =D28-E28+F27 -> 2749960
A29: 45026 | B29: Crédito em conta | C29: MOEMA BIOENERGIA S A | D29: 262470.43 | F29: =D29-E29+F28 -> 3012430.4
A30: 45026 | B30: Gestão de caixa | E30: =(D29*0.005)+10 -> 1322.3521 | F30: =D30-E30+F29 -> 3011108.1
A31: 45026 | B31: Crédito em conta | C31: RENATO HAAG DA SILVA | D31: 85357.03 | F31: =D31-E31+F30 -> 3096465.1
A32: 45026 | B32: Gestão de caixa | E32: =(D31*0.005)+10 -> 436.78515 | F32: =D32-E32+F31 -> 3096028.3
A33: 45028 | B33: Crédito em conta | C33: TRANSPORTADORA TURISTICA BENFICA AS | D33: 18000 | F33: =D33-E33+F32 -> 3114028.3
A34: 45028 | B34: Gestão de caixa | E34: =(D33*0.005)+10 -> 100 | F34: =D34-E34+F33 -> 3113928.3
A35: 45028 | B35: Crédito em conta | C35: SANCETUR - SANTA CECILIA TURISMO LTDA | D35: 18000 | F35: =D35-E35+F34 -> 3131928.3
A36: 45028 | B36: Gestão de caixa | E36: =(D35*0.005)+10 -> 100 | F36: =D36-E36+F35 -> 3131828.3
A37: 45028 | B37: Crédito em conta | C37: ARENA FUTIBA LTDA | D37: 27000 | F37: =D37-E37+F36 -> 3158828.3
A38: 45028 | B38: Gestão de caixa | E38: =(D37*0.005)+10 -> 145 | F38: =D38-E38+F37 -> 3158683.3
A39: 45033 | B39: Transferência entre contas | C39: TRANSPORTADORA TURISTICA BENFICA S.A | E39: 67000 | F39: =D39-E39+F38 -> 3091683.3
A40: 45033 | B40: Transferência entre contas | C40: TRANSPORTADORA TURISTICA BENFICA S.A | E40: 12000 | F40: =D40-E40+F39 -> 3079683.3
A41: 45033 | B41: Crédito em conta | C41: BY BUS TRANSPORTES LTDA | D41: 17100 | F41: =D41-E41+F40 -> 3096783.3
A42: 45033 | B42: Gestão de caixa | E42: =(D41*0.005)+10 -> 95.5 | F42: =D42-E42+F41 -> 3096687.8
A43: 45034 | B43: Transferência entre contas | C43: TRANSPORTADORA TURISTICA BENFICA S.A | E43: 9000 | F43: =D43-E43+F42 -> 3087687.8
A44: 45034 | B44: Transferência entre contas | C44: TRANSPORTADORA TURISTICA BENFICA S.A | E44: 3000 | F44: =D44-E44+F43 -> 3084687.8
A45: 45035 | B45: Transferência entre contas | C45: TRANSPORTADORA TURISTICA BENFICA S.A | E45: 15000 | F45: =D45-E45+F44 -> 3069687.8
A46: 45035 | B46: Transferência entre contas | C46: TRANSPORTADORA TURISTICA BENFICA S.A | E46: 50000 | F46: =D46-E46+F45 -> 3019687.8
A47: 45036 | B47: Transferência entre contas | C47: TRANSPORTADORA TURISTICA BENFICA S.A | E47: 80000 | F47: =D47-E47+F46 -> 2939687.8
A48: 45036 | B48: Transferência entre contas | C48: TRANSPORTADORA TURISTICA BENFICA S.A | E48: 45000 | F48: =D48-E48+F47 -> 2894687.8
A49: 45036 | B49: Crédito em conta | C49: MENDES FERREIRA AGRICOLA LTDA | D49: 16000 | F49: =D49-E49+F48 -> 2910687.8
A50: 45036 | B50: Gestão de caixa | E50: =(D49*0.005)+10 -> 90 | F50: =D50-E50+F49 -> 2910597.8
A51: 45036 | B51: Crédito em conta | C51: JOSE APARICIO ALVES DA SILVA | D51: 8000 | F51: =D51-E51+F50 -> 2918597.8
A52: 45036 | B52: Gestão de caixa | E52: =(D51*0.005)+10 -> 50 | F52: =D52-E52+F51 -> 2918547.8
A53: 45040 | B53: Transferência entre contas | C53: TRANSPORTADORA TURISTICA BENFICA S.A | E53: 2000 | F53: =D53-E53+F52 -> 2916547.8
A54: 45041 | B54: Crédito em conta | C54: TRANSPORTADORA TURISTICA BENFICA AS | D54: 28125 | F54: =D54-E54+F53 -> 2944672.8
A55: 45041 | B55: Gestão de caixa | E55: =(D54*0.005)+10 -> 150.625 | F55: =D55-E55+F54 -> 2944522.2
A56: 45041 | B56: Transferência entre contas | C56: TRANSPORTADORA TURISTICA BENFICA S.A | E56: 60000 | F56: =D56-E56+F55 -> 2884522.2
A57: 45042 | B57: Crédito em conta | C57: BENFICA CARGAS E LOGISTICA S.A | D57: 25500 | F57: =D57-E57+F56 -> 2910022.2
A58: 45042 | B58: Gestão de caixa | E58: =(D57*0.005)+10 -> 137.5 | F58: =D58-E58+F57 -> 2909884.7
A59: 45043 | B59: Transferência entre contas | C59: TRANSPORTADORA TURISTICA BENFICA S.A | E59: 38000 | F59: =D59-E59+F58 -> 2871884.7
A60: 45044 | B60: Transferência entre contas | C60: TRANSPORTADORA TURISTICA BENFICA S.A | E60: 104000 | F60: =D60-E60+F59 -> 2767884.7
A61: 45044 | B61: Crédito em conta | C61: TRANSPORTADORA TURISTICA BENFICA AS | D61: 9361.62 | F61: =D61-E61+F60 -> 2777246.3
A62: 45044 | B62: Gestão de caixa | E62: =(D61*0.005)+10 -> 56.8081 | F62: =D62-E62+F61 -> 2777189.5
A63: 45044 | B63: Ajuste de Saldo | E63: 0.01 | F63: =D63-E63+F62 -> 2777189.5
F64: =D64-E64+F63 -> 2777189.5
F65: =D65-E65+F64 -> 2777189.5
F66: =D66-E66+F65 -> 2777189.5
F67: =D67-E67+F66 -> 2777189.5
F68: =D68-E68+F67 -> 2777189.5
F69: =D69-E69+F68 -> 2777189.5
F70: =D70-E70+F69 -> 2777189.5
F71: =D71-E71+F70 -> 2777189.5
F72: =D72-E72+F71 -> 2777189.5
F73: =D73-E73+F72 -> 2777189.5
F74: =D74-E74+F73 -> 2777189.5
F75: =D75-E75+F74 -> 2777189.5
... F609: =D609-E609+F608 -> 2777189.5

Sheet Maio2023
A2: EXTRATO DE MOVIMENTAÇÃO
A4: Banco | B4: LEPTA BANK (274) | C4: Agência | D4: 1 | E4: Conta | F4: 08198095-5
A5: Empresa | B5: TRANSP. TURISTICA BENFICA S.A | C5: Saldo Anterior | D5: =Abril2023!F6 -> 2777189.5 | F5: Saldo Disponível
A6: CNPJ | B6: 59.275.289/0001-02 | C6: Totais (Entradas/Saídas) | D6: =SUM(D9:D609) -> 2312808.2 | E6: =SUM(E9:E609) -> 1154434 | F6: =F609 -> 3935563.7
A8: Data | B8: Histórico | C8: Complemento | D8: Créditos | E8: Débitos | F8: Saldo
A9: 45048 | B9: Transferência entre contas | C9: TRANSPORTADORA TURISTICA BENFICA S.A | E9: 35000 | F9: =D9-E9+D5 -> 2742189.5
A10: 45048 | B10: Crédito em conta | C10: TRANSPORTADORA TUR BENFICA S A | D10: 20947.55 | F10: =D10-E10+F9 -> 2763137
A11: 45048 | B11: Gestão de caixa | E11: =(D10*0.005)+10 -> 114.73775 | F11: =D11-E11+F10 -> 2763022.3
A12: 45048 | B12: Crédito em conta | C12: PERFICE DO BRASIL SERVICOS DE | D12: 20430 | F12: =D12-E12+F11 -> 2783452.3
A13: 45048 | B13: Gestão de caixa | E13: =(D12*0.005)+10 -> 112.15 | F13: =D13-E13+F12 -> 2783340.2
A14: 45049 | B14: Tarifa de manutenção de conta | C14: TRANSPORTADORA TURISTICA BENFICA S.A - (Vinculada) | E14: 1500 | F14: =D14-E14+F13 -> 2781840.2
A15: 45049 | B15: Tarifa de manutenção de conta | C15: TED's, PIX e demais | E15: 300 | F15: =D15-E15+F14 -> 2781540.2
A16: 45049 | B16: Transferência entre contas | C16: TRANSPORTADORA TURISTICA BENFICA S.A | E16: 10500 | F16: =D16-E16+F15 -> 2771040.2
A17: 45050 | B17: Crédito em conta | C17: BENFICA CARGAS E LOGISTICA S.A | D17: 32000 | F17: =D17-E17+F16 -> 2803040.2
A18: 45050 | B18: Gestão de caixa | E18: =(D17*0.005)+10 -> 170 | F18: =D18-E18+F17 -> 2802870.2
A19: 45050 | B19: Crédito em conta | C19: TRANSPORTADORA TURISTICA BENFICA S.A | D19: 59000 | F19: =D19-E19+F18 -> 2861870.2
A20: 45050 | B20: Gestão de caixa | E20: =(D19*0.005)+10 -> 305 | F20: =D20-E20+F19 -> 2861565.2
A21: 45050 | B21: Crédito em conta | C21: MIGUEL ARAUJO GIMENEZ | D21: 30000 | F21: =D21-E21+F20 -> 2891565.2
A22: 45050 | B22: Gestão de caixa | E22: =(D21*0.005)+10 -> 160 | F22: =D22-E22+F21 -> 2891405.2
A23: 45051 | B23: Crédito em conta | C23: BB TRANSPORTE E TURISMO LTDA | D23: 90000 | F23: =D23-E23+F22 -> 2981405.2
A24: 45051 | B24: Gestão de caixa | E24: =(D23*0.005)+10 -> 460 | F24: =D24-E24+F23 -> 2980945.2
A25: 45051 | B25: Transferência entre contas | C25: TRANSPORTADORA TURISTICA BENFICA S.A | E25: 228500 | F25: =D25-E25+F24 -> 2752445.2
A26: 45051 | B26: Transferência entre contas | C26: TRANSPORTADORA TURISTICA BENFICA S.A | E26: 82000 | F26: =D26-E26+F25 -> 2670445.2
A27: 45051 | B27: Crédito em conta | C27: MIGUEL ARAUJO GIMENEZ | D27: 6000 | F27: =D27-E27+F26 -> 2676445.2
A28: 45051 | B28: Gestão de caixa | E28: =(D27*0.005)+10 -> 40 | F28: =D28-E28+F27 -> 2676405.2
A29: 45054 | B29: Transferência entre contas | C29: TRANSPORTADORA TURISTICA BENFICA S.A | E29: 65000 | F29: =D29-E29+F28 -> 2611405.2
A30: 45054 | B30: Tarifa de manutenção de conta | C30: TRANSPORTADORA TURISTICA BENFICA S.A - (Empresa) | E30: 1500 | F30: =D30-E30+F29 -> 2609905.2
A31: 45054 | B31: Crédito em conta | C31: PATRIMONY ADMINISTRADORA DE BENS AS | D31: 1180030.8 | F31: =D31-E31+F30 -> 3789936
A32: 45054 | B32: Gestão de caixa | E32: =(D31*0.005)+10 -> 5910.1542 | F32: =D32-E32+F31 -> 3784025.8
A33: 45055 | B33: Crédito em conta | C33: BY BUS TRANSPORTES LTDA | D33: 22483.31 | F33: =D33-E33+F32 -> 3806509.1
A34: 45055 | B34: Gestão de caixa | E34: =(D33*0.005)+10 -> 122.41655 | F34: =D34-E34+F33 -> 3806386.7
A35: 45055 | B35: Ajuste de Saldo | D35: 0.01 | F35: =D35-E35+F34 -> 3806386.7
A36: 45055 | B36: Transferência entre contas | C36: TRANSPORTADORA TURISTICA BENFICA S.A | E36: 39000 | F36: =D36-E36+F35 -> 3767386.7
A37: 45055 | B37: Crédito em conta | C37: OUROESTE BIOENERGIA LTDA | D37: 19946.43 | F37: =D37-E37+F36 -> 3787333.2
A38: 45055 | B38: Gestão de caixa | E38: =(D37*0.005)+10 -> 109.73215 | F38: =D38-E38+F37 -> 3787223.4
A39: 45055 | B39: Crédito em conta | C39: GUARIROBA BIOENERGIA LTDA | D39: 161546.23 | F39: =D39-E39+F38 -> 3948769.7
A40: 45055 | B40: Gestão de caixa | E40: =(D39*0.005)+10 -> 817.73115 | F40: =D40-E40+F39 -> 3947951.9
A41: 45055 | B41: Crédito em conta | C41: MOEMA BIOENERGIA S A | D41: 317084.51 | F41: =D41-E41+F40 -> 4265036.4
A42: 45055 | B42: Gestão de caixa | E42: =(D41*0.005)+10 -> 1595.4226 | F42: =D42-E42+F41 -> 4263441
A43: 45055 | B43: Crédito em conta | C43: AGROCANA A N H LTDA | D43: 26000 | F43: =D43-E43+F42 -> 4289441
A44: 45055 | B44: Gestão de caixa | E44: =(D43*0.005)+10 -> 140 | F44: =D44-E44+F43 -> 4289301
A45: 45056 | B45: Transferência entre contas | C45: TRANSPORTADORA TURISTICA BENFICA S.A | E45: 81000 | F45: =D45-E45+F44 -> 4208301
A46: 45056 | B46: Transferência entre contas | C46: TRANSPORTADORA TURISTICA BENFICA S.A | E46: 1500 | F46: =D46-E46+F45 -> 4206801
A47: 45056 | B47: Crédito em conta | C47: SANCETUR - SANTA CECILIA TURISMO LTDA | D47: 18000 | F47: =D47-E47+F46 -> 4224801
A48: 45056 | B48: Gestão de caixa | E48: =(D47*0.005)+10 -> 100 | F48: =D48-E48+F47 -> 4224701
A49: 45057 | B49: Crédito em conta | C49: SILVA & BEGHINI COMERCIO DE ONIBUS LTDA | D49: 6500 | F49: =D49-E49+F48 -> 4231201
A50: 45057 | B50: Gestão de caixa | E50: =(D49*0.005)+10 -> 42.5 | F50: =D50-E50+F49 -> 4231158.5
A51: 45058 | B51: Transferência entre contas | C51: TRANSPORTADORA TURISTICA BENFICA S.A | E51: 18000 | F51: =D51-E51+F50 -> 4213158.5
A52: 45058 | B52: Transferência entre contas | C52: TRANSPORTADORA TURISTICA BENFICA S.A | E52: 1000 | F52: =D52-E52+F51 -> 4212158.5
A53: 45061 | B53: Transferência entre contas | C53: TRANSPORTADORA TURISTICA BENFICA S.A | E53: 93000 | F53: =D53-E53+F52 -> 4119158.5
A54: 45064 | B54: Transferência entre contas | C54: TRANSPORTADORA TURISTICA BENFICA S.A | E54: 131500 | F54: =D54-E54+F53 -> 3987658.5
A55: 45065 | B55: Crédito em conta | C55: ARD TRANSPORTES LTDA | D55: 9000 | F55: =D55-E55+F54 -> 3996658.5
A56: 45065 | B56: Gestão de caixa | E56: =(D55*0.005)+10 -> 55 | F56: =D56-E56+F55 -> 3996603.5
A57: 45065 | B57: Transferência entre contas | C57: TRANSPORTADORA TURISTICA BENFICA S.A | E57: 61000 | F57: =D57-E57+F56 -> 3935603.5
A58: 45068 | B58: Transferência entre contas | C58: TRANSPORTADORA TURISTICA BENFICA S.A | E58: 34000 | F58: =D58-E58+F57 -> 3901603.5
A59: 45069 | B59: Crédito em conta | C59: MENDES FERREIRA AGRICOLA LTDA | D59: 8000 | F59: =D59-E59+F58 -> 3909603.5
A60: 45069 | B60: Gestão de caixa | E60: =(D59*0.005)+10 -> 50 | F60: =D60-E60+F59 -> 3909553.5
A61: 45069 | B61: Transferência entre contas | C61: TRANSPORTADORA TURISTICA BENFICA S.A | E61: 21000 | F61: =D61-E61+F60 -> 3888553.5
A62: 45069 | B62: Crédito em conta | C62: DORIS ELENA USLENGHI NEVES DE MEJIA | D62: 337.41 | F62: =D62-E62+F61 -> 3888890.9
A63: 45069 | B63: Gestão de caixa | E63: =(D62*0.005)+10 -> 11.68705 | F63: =D63-E63+F62 -> 3888879.2
A64: 45069 | B64: Crédito em conta | C64: DORIS ELENA USLENGHI NEVES DE MEJIA | D64: 5644.67 | F64: =D64-E64+F63 -> 3894523.9
A65: 45069 | B65: Gestão de caixa | E65: =(D64*0.005)+10 -> 38.22335 | F65: =D65-E65+F64 -> 3894485.7
A66: 45070 | B66: Transferência entre contas | C66: TRANSPORTADORA TURISTICA BENFICA S.A | E66: 23000 | F66: =D66-E66+F65 -> 3871485.7
A67: 45071 | B67: Transferência entre contas | C67: TRANSPORTADORA TURISTICA BENFICA S.A | E67: 51000 | F67: =D67-E67+F66 -> 3820485.7
A68: 45072 | B68: Transferência entre contas | C68: TRANSPORTADORA TURISTICA BENFICA S.A | E68: 3000 | F68: =D68-E68+F67 -> 3817485.7
A69: 45072 | B69: Crédito em conta | C69: MENDES FERREIRA AGRICOLA LTDA | D69: 2666 | F69: =D69-E69+F68 -> 3820151.7
A70: 45072 | B70: Gestão de caixa | E70: =(D69*0.005)+10 -> 23.33 | F70: =D70-E70+F69 -> 3820128.4
A71: 45075 | B71: Crédito em conta | C71: TRANSPORTADORA TURISTICA BENFICA AS | D71: 9300 | F71: =D71-E71+F70 -> 3829428.4
A72: 45075 | B72: Gestão de caixa | E72: =(D71*0.005)+10 -> 56.5 | F72: =D72-E72+F71 -> 3829371.9
A73: 45075 | B73: Transferência entre contas | C73: TRANSPORTADORA TURISTICA BENFICA S.A | E73: 11300 | F73: =D73-E73+F72 -> 3818071.9
A74: 45075 | B74: Crédito em conta | C74: SOFIA TRANSPORTES E LOCADORA LTDA | D74: 145000 | F74: =D74-E74+F73 -> 3963071.9
A75: 45075 | B75: Gestão de caixa | E75: =(D74*0.005)+10 -> 735 | F75: =D75-E75+F74 -> 3962336.9
A76: 45075 | B76: Crédito em conta | C76: ARD TRANSPORTES LTDA | D76: 9000 | F76: =D76-E76+F75 -> 3971336.9
A77: 45075 | B77: Gestão de caixa | E77: =(D76*0.005)+10 -> 55 | F77: =D77-E77+F76 -> 3971281.9
A78: 45076 | B78: Transferência entre contas | C78: TRANSPORTADORA TURISTICA BENFICA S.A | E78: 39000 | F78: =D78-E78+F77 -> 3932281.9
A79: 45076 | B79: Crédito em conta | C79: BENFICA CARGAS E LOGISTICA S.A | D79: 20000 | F79: =D79-E79+F78 -> 3952281.9
A80: 45076 | B80: Gestão de caixa | E80: =(D79*0.005)+10 -> 110 | F80: =D80-E80+F79 -> 3952171.9
A81: 45077 | B81: Crédito em conta | C81: TRANSPORTADORA TUR BENFICA S A | D81: 22756.28 | F81: =D81-E81+F80 -> 3974928.1
A82: 45077 | B82: Gestão de caixa | E82: =(D81*0.005)+10 -> 123.7814 | F82: =D82-E82+F81 -> 3974804.4
A83: 45077 | B83: Transferência entre contas | C83: TRANSPORTADORA TURISTICA BENFICA S.A | E83: 91000 | F83: =D83-E83+F82 -> 3883804.4
A84: 45077 | B84: Transferência entre contas | C84: TRANSPORTADORA TURISTICA BENFICA S.A | E84: 19000 | F84: =D84-E84+F83 -> 3864804.4
A85: 45077 | B85: Crédito em conta | C85: BENFICA CARGAS E LOGISTICA S.A | D85: 33000 | F85: =D85-E85+F84 -> 3897804.4
A86: 45077 | B86: Gestão de caixa | E86: =(D85*0.005)+10 -> 175 | F86: =D86-E86+F85 -> 3897629.4
A87: 45077 | B87: Crédito em conta | C87: PERFICE DO BRASIL SERVICOS DE | D87: 38135 | F87: =D87-E87+F86 -> 3935764.4
A88: 45077 | B88: Gestão de caixa | E88: =(D87*0.005)+10 -> 200.675 | F88: =D88-E88+F87 -> 3935563.7
F89: =D89-E89+F88 -> 3935563.7
F90: =D90-E90+F89 -> 3935563.7
F91: =D91-E91+F90 -> 3935563.7
F92: =D92-E92+F91 -> 3935563.7
F93: =D93-E93+F92 -> 3935563.7
F94: =D94-E94+F93 -> 3935563.7
F95: =D95-E95+F94 -> 3935563.7
F96: =D96-E96+F95 -> 3935563.7
F97: =D97-E97+F96 -> 3935563.7
F98: =D98-E98+F97 -> 3935563.7
F99: =D99-E99+F98 -> 3935563.7
F100: =D100-E100+F99 -> 3935563.7
... F609: =D609-E609+F608 -> 3935563.7

Sheet Junho2023
A2: EXTRATO DE MOVIMENTAÇÃO
A4: Banco | B4: LEPTA BANK (274) | C4: Agência | D4: 1 | E4: Conta | F4: 08198095-5
A5: Empresa | B5: TRANSP. TURISTICA BENFICA S.A | C5: Saldo Anterior | D5: =Maio2023!F6 -> 3935563.7 | F5: Saldo Disponível
A6: CNPJ | B6: 59.275.289/0001-02 | C6: Totais (Entradas/Saídas) | D6: =SUM(D9:D609) -> 1473498 | E6: =SUM(E9:E609) -> 1097197.5 | F6: =F609 -> 4311864.2
A8: Data | B8: Histórico | C8: Complemento | D8: Créditos | E8: Débitos | F8: Saldo
A9: 45078 | B9: Transferência entre contas | C9: TRANSPORTADORA TURISTICA BENFICA S.A | E9: 37000 | F9: =D9-E9+D5 -> 3898563.7
A10: 45078 | B10: Transferência entre contas | C10: TRANSPORTADORA TURISTICA BENFICA S.A | E10: 8000 | F10: =D10-E10+F9 -> 3890563.7
A11: 45080 | B11: Tarifa de manutenção de conta | C11: TRANSPORTADORA TURISTICA BENFICA S.A - (Vinculada) | E11: 1500 | F11: =D11-E11+F10 -> 3889063.7
A12: 45080 | B12: Tarifa de manutenção da conta | C12: TED's, PIX e demais | E12: 440 | F12: =D12-E12+F11 -> 3888623.7
A13: 45082 | B13: Crédito em conta | C13: BB TRANSPORTE E TURISMO LTDA | D13: 90000 | F13: =D13-E13+F12 -> 3978623.7
A14: 45082 | B14: Gestão de caixa | E14: =(D13*0.005)+10 -> 460 | F14: =D14-E14+F13 -> 3978163.7
A15: 45082 | B15: Transferência entre contas | C15: TRANSPORTADORA TURISTICA BENFICA S.A | E15: 132000 | F15: =D15-E15+F14 -> 3846163.7
A16: 45083 | B16: Transferência entre contas | C16: TRANSPORTADORA TURISTICA BENFICA S.A | E16: 37000 | F16: =D16-E16+F15 -> 3809163.7
A17: 45083 | B17: Transferência entre contas | C17: TRANSPORTADORA TURISTICA BENFICA S.A | E17: 87000 | F17: =D17-E17+F16 -> 3722163.7
A18: 45083 | B18: Crédito em conta | C18: ROGERIO SOARES MARQUES | D18: 4000 | F18: =D18-E18+F17 -> 3726163.7
A19: 45083 | B19: Gestão de caixa | E19: =(D18*0.005)+10 -> 30 | F19: =D19-E19+F18 -> 3726133.7
A20: 45084 | B20: Transferência entre contas | C20: TRANSPORTADORA TURISTICA BENFICA S.A | E20: 64000 | F20: =D20-E20+F19 -> 3662133.7
A21: 45084 | B21: Tarifa de manutenção de conta | C21: TRANSPORTADORA TURISTICA BENFICA S.A - (Empresa) | E21: 1500 | F21: =D21-E21+F20 -> 3660633.7
A22: 45086 | B22: Crédito em conta | C22: PATRIMONY ADMINISTRADORA DE BENS AS | D22: 152544 | F22: =D22-E22+F21 -> 3813177.7
A23: 45086 | B23: Gestão de caixa | E23: =(D22*0.005)+10 -> 772.72 | F23: =D23-E23+F22 -> 3812405
A24: 45086 | B24: Crédito em conta | C24: OUROESTE BIOENERGIA LTDA | D24: 21478.61 | F24: =D24-E24+F23 -> 3833883.6
A25: 45086 | B25: Gestão de caixa | E25: =(D24*0.005)+10 -> 117.39305 | F25: =D25-E25+F24 -> 3833766.2
A26: 45086 | B26: Crédito em conta | C26: MOEMA BIOENERGIA S A | D26: 332407.53 | F26: =D26-E26+F25 -> 4166173.7
A27: 45086 | B27: Gestão de caixa | E27: =(D26*0.005)+10 -> 1672.0377 | F27: =D27-E27+F26 -> 4164501.7
A28: 45086 | B28: Crédito em conta | C28: GUARIROBA BIOENERGIA LTDA | D28: 183280.34 | F28: =D28-E28+F27 -> 4347782
A29: 45086 | B29: Gestão de caixa | E29: =(D28*0.005)+10 -> 926.4017 | F29: =D29-E29+F28 -> 4346855.6
A30: 45089 | B30: Transferência entre contas | C30: TRANSPORTADORA TURISTICA BENFICA S.A | E30: 120000 | F30: =D30-E30+F29 -> 4226855.6
A31: 45089 | B31: Crédito em conta | C31: SANCETUR - SANTA CECILIA TURISMO LTDA | D31: 18000 | F31: =D31-E31+F30 -> 4244855.6
A32: 45089 | B32: Gestão de caixa | E32: =(D31*0.005)+10 -> 100 | F32: =D32-E32+F31 -> 4244755.6
A33: 45090 | B33: Transferência entre contas | C33: TRANSPORTADORA TURISTICA BENFICA S.A | E33: 2000 | F33: =D33-E33+F32 -> 4242755.6
A34: 45090 | B34: Transferência entre contas | C34: TRANSPORTADORA TURISTICA BENFICA S.A | E34: 1200 | F34: =D34-E34+F33 -> 4241555.6
A35: 45092 | B35: Transferência entre contas | C35: TRANSPORTADORA TURISTICA BENFICA S.A | E35: 95000 | F35: =D35-E35+F34 -> 4146555.6
A36: 45092 | B36: Crédito em conta | C36: TRANSPORTADORA TURISTICA BENFICA S.A | D36: 16030 | F36: =D36-E36+F35 -> 4162585.6
A37: 45092 | B37: Gestão de caixa | E37: =(D36*0.005)+10 -> 90.15 | F37: =D37-E37+F36 -> 4162495.5
A38: 45093 | B38: Transferência entre contas | C38: TRANSPORTADORA TURISTICA BENFICA S.A | E38: 11000 | F38: =D38-E38+F37 -> 4151495.5
A39: 45093 | B39: Transferência entre contas | C39: TRANSPORTADORA TURISTICA BENFICA S.A | E39: 3000 | F39: =D39-E39+F38 -> 4148495.5
A40: 45093 | B40: Crédito em conta | C40: SILVA & BEGHINI COMERCIO DE ONIBUS LTDA | D40: 13000 | F40: =D40-E40+F39 -> 4161495.5
A41: 45093 | B41: Gestão de caixa | E41: =(D40*0.005)+10 -> 75 | F41: =D41-E41+F40 -> 4161420.5
A42: 45096 | B42: Crédito em conta | C42: UNIVERSAL TURISMO LTDA-EPP | D42: 18000 | F42: =D42-E42+F41 -> 4179420.5
A43: 45096 | B43: Gestão de caixa | E43: =(D42*0.005)+10 -> 100 | F43: =D43-E43+F42 -> 4179320.5
A44: 45096 | B44: Crédito em conta | C44: EURIPEDES VERALDI | D44: 4959.99 | F44: =D44-E44+F43 -> 4184280.5
A45: 45096 | B45: Gestão de caixa | E45: =(D44*0.005)+10 -> 34.79995 | F45: =D45-E45+F44 -> 4184245.7
A46: 45096 | B46: Transferência entre contas | C46: TRANSPORTADORA TURISTICA BENFICA S.A | E46: 144000 | F46: =D46-E46+F45 -> 4040245.7
A47: 45097 | B47: Transferência entre contas | C47: TRANSPORTADORA TURISTICA BENFICA S.A | E47: 76000 | F47: =D47-E47+F46 -> 3964245.7
A48: 45098 | B48: Crédito em conta | C48: AGROCANA A N H LTDA | D48: 27200 | F48: =D48-E48+F47 -> 3991445.7
A49: 45098 | B49: Gestão de caixa | E49: =(D48*0.005)+10 -> 146 | F49: =D49-E49+F48 -> 3991299.7
A50: 45100 | B50: Crédito em conta | C50: REGINALDO DA SILVA ALVES | D50: 132405 | F50: =D50-E50+F49 -> 4123704.7
A51: 45100 | B51: Gestão de caixa | E51: =(D50*0.005)+10 -> 672.025 | F51: =D51-E51+F50 -> 4123032.6
A52: 45100 | B52: Transferência entre contas | C52: TRANSPORTADORA TURISTICA BENFICA S.A | E52: 30000 | F52: =D52-E52+F51 -> 4093032.6
A53: 45100 | B53: Crédito em conta | C53: WAGUINHO & NEY TRANSPORTE E LOCADORA DE VEICULOS L | D53: 100000 | F53: =D53-E53+F52 -> 4193032.6
A54: 45100 | B54: Gestão de caixa | E54: =(D53*0.005)+10 -> 510 | F54: =D54-E54+F53 -> 4192522.6
A55: 45100 | B55: Transferência entre contas | C55: TRANSPORTADORA TURISTICA BENFICA S.A | E55: 11000 | F55: =D55-E55+F54 -> 4181522.6
A56: 45100 | B56: Crédito em conta | C56: WAGUINHO & NEY TRANSPORTE E LOCADORA DE VEICULOS L | D56: 20000 | F56: =D56-E56+F55 -> 4201522.6
A57: 45100 | B57: Gestão de caixa | E57: =(D56*0.005)+10 -> 110 | F57: =D57-E57+F56 -> 4201412.6
A58: 45103 | B58: Crédito em conta | C58: WAGUINHO N T L V LTDA | D58: 10000 | F58: =D58-E58+F57 -> 4211412.6
A59: 45103 | B59: Gestão de caixa | E59: =(D58*0.005)+10 -> 60 | F59: =D59-E59+F58 -> 4211352.6
A60: 45103 | B60: Transferência entre contas | C60: TRANSPORTADORA TURISTICA BENFICA S.A | E60: 30000 | F60: =D60-E60+F59 -> 4181352.6
A61: 45103 | B61: Transferência entre contas | C61: TRANSPORTADORA TURISTICA BENFICA S.A | E61: 41000 | F61: =D61-E61+F60 -> 4140352.6
A62: 45103 | B62: Ajuste de Saldo | E62: 0.01 | F62: =D62-E62+F61 -> 4140352.6
A63: 45104 | B63: Transferência entre contas | C63: TRANSPORTADORA TURISTICA BENFICA S.A | E63: 8000 | F63: =D63-E63+F62 -> 4132352.6
A64: 45106 | B64: Crédito em conta | C64: REGINALDO DA SILVA ALVES | D64: 158000 | F64: =D64-E64+F63 -> 4290352.6
A65: 45106 | B65: Gestão de caixa | E65: =(D64*0.005)+10 -> 800 | F65: =D65-E65+F64 -> 4289552.6
A66: 45106 | B66: Transferência entre contas | C66: TRANSPORTADORA TURISTICA BENFICA S.A | E66: 40000 | F66: =D66-E66+F65 -> 4249552.6
A67: 45106 | B67: Transferência entre contas | C67: TRANSPORTADORA TURISTICA BENFICA S.A | E67: 8000 | F67: =D67-E67+F66 -> 4241552.6
A68: 45107 | B68: Crédito em conta | C68: REGINALDO DA SILVA ALVES | D68: 150945 | F68: =D68-E68+F67 -> 4392497.6
A69: 45107 | B69: Gestão de caixa | E69: =(D68*0.005)+10 -> 764.725 | F69: =D69-E69+F68 -> 4391732.9
A70: 45107 | B70: Transferência entre contas | C70: TRANSPORTADORA TURISTICA BENFICA S.A | E70: 101000 | F70: =D70-E70+F69 -> 4290732.9
A71: 45107 | B71: Crédito em conta | C71: TRANSPORTADORA TUR BENFICA S A | D71: 21247.55 | F71: =D71-E71+F70 -> 4311980.4
A72: 45107 | B72: Gestão de caixa | E72: =(D71*0.005)+10 -> 116.23775 | F72: =D72-E72+F71 -> 4311864.2
F73: =D73-E73+F72 -> 4311864.2
F74: =D74-E74+F73 -> 4311864.2
F75: =D75-E75+F74 -> 4311864.2
F76: =D76-E76+F75 -> 4311864.2
F77: =D77-E77+F76 -> 4311864.2
F78: =D78-E78+F77 -> 4311864.2
F79: =D79-E79+F78 -> 4311864.2
F80: =D80-E80+F79 -> 4311864.2
F81: =D81-E81+F80 -> 4311864.2
F82: =D82-E82+F81 -> 4311864.2
F83: =D83-E83+F82 -> 4311864.2
F84: =D84-E84+F83 -> 4311864.2
... F609: =D609-E609+F608 -> 4311864.2

Sheet Julho2023
A2: EXTRATO DE MOVIMENTAÇÃO
A4: Banco | B4: LEPTA BANK (274) | C4: Agência | D4: 1 | E4: Conta | F4: 08198095-5
A5: Empresa | B5: TRANSP. TURISTICA BENFICA S.A | C5: Saldo Anterior | D5: =Junho2023!F6 -> 4311864.2 | F5: Saldo Disponível
A6: CNPJ | B6: 59.275.289/0001-02 | C6: Totais (Entradas/Saídas) | D6: =SUM(D9:D609) -> 1826393.8 | E6: =SUM(E9:E609) -> 2288162 | F6: =F609 -> 3850096
A8: Data | B8: Histórico | C8: Complemento | D8: Créditos | E8: Débitos | F8: Saldo
A9: 45110 | B9: Tarifa de manutenção de conta | C9: TRANSPORTADORA TURISTICA BENFICA S.A - (Vinculada) | E9: 1500 | F9: =D9-E9+D5 -> 4310364.2
A10: 45110 | B10: Tarifa de manutenção da conta | C10: TED's, PIX e demais | E10: 440 | F10: =D10-E10+F9 -> 4309924.2
A11: 45110 | B11: Ajuste de Saldo | D11: 0.01 | F11: =D11-E11+F10 -> 4309924.2
A12: 45110 | B12: Crédito em conta | C12: PERFICE DO BRASIL SERVICOS DE TRANSPORTE E LOGISTICA LTDA | D12: 33250 | F12: =D12-E12+F11 -> 4343174.2
A13: 45110 | B13: Gestão de caixa | E13: =(D12*0.005)+10 -> 176.25 | F13: =D13-E13+F12 -> 4342998
A14: 45110 | B14: Crédito em conta | C14: PERFICE DO BRASIL SERVICOS DE TRANSPORTE E LOGISTICA LTDA | D14: 38135 | F14: =D14-E14+F13 -> 4381133
A15: 45110 | B15: Gestão de caixa | E15: =(D14*0.005)+10 -> 200.675 | F15: =D15-E15+F14 -> 4380932.3
A16: 45110 | B16: Transferência entre contas | C16: TRANSPORTADORA TURISTICA BENFICA S.A | E16: 21000 | F16: =D16-E16+F15 -> 4359932.3
A17: 45111 | B17: Tarifa de manutenção de conta | C17: TRANSPORTADORA TURISTICA BENFICA S.A - (Empresa) | E17: 1500 | F17: =D17-E17+F16 -> 4358432.3
A18: 45111 | B18: Transferência entre contas | C18: TRANSPORTADORA TURISTICA BENFICA S.A | E18: 447860 | F18: =D18-E18+F17 -> 3910572.3
A19: 45111 | B19: Transferência entre contas | C19: TRANSPORTADORA TURISTICA BENFICA S.A | E19: 30000 | F19: =D19-E19+F18 -> 3880572.3
A20: 45111 | B20: Crédito em conta | C20: TRANSPORTADORA TURISTICA BENFICA S.A | D20: 80000 | F20: =D20-E20+F19 -> 3960572.3
A21: 45111 | B21: Gestão de caixa | E21: =(D20*0.005)+10 -> 410 | F21: =D21-E21+F20 -> 3960162.3
A22: 45112 | B22: Crédito em conta | C22: BB TRANSPORTE E TURISMO LTDA | D22: 90000 | F22: =D22-E22+F21 -> 4050162.3
A23: 45112 | B23: Gestão de caixa | E23: =(D22*0.005)+10 -> 460 | F23: =D23-E23+F22 -> 4049702.3
A24: 45112 | B24: Transferência entre contas | C24: TRANSPORTADORA TURISTICA BENFICA S.A | E24: 212000 | F24: =D24-E24+F23 -> 3837702.3
A25: 45112 | B25: Transferência entre contas | C25: TRANSPORTADORA TURISTICA BENFICA S.A | E25: 79000 | F25: =D25-E25+F24 -> 3758702.3
A26: 45112 | B26: Ajuste de Saldo | E26: 0.01 | F26: =D26-E26+F25 -> 3758702.3
A27: 45113 | B27: Crédito em conta | C27: TRANSPORTADORA TURISTICA BENFICA S.A | D27: 19000 | F27: =D27-E27+F26 -> 3777702.3
A28: 45113 | B28: Gestão de caixa | E28: =(D27*0.005)+10 -> 105 | F28: =D28-E28+F27 -> 3777597.3
A29: 45113 | B29: Transferência entre contas | C29: TRANSPORTADORA TURISTICA BENFICA S.A | E29: 338000 | F29: =D29-E29+F28 -> 3439597.3
A30: 45114 | B30: Crédito em conta | C30: ARENA FUTIBA LTDA | D30: 707.01 | F30: =D30-E30+F29 -> 3440304.3
A31: 45114 | B31: Gestão de caixa | E31: =(D30*0.005)+10 -> 13.53505 | F31: =D31-E31+F30 -> 3440290.8
A32: 45114 | B32: Transferência entre contas | C32: TRANSPORTADORA TURISTICA BENFICA S.A | E32: 45000 | F32: =D32-E32+F31 -> 3395290.8
A33: 45114 | B33: Transferência entre contas | C33: TRANSPORTADORA TURISTICA BENFICA S.A | E33: 2500 | F33: =D33-E33+F32 -> 3392790.8
A34: 45117 | B34: Crédito em conta | C34: PATRIMONY ADMINISTRADORA DE BENS AS | D34: 152544 | F34: =D34-E34+F33 -> 3545334.8
A35: 45117 | B35: Gestão de caixa | E35: =(D34*0.005)+10 -> 772.72 | F35: =D35-E35+F34 -> 3544562
A36: 45117 | B36: Transferência entre contas | C36: TRANSPORTADORA TURISTICA BENFICA S.A | E36: 131000 | F36: =D36-E36+F35 -> 3413562
A37: 45117 | B37: Transferência entre contas | C37: TRANSPORTADORA TURISTICA BENFICA S.A | E37: 4000 | F37: =D37-E37+F36 -> 3409562
A38: 45117 | B38: Crédito em conta | C38: SANCETUR - SANTA CECILIA TURISMO LTDA | D38: 18000 | F38: =D38-E38+F37 -> 3427562
A39: 45117 | B39: Gestão de caixa | E39: =(D38*0.005)+10 -> 100 | F39: =D39-E39+F38 -> 3427462
A40: 45118 | B40: Crédito em conta | C40: MENDES FERREIRA AGRICOLA LTDA | D40: 8000 | F40: =D40-E40+F39 -> 3435462
A41: 45118 | B41: Gestão de caixa | E41: =(D40*0.005)+10 -> 50 | F41: =D41-E41+F40 -> 3435412
A42: 45118 | B42: Crédito em conta | C42: GUARIROBA BIOENERGIA LTDA | D42: 198183.88 | F42: =D42-E42+F41 -> 3633595.9
A43: 45118 | B43: Gestão de caixa | E43: =(D42*0.005)+10 -> 1000.9194 | F43: =D43-E43+F42 -> 3632595
A44: 45118 | B44: Crédito em conta | C44: MOEMA BIOENERGIA S A | D44: 338183.98 | F44: =D44-E44+F43 -> 3970779
A45: 45118 | B45: Gestão de caixa | E45: =(D44*0.005)+10 -> 1700.9199 | F45: =D45-E45+F44 -> 3969078.1
A46: 45118 | B46: Crédito em conta | C46: OUROESTE BIOENERGIA LTDA | D46: 21566.42 | F46: =D46-E46+F45 -> 3990644.5
A47: 45118 | B47: Gestão de caixa | E47: =(D46*0.005)+10 -> 117.8321 | F47: =D47-E47+F46 -> 3990526.6
A48: 45120 | B48: Transferência entre contas | C48: TRANSPORTADORA TURISTICA BENFICA S.A | E48: 34000 | F48: =D48-E48+F47 -> 3956526.6
A49: 45121 | B49: Transferência entre contas | C49: TRANSPORTADORA TURISTICA BENFICA S.A | E49: 28000 | F49: =D49-E49+F48 -> 3928526.6
A50: 45124 | B50: Transferência entre contas | C50: TRANSPORTADORA TURISTICA BENFICA S.A | E50: 46000 | F50: =D50-E50+F49 -> 3882526.6
A51: 45124 | B51: Crédito em conta | C51: SCATENA AGENCIA DE VIAGENS E TURISMO EIRELI | D51: 28000 | F51: =D51-E51+F50 -> 3910526.6
A52: 45124 | B52: Gestão de caixa | E52: =(D51*0.005)+10 -> 150 | F52: =D52-E52+F51 -> 3910376.6
A53: 45125 | B53: Transferência entre contas | C53: TRANSPORTADORA TURISTICA BENFICA S.A | E53: 87000 | F53: =D53-E53+F52 -> 3823376.6
A54: 45126 | B54: Transferência entre contas | C54: TRANSPORTADORA TURISTICA BENFICA S.A | E54: 70000 | F54: =D54-E54+F53 -> 3753376.6
A55: 45126 | B55: Crédito em conta | C55: EURIPEDES VERALDI | D55: 17493.33 | F55: =D55-E55+F54 -> 3770870
A56: 45126 | B56: Gestão de caixa | E56: =(D55*0.005)+10 -> 97.46665 | F56: =D56-E56+F55 -> 3770772.5
A57: 45126 | B57: Crédito em conta | C57: AGROCANA A N H LTDA | D57: 24000 | F57: =D57-E57+F56 -> 3794772.5
A58: 45126 | B58: Gestão de caixa | E58: =(D57*0.005)+10 -> 130 | F58: =D58-E58+F57 -> 3794642.5
A59: 45127 | B59: Transferência entre contas | C59: TRANSPORTADORA TURISTICA BENFICA S.A | E59: 75000 | F59: =D59-E59+F58 -> 3719642.5
A60: 45127 | B60: Crédito em conta | C60: MARFIN COMERCIO E SERVICOS AUTOMOTIVOS LTDA | D60: 92000 | F60: =D60-E60+F59 -> 3811642.5
A61: 45127 | B61: Gestão de caixa | E61: =(D60*0.005)+10 -> 470 | F61: =D61-E61+F60 -> 3811172.5
A62: 45128 | B62: Transferência entre contas | C62: TRANSPORTADORA TURISTICA BENFICA S.A | E62: 24000 | F62: =D62-E62+F61 -> 3787172.5
A63: 45128 | B63: Ajuste de Saldo | E63: 0.01 | F63: =D63-E63+F62 -> 3787172.5
A64: 45128 | B64: Crédito em conta | C64: JOANA MARIA DA COSTA SILV | D64: 20000 | F64: =D64-E64+F63 -> 3807172.5
A65: 45128 | B65: Gestão de caixa | E65: =(D64*0.005)+10 -> 110 | F65: =D65-E65+F64 -> 3807062.5
A66: 45128 | B66: Crédito em conta | C66: REGINALDO DA SILVA ALVES | D66: 574750 | F66: =D66-E66+F65 -> 4381812.5
A67: 45128 | B67: Gestão de caixa | E67: =(D66*0.005)+10 -> 2883.75 | F67: =D67-E67+F66 -> 4378928.7
A68: 45131 | B68: Transferência entre contas | C68: TRANSPORTADORA TURISTICA BENFICA S.A | E68: 66000 | F68: =D68-E68+F67 -> 4312928.7
A69: 45131 | B69: Crédito em conta | C69: JOANA MARIA DA COSTA SILV | D69: 20000 | F69: =D69-E69+F68 -> 4332928.7
A70: 45131 | B70: Gestão de caixa | E70: =(D69*0.005)+10 -> 110 | F70: =D70-E70+F69 -> 4332818.7
A71: 45132 | B71: Transferência entre contas | C71: TRANSPORTADORA TURISTICA BENFICA S.A | E71: 67000 | F71: =D71-E71+F70 -> 4265818.7
A72: 45133 | B72: Transferência entre contas | C72: TRANSPORTADORA TURISTICA BENFICA S.A | E72: 11000 | F72: =D72-E72+F71 -> 4254818.7
A73: 45133 | B73: Crédito em conta | C73: REGINALDO DA SILVA ALVES | D73: 12100 | F73: =D73-E73+F72 -> 4266918.7
A74: 45133 | B74: Gestão de caixa | E74: =(D73*0.005)+10 -> 70.5 | F74: =D74-E74+F73 -> 4266848.2
A75: 45134 | B75: Crédito em conta | C75: LUIZ PAULO DIAS MACHADO | D75: 25000 | F75: =D75-E75+F74 -> 4291848.2
A76: 45134 | B76: Gestão de caixa | E76: =(D75*0.005)+10 -> 135 | F76: =D76-E76+F75 -> 4291713.2
A77: 45135 | B77: Crédito em conta | C77: JOCA PRESTACAO DE SERVICO | D77: 5480.15 | F77: =D77-E77+F76 -> 4297193.4
A78: 45135 | B78: Gestão de caixa | E78: =(D77*0.005)+10 -> 37.40075 | F78: =D78-E78+F77 -> 4297156
A79: 45135 | B79: Crédito em conta | C79: ARD TRANSPORTES LTDA | D79: 10000 | F79: =D79-E79+F78 -> 4307156
A80: 45135 | B80: Gestão de caixa | E80: =(D79*0.005)+10 -> 60 | F80: =D80-E80+F79 -> 4307096
A81: 45138 | B81: Transferência entre contas | C81: TRANSPORTADORA TURISTICA BENFICA S.A | E81: 457000 | F81: =D81-E81+F80 -> 3850096
F82: =D82-E82+F81 -> 3850096
F83: =D83-E83+F82 -> 3850096
F84: =D84-E84+F83 -> 3850096
F85: =D85-E85+F84 -> 3850096
F86: =D86-E86+F85 -> 3850096
F87: =D87-E87+F86 -> 3850096
F88: =D88-E88+F87 -> 3850096
F89: =D89-E89+F88 -> 3850096
F90: =D90-E90+F89 -> 3850096
F91: =D91-E91+F90 -> 3850096
F92: =D92-E92+F91 -> 3850096
F93: =D93-E93+F92 -> 3850096
... F609: =D609-E609+F608 -> 3850096

Sheet Agosto2023
A2: EXTRATO DE MOVIMENTAÇÃO
A4: Banco | B4: LEPTA BANK (274) | C4: Agência | D4: 1 | E4: Conta | F4: 08198095-5
A5: Empresa | B5: TRANSP. TURISTICA BENFICA S.A | C5: Saldo Anterior | D5: =Julho2023!F6 -> 3850096 | F5: Saldo Disponível
A6: CNPJ | B6: 59.275.289/0001-02 | C6: Totais (Entradas/Saídas) | D6: =SUM(D9:D609) -> 1309666.8 | E6: =SUM(E9:E609) -> 1169768.3 | F6: =F609 -> 3989994.5
A8: Data | B8: Histórico | C8: Complemento | D8: Créditos | E8: Débitos | F8: Saldo
A9: 45139 | B9: Transferência entre contas | C9: TRANSPORTADORA TURISTICA BENFICA S.A | E9: 25500 | F9: =D9-E9+D5 -> 3824596
A10: 45140 | B10: Crédito em conta | C10: TRANSPORTADORA TURISTICA BENFICA S.A | D10: 93000 | F10: =D10-E10+F9 -> 3917596
A11: 45140 | B11: Gestão de caixa | E11: =(D10*0.005)+10 -> 475 | F11: =D11-E11+F10 -> 3917121
A12: 45140 | B12: Crédito em conta | C12: TRANSPORTADORA TURISTICA BENFICA S.A | D12: 23747.85 | F12: =D12-E12+F11 -> 3940868.8
A13: 45140 | B13: Gestão de caixa | E13: =(D12*0.005)+10 -> 128.73925 | F13: =D13-E13+F12 -> 3940740.1
A14: 45141 | B14: Tarifa de manutenção de conta | C14: TRANSPORTADORA TURISTICA BENFICA S.A - (Vinculada) | E14: 1500 | F14: =D14-E14+F13 -> 3939240.1
A15: 45141 | B15: Tarifa de manutenção da conta | C15: TED's, PIX e demais | E15: 420 | F15: =D15-E15+F14 -> 3938820.1
A16: 45141 | B16: Transferência entre contas | C16: TRANSPORTADORA TURISTICA BENFICA S.A | E16: 19000 | F16: =D16-E16+F15 -> 3919820.1
A17: 45141 | B17: Transferência entre contas | C17: TRANSPORTADORA TURISTICA BENFICA S.A | E17: 176000 | F17: =D17-E17+F16 -> 3743820.1
A18: 45141 | B18: Transferência entre contas | C18: TRANSPORTADORA TURISTICA BENFICA S.A | E18: 3000 | F18: =D18-E18+F17 -> 3740820.1
A19: 45142 | B19: Tarifa de manutenção de conta | C19: TRANSPORTADORA TURISTICA BENFICA S.A - (Empresa) | E19: 1500 | F19: =D19-E19+F18 -> 3739320.1
A20: 45142 | B20: Transferência entre contas | C20: TRANSPORTADORA TURISTICA BENFICA S.A | E20: 22500 | F20: =D20-E20+F19 -> 3716820.1
A21: 45142 | B21: Transferência entre contas | C21: TRANSPORTADORA TURISTICA BENFICA S.A | E21: 63000 | F21: =D21-E21+F20 -> 3653820.1
A22: 45142 | B22: Transferência entre contas | C22: TRANSPORTADORA TURISTICA BENFICA S.A | E22: 2500 | F22: =D22-E22+F21 -> 3651320.1
A23: 45142 | B23: Crédito em conta | C23: ARENA FUTIBA | D23: 3707.01 | F23: =D23-E23+F22 -> 3655027.1
A24: 45142 | B24: Gestão de caixa | E24: =(D23*0.005)+10 -> 28.53505 | F24: =D24-E24+F23 -> 3654998.6
A25: 45142 | B25: Crédito em conta | C25: LUBRIFICANTES S. K. LTDA | D25: 1190.7 | F25: =D25-E25+F24 -> 3656189.3
A26: 45142 | B26: Gestão de caixa | E26: =(D25*0.005)+10 -> 15.9535 | F26: =D26-E26+F25 -> 3656173.3
A27: 45145 | B27: Crédito em conta | C27: BB TRANSPORTE E TURISMO LTDA | D27: 90000 | F27: =D27-E27+F26 -> 3746173.3
A28: 45145 | B28: Gestão de caixa | E28: =(D27*0.005)+10 -> 460 | F28: =D28-E28+F27 -> 3745713.3
A29: 45145 | B29: Transferência entre contas | C29: TRANSPORTADORA TURISTICA BENFICA S.A | E29: 52000 | F29: =D29-E29+F28 -> 3693713.3
A30: 45145 | B30: Transferência entre contas | C30: TRANSPORTADORA TURISTICA BENFICA S.A | E30: 2000 | F30: =D30-E30+F29 -> 3691713.3
A31: 45146 | B31: Crédito em conta | C31: GUARIROBA BIOENERGIA LTDA | D31: 181682.6 | F31: =D31-E31+F30 -> 3873395.9
A32: 45146 | B32: Gestão de caixa | E32: =(D31*0.005)+10 -> 918.413 | F32: =D32-E32+F31 -> 3872477.5
A33: 45146 | B33: Crédito em conta | C33: MOEMA BIOENERGIA S A | D33: 224615.81 | F33: =D33-E33+F32 -> 4097093.3
A34: 45146 | B34: Gestão de caixa | E34: =(D33*0.005)+10 -> 1133.0791 | F34: =D34-E34+F33 -> 4095960.2
A35: 45146 | B35: Crédito em conta | C35: OUROESTE BIOENERGIA LTDA | D35: 23696.9 | F35: =D35-E35+F34 -> 4119657.1
A36: 45146 | B36: Gestão de caixa | E36: =(D35*0.005)+10 -> 128.4845 | F36: =D36-E36+F35 -> 4119528.7
A37: 45147 | B37: Crédito em conta | C37: TRANSPORTADORA TURISTICA BENFICA AS | D37: 22400 | F37: =D37-E37+F36 -> 4141928.7
A38: 45147 | B38: Gestão de caixa | E38: =(D37*0.005)+10 -> 122 | F38: =D38-E38+F37 -> 4141806.7
A39: 45147 | B39: Crédito em conta | C39: TRANSPORTADORA TURISTICA BENFICA AS | D39: 152524 | F39: =D39-E39+F38 -> 4294330.7
A40: 45147 | B40: Gestão de caixa | E40: =(D39*0.005)+10 -> 772.62 | F40: =D40-E40+F39 -> 4293558
A41: 45148 | B41: Transferência entre contas | C41: TRANSPORTADORA TURISTICA BENFICA S.A | E41: 141500 | F41: =D41-E41+F40 -> 4152058
A42: 45148 | B42: Transferência entre contas | C42: TRANSPORTADORA TURISTICA BENFICA S.A | E42: 16500 | F42: =D42-E42+F41 -> 4135558
A43: 45148 | B43: Crédito em conta | C43: SANCETUR - SANTA CECILIA TURISMO LTDA | D43: 15000 | F43: =D43-E43+F42 -> 4150558
A44: 45148 | B44: Gestão de caixa | E44: =(D43*0.005)+10 -> 85 | F44: =D44-E44+F43 -> 4150473
A45: 45149 | B45: Crédito em conta | C45: TRANSPORTADORA TUR BENFICA S A | D45: 330 | F45: =D45-E45+F44 -> 4150803
A46: 45149 | B46: Gestão de caixa | E46: =(D45*0.005)+10 -> 11.65 | F46: =D46-E46+F45 -> 4150791.4
A47: 45149 | B47: Transferência entre contas | C47: TRANSPORTADORA TURISTICA BENFICA S.A | E47: 8000 | F47: =D47-E47+F46 -> 4142791.4
A48: 45152 | B48: Transferência entre contas | C48: TRANSPORTADORA TURISTICA BENFICA S.A | E48: 45000 | F48: =D48-E48+F47 -> 4097791.4
A49: 45153 | B49: Transferência entre contas | C49: TRANSPORTADORA TURISTICA BENFICA S.A | E49: 75000 | F49: =D49-E49+F48 -> 4022791.4
A50: 45153 | B50: Crédito em conta | C50: SCATENA AGENCIA DE VIAGENS E TURISMO EIRELI | D50: 28000 | F50: =D50-E50+F49 -> 4050791.4
A51: 45153 | B51: Gestão de caixa | E51: =(D50*0.005)+10 -> 150 | F51: =D51-E51+F50 -> 4050641.4
A52: 45153 | B52: Crédito em conta | C52: AGROCANA A N H LTDA | D52: 21066.67 | F52: =D52-E52+F51 -> 4071708.1
A53: 45153 | B53: Gestão de caixa | E53: =(D52*0.005)+10 -> 115.33335 | F53: =D53-E53+F52 -> 4071592.7
A54: 45154 | B54: Crédito em conta | C54: EURIPEDES VERALDI | D54: 22000 | F54: =D54-E54+F53 -> 4093592.7
A55: 45154 | B55: Gestão de caixa | E55: =(D54*0.005)+10 -> 120 | F55: =D55-E55+F54 -> 4093472.7
A56: 45154 | B56: Crédito em conta | C56: MENDES FERREIRA AGRICOLA LTDA | D56: 8000 | F56: =D56-E56+F55 -> 4101472.7
A57: 45154 | B57: Gestão de caixa | E57: =(D56*0.005)+10 -> 50 | F57: =D57-E57+F56 -> 4101422.7
A58: 45156 | B58: Transferência entre contas | C58: TRANSPORTADORA TURISTICA BENFICA S.A | E58: 187000 | F58: =D58-E58+F57 -> 3914422.7
A59: 45156 | B59: Crédito em conta | C59: GERACAO TRANSPORTES E LOCADORA DE VEICUL | D59: 140000 | F59: =D59-E59+F58 -> 4054422.7
A60: 45156 | B60: Gestão de caixa | E60: =(D59*0.005)+10 -> 710 | F60: =D60-E60+F59 -> 4053712.7
A61: 45159 | B61: Transferência entre contas | C61: TRANSPORTADORA TURISTICA BENFICA S.A | E61: 24500 | F61: =D61-E61+F60 -> 4029212.7
A62: 45160 | B62: Transferência entre contas | C62: TRANSPORTADORA TURISTICA BENFICA S.A | E62: 12000 | F62: =D62-E62+F61 -> 4017212.7
A63: 45161 | B63: Transferência entre contas | C63: TRANSPORTADORA TURISTICA BENFICA S.A | E63: 15500 | F63: =D63-E63+F62 -> 4001712.7
A64: 45162 | B64: Crédito em conta | C64: SILVA & BEGHINI COMERCIO DE ONIBUS LTDA | D64: 6000 | F64: =D64-E64+F63 -> 4007712.7
A65: 45162 | B65: Gestão de caixa | E65: =(D64*0.005)+10 -> 40 | F65: =D65-E65+F64 -> 4007672.7
A66: 45162 | B66: Crédito em conta | C66: JOCA PRESTACAO DE SERVICO | D66: 6774 | F66: =D66-E66+F65 -> 4014446.7
A67: 45162 | B67: Gestão de caixa | E67: =(D66*0.005)+10 -> 43.87 | F67: =D67-E67+F66 -> 4014402.9
A68: 45163 | B68: Crédito em conta | C68: FENILZA FREITAS PERON | D68: 5700 | F68: =D68-E68+F67 -> 4020102.9
A69: 45163 | B69: Gestão de caixa | E69: =(D68*0.005)+10 -> 38.5 | F69: =D69-E69+F68 -> 4020064.4
A70: 45163 | B70: Crédito em conta | C70: FENILZA FREITAS PERON | D70: 800 | F70: =D70-E70+F69 -> 4020864.4
A71: 45163 | B71: Gestão de caixa | E71: =(D70*0.005)+10 -> 14 | F71: =D71-E71+F70 -> 4020850.4
A72: 45163 | B72: Transferência entre contas | C72: TRANSPORTADORA TURISTICA BENFICA S.A | E72: 23000 | F72: =D72-E72+F71 -> 3997850.4
A73: 45163 | B73: Crédito em conta | C73: UNIVERSAL TURISMO LTDA-EPP | D73: 6000 | F73: =D73-E73+F72 -> 4003850.4
A74: 45163 | B74: Gestão de caixa | E74: =(D73*0.005)+10 -> 40 | F74: =D74-E74+F73 -> 4003810.4
A75: 45166 | B75: Crédito em conta | C75: ROGERIO ALMIR ZAPALA | D75: 140000 | F75: =D75-E75+F74 -> 4143810.4
A76: 45166 | B76: Gestão de caixa | E76: =(D75*0.005)+10 -> 710 | F76: =D76-E76+F75 -> 4143100.4
A77: 45167 | B77: Crédito em conta | C77: OTACILIO GOMES FERRAZ FILHO | D77: 15000 | F77: =D77-E77+F76 -> 4158100.4
A78: 45167 | B78: Gestão de caixa | E78: =(D77*0.005)+10 -> 85 | F78: =D78-E78+F77 -> 4158015.4
A79: 45167 | B79: Crédito em conta | C79: TRANSPORTADORA TURISTICA BENFICA S.A | D79: 9000 | F79: =D79-E79+F78 -> 4167015.4
A80: 45167 | B80: Gestão de caixa | E80: =(D79*0.005)+10 -> 55 | F80: =D80-E80+F79 -> 4166960.4
A81: 45167 | B81: Crédito em conta | C81: TRANSPORTADORA TUR BENFICA S A | D81: 30724.28 | F81: =D81-E81+F80 -> 4197684.6
A82: 45167 | B82: Gestão de caixa | E82: =(D81*0.005)+10 -> 163.6214 | F82: =D82-E82+F81 -> 4197521
A83: 45168 | B83: Transferência entre contas | C83: TRANSPORTADORA TURISTICA BENFICA S.A | E83: 228000 | F83: =D83-E83+F82 -> 3969521
A84: 45168 | B84: Crédito em conta | C84: ARENA FUTIBA | D84: 3707.01 | F84: =D84-E84+F83 -> 3973228
A85: 45168 | B85: Gestão de caixa | E85: =(D84*0.005)+10 -> 28.53505 | F85: =D85-E85+F84 -> 3973199.5
A86: 45169 | B86: Crédito em conta | C86: ALESSANDRO R DOS SANTOS AGRICOLA E TRANSPORTE | D86: 20000 | F86: =D86-E86+F85 -> 3993199.5
A87: 45169 | B87: Gestão de caixa | E87: =(D86*0.005)+10 -> 110 | F87: =D87-E87+F86 -> 3993089.5
A88: 45169 | B88: Crédito em conta | C88: MIGUEL ARAUJO GIMENEZ | D88: 5000 | F88: =D88-E88+F87 -> 3998089.5
A89: 45169 | B89: Gestão de caixa | E89: =(D88*0.005)+10 -> 35 | F89: =D89-E89+F88 -> 3998054.5
A90: 45169 | B90: Transferência entre contas | C90: TRANSPORTADORA TURISTICA BENFICA S.A | E90: 18000 | F90: =D90-E90+F89 -> 3980054.5
A91: 45169 | B91: Crédito em conta | C91: ARD TRANSPORTES LTDA | D91: 10000 | F91: =D91-E91+F90 -> 3990054.5
A92: 45169 | B92: Gestão de caixa | E92: =(D91*0.005)+10 -> 60 | F92: =D92-E92+F91 -> 3989994.5
F93: =D93-E93+F92 -> 3989994.5
F94: =D94-E94+F93 -> 3989994.5
F95: =D95-E95+F94 -> 3989994.5
F96: =D96-E96+F95 -> 3989994.5
F97: =D97-E97+F96 -> 3989994.5
F98: =D98-E98+F97 -> 3989994.5
F99: =D99-E99+F98 -> 3989994.5
F100: =D100-E100+F99 -> 3989994.5
F101: =D101-E101+F100 -> 3989994.5
F102: =D102-E102+F101 -> 3989994.5
F103: =D103-E103+F102 -> 3989994.5
...

Sheet Setembro2023
A2: EXTRATO DE MOVIMENTAÇÃO
A4: Banco | B4: LEPTA BANK (274) | C4: Agência | D4: 1 | E4: Conta | F4: 08198095-5
A5: Empresa | B5: TRANSP. TURISTICA BENFICA S.A | C5: Saldo Anterior | D5: =Agosto2023!F6 -> 3989994.5 | F5: Saldo Disponível
A6: CNPJ | B6: 59.275.289/0001-02 | C6: Totais (Entradas/Saídas) | D6: =SUM(D9:D609) -> 1112643 | E6: =SUM(E9:E609) -> 951483.22 | F6: =F609 -> 4151154.3
A8: Data | B8: Histórico | C8: Complemento | D8: Créditos | E8: Débitos | F8: Saldo
A9: 45170 | B9: Crédito em conta | C9: OTACILIO GOMES FERRAZ FILHO | D9: 13125 | F9: =D9-E9+D5 -> 4003119.5
A10: 45170 | B10: Gestão de caixa | E10: =(D9*0.005)+10 -> 75.625 | F10: =D10-E10+F9 -> 4003043.9
A11: 45172 | B11: Tarifa de manutenção de conta | C11: TRANSPORTADORA TURISTICA BENFICA S.A - (Vinculada) | E11: 1500 | F11: =D11-E11+F10 -> 4001543.9
A12: 45172 | B12: Tarifa de manutenção da conta | C12: TED's, PIX e demais | E12: 420 | F12: =D12-E12+F11 -> 4001123.9
A13: 45173 | B13: Crédito em conta | C13: TRANSPORTADORA TURISTICA BENFICA S.A | D13: 50000 | F13: =D13-E13+F12 -> 4051123.9
A14: 45173 | B14: Gestão de caixa | E14: =(D13*0.005)+10 -> 260 | F14: =D14-E14+F13 -> 4050863.9
A15: 45174 | B15: Crédito em conta | C15: BB TRANSPORTE E TURISMO LTDA | D15: 90000 | F15: =D15-E15+F14 -> 4140863.9
A16: 45174 | B16: Gestão de caixa | E16: =(D15*0.005)+10 -> 460 | F16: =D16-E16+F15 -> 4140403.9
A17: 45174 | B17: Crédito em conta | C17: GERACAO TRANSPORTES E LOCADORA DE VEICUL | D17: 120000 | F17: =D17-E17+F16 -> 4260403.9
A18: 45174 | B18: Gestão de caixa | E18: =(D17*0.005)+10 -> 610 | F18: =D18-E18+F17 -> 4259793.9
A19: 45174 | B19: Transferência entre contas | C19: TRANSPORTADORA TURISTICA BENFICA S.A | E19: 186000 | F19: =D19-E19+F18 -> 4073793.9
A20: 45174 | B20: Transferência entre contas | C20: TRANSPORTADORA TURISTICA BENFICA S.A | E20: 1000 | F20: =D20-E20+F19 -> 4072793.9
A21: 45175 | B21: Transferência entre contas | C21: TRANSPORTADORA TURISTICA BENFICA S.A | E21: 81000 | F21: =D21-E21+F20 -> 3991793.9
A22: 45175 | B22: Transferência entre contas | C22: TRANSPORTADORA TURISTICA BENFICA S.A | E22: 73000 | F22: =D22-E22+F21 -> 3918793.9
A23: 45175 | B23: Tarifa de manutenção de conta | C23: TRANSPORTADORA TURISTICA BENFICA S.A - (Empresa) | E23: 1500 | F23: =D23-E23+F22 -> 3917293.9
A24: 45177 | B24: Crédito em conta | C24: GUARIROBA BIOENERGIA LTDA | D24: 154450.08 | F24: =D24-E24+F23 -> 4071743.9
A25: 45177 | B25: Gestão de caixa | E25: =(D24*0.005)+10 -> 782.2504 | F25: =D25-E25+F24 -> 4070961.7
A26: 45177 | B26: Crédito em conta | C26: MOEMA BIOENERGIA S A | D26: 203313.03 | F26: =D26-E26+F25 -> 4274274.7
A27: 45177 | B27: Gestão de caixa | E27: =(D26*0.005)+10 -> 1026.5651 | F27: =D27-E27+F26 -> 4273248.2
A28: 45177 | B28: Crédito em conta | C28: OUROESTE BIOENERGIA LTDA | D28: 25171.69 | F28: =D28-E28+F27 -> 4298419.9
A29: 45177 | B29: Gestão de caixa | E29: =(D28*0.005)+10 -> 135.85845 | F29: =D29-E29+F28 -> 4298284
A30: 45180 | B30: Crédito em conta | C30: REGINALDO DA SILVA ALVES | D30: 140650 | F30: =D30-E30+F29 -> 4438934
A31: 45180 | B31: Gestão de caixa | E31: =(D30*0.005)+10 -> 713.25 | F31: =D31-E31+F30 -> 4438220.7
A32: 45180 | B32: Transferência entre contas | C32: TRANSPORTADORA TURISTICA BENFICA S.A | E32: 113000 | F32: =D32-E32+F31 -> 4325220.7
A33: 45181 | B33: Crédito em conta | C33: TRANSPORTADORA TUR BENFICA S A | D33: 147854 | F33: =D33-E33+F32 -> 4473074.7
A34: 45181 | B34: Gestão de caixa | E34: =(D33*0.005)+10 -> 749.27 | F34: =D34-E34+F33 -> 4472325.5
A35: 45181 | B35: Crédito em conta | C35: SANCETUR - SANTA CECILIA TURISMO LTDA | D35: 12000 | F35: =D35-E35+F34 -> 4484325.5
A36: 45181 | B36: Gestão de caixa | E36: =(D35*0.005)+10 -> 70 | F36: =D36-E36+F35 -> 4484255.5
A37: 45182 | B37: Transferência entre contas | C37: TRANSPORTADORA TURISTICA BENFICA S.A | E37: 34000 | F37: =D37-E37+F36 -> 4450255.5
A38: 45183 | B38: Transferência entre contas | C38: TRANSPORTADORA TURISTICA BENFICA S.A | E38: 20000 | F38: =D38-E38+F37 -> 4430255.5
A39: 45184 | B39: Transferência entre contas | C39: TRANSPORTADORA TURISTICA BENFICA S.A | E39: 37500 | F39: =D39-E39+F38 -> 4392755.5
A40: 45184 | B40: Crédito em conta | C40: SCATENA AGENCIA DE VIAGENS E TURISMO EIR | D40: 23333.33 | F40: =D40-E40+F39 -> 4416088.8
A41: 45184 | B41: Gestão de caixa | E41: =(D40*0.005)+10 -> 126.66665 | F41: =D41-E41+F40 -> 4415962.1
A42: 45187 | B42: Transferência entre contas | C42: TRANSPORTADORA TURISTICA BENFICA S.A | E42: 82000 | F42: =D42-E42+F41 -> 4333962.1
A43: 45188 | B43: Crédito em conta | C43: ANANIAS MORICIO DA SILVA | D43: 11000 | F43: =D43-E43+F42 -> 4344962.1
A44: 45188 | B44: Gestão de caixa | E44: =(D43*0.005)+10 -> 65 | F44: =D44-E44+F43 -> 4344897.1
A45: 45189 | B45: Transferência entre contas | C45: TRANSPORTADORA TURISTICA BENFICA S.A | E45: 125300 | F45: =D45-E45+F44 -> 4219597.1
A46: 45189 | B46: Crédito em conta | C46: AGROCANA A N H LTDA. | D46: 11466.67 | F46: =D46-E46+F45 -> 4231063.8
A47: 45189 | B47: Gestão de caixa | E47: =(D46*0.005)+10 -> 67.33335 | F47: =D47-E47+F46 -> 4230996.5
A48: 45190 | B48: Crédito em conta | C48: ARENA FUTIBA | D48: 3707.01 | F48: =D48-E48+F47 -> 4234703.5
A49: 45190 | B49: Gestão de caixa | E49: =(D48*0.005)+10 -> 28.53505 | F49: =D49-E49+F48 -> 4234674.9
A50: 45191 | B50: Transferência entre contas | C50: TRANSPORTADORA TURISTICA BENFICA S.A | E50: 16500 | F50: =D50-E50+F49 -> 4218174.9
A51: 45194 | B51: Crédito em conta | C51: LUIZ PAULO DIAS MACHADO | D51: 20000 | F51: =D51-E51+F50 -> 4238174.9
A52: 45194 | B52: Gestão de caixa | E52: =(D51*0.005)+10 -> 110 | F52: =D52-E52+F51 -> 4238064.9
A53: 45194 | B53: Transferência entre contas | C53: TRANSPORTADORA TURISTICA BENFICA S.A | E53: 23000 | F53: =D53-E53+F52 -> 4215064.9
A54: 45195 | B54: Transferência entre contas | C54: TRANSPORTADORA TURISTICA BENFICA S.A | E54: 1500 | F54: =D54-E54+F53 -> 4213564.9
A55: 45195 | B55: Crédito em conta | C55: TRANSPORTADORA TUR BENFICA S A | D55: 9552.72 | F55: =D55-E55+F54 -> 4223117.7
A56: 45195 | B56: Gestão de caixa | E56: =(D55*0.005)+10 -> 57.7636 | F56: =D56-E56+F55 -> 4223059.9
A57: 45197 | B57: Crédito em conta | C57: EXPRESSO ITAMARATI AS | D57: 45000 | F57: =D57-E57+F56 -> 4268059.9
A58: 45197 | B58: Gestão de caixa | E58: =(D57*0.005)+10 -> 235 | F58: =D58-E58+F57 -> 4267824.9
A59: 45197 | B59: Crédito em conta | C59: TRANSPORTADORA TUR BENFICA S A | D59: 21247.55 | F59: =D59-E59+F58 -> 4289072.5
A60: 45197 | B60: Gestão de caixa | E60: =(D59*0.005)+10 -> 116.23775 | F60: =D60-E60+F59 -> 4288956.2
A61: 45198 | B61: Transferência entre contas | C61: TRANSPORTADORA TURISTICA BENFICA S.A | E61: 147000 | F61: =D61-E61+F60 -> 4141956.2
A62: 45198 | B62: Transferência entre contas | C62: TRANSPORTADORA TURISTICA BENFICA S.A | E62: 1500 | F62: =D62-E62+F61 -> 4140456.2
A63: 45198 | B63: Crédito em conta | C63: ARD TRANSPORTES LTDA | D63: 10000 | F63: =D63-E63+F62 -> 4150456.2
A64: 45198 | B64: Gestão de caixa | E64: =(D63*0.005)+10 -> 60 | F64: =D64-E64+F63 -> 4150396.2
A65: 45198 | B65: Crédito em conta | C65: TRANSPORTADORA TURISTICA BENFICA AS | D65: 771.92 | F65: =D65-E65+F64 -> 4151168.1
A66: 45198 | B66: Gestão de caixa | E66: =(D65*0.005)+10 -> 13.8596 | F66: =D66-E66+F65 -> 4151154.3
A67: 45198 | B67: Ajuste de Saldo | E67: 0.01 | F67: =D67-E67+F66 -> 4151154.3
F68: =D68-E68+F67 -> 4151154.3
F69: =D69-E69+F68 -> 4151154.3
F70: =D70-E70+F69 -> 4151154.3
F71: =D71-E71+F70 -> 4151154.3
F72: =D72-E72+F71 -> 4151154.3
F73: =D73-E73+F72 -> 4151154.3
F74: =D74-E74+F73 -> 4151154.3
F75: =D75-E75+F74 -> 4151154.3
F76: =D76-E76+F75 -> 4151154.3
F77: =D77-E77+F76 -> 4151154.3
F78: =D78-E78+F77 -> 4151154.3
F79: =D79-E79+F78 -> 4151154.3
... F609: =D609-E609+F608 -> 4151154.3

Sheet Outubro2023
A2: EXTRATO DE MOVIMENTAÇÃO
A4: Banco | B4: LEPTA BANK (274) | C4: Agência | D4: 1 | E4: Conta | F4: 08198095-5
A5: Empresa | B5: TRANSP. TURISTICA BENFICA S.A | C5: Saldo Anterior | D5: =Setembro2023!F6 -> 4151154.3 | F5: Saldo Disponível
A6: CNPJ | B6: 59.275.289/0001-02 | C6: Totais (Entradas/Saídas) | D6: =SUM(D9:D609) -> 1738820.8 | E6: =SUM(E9:E609) -> 2615004.1 | F6: =F609 -> 3274971
A8: Data | B8: Histórico | C8: Complemento | D8: Créditos | E8: Débitos | F8: Saldo
A9: 45200 | B9: Tarifa de manutenção de conta | C9: TRANSPORTADORA TURISTICA BENFICA S.A - (Vinculada) | E9: 1500 | F9: =D9-E9+D5 -> 4149654.3
A10: 45200 | B10: Tarifa de manutenção da conta | C10: TED's, PIX e demais | E10: 300 | F10: =D10-E10+F9 -> 4149354.3
A11: 45201 | B11: Transferência entre contas | C11: TRANSPORTADORA TURISTICA BENFICA S.A | E11: 9500 | F11: =D11-E11+F10 -> 4139854.3
A12: 45202 | B12: Transferência entre contas | C12: TRANSPORTADORA TURISTICA BENFICA S.A | E12: 12000 | F12: =D12-E12+F11 -> 4127854.3
A13: 45203 | B13: Transferência entre contas | C13: TRANSPORTADORA TURISTICA BENFICA S.A | E13: 184000 | F13: =D13-E13+F12 -> 3943854.3
A14: 45204 | B14: Crédito em conta | C14: BB TRANSPORTE E TURISMO LTDA | D14: 90000 | F14: =D14-E14+F13 -> 4033854.3
A15: 45204 | B15: Gestão de caixa | E15: =(D14*0.005)+10 -> 460 | F15: =D15-E15+F14 -> 4033394.3
A16: 45204 | B16: Transferência entre contas | C16: TRANSPORTADORA TURISTICA BENFICA S.A | E16: 1000 | F16: =D16-E16+F15 -> 4032394.3
A17: 45204 | B17: Tarifa de manutenção de conta | C17: TRANSPORTADORA TURISTICA BENFICA S.A - (Empresa) | E17: 1500 | F17: =D17-E17+F16 -> 4030894.3
A18: 45205 | B18: Transferência entre contas | C18: TRANSPORTADORA TURISTICA BENFICA S.A | E18: 38000 | F18: =D18-E18+F17 -> 3992894.3
A19: 45205 | B19: Transferência entre contas | C19: TRANSPORTADORA TURISTICA BENFICA S.A | E19: 26800 | F19: =D19-E19+F18 -> 3966094.3
A20: 45208 | B20: Transferência entre contas | C20: TRANSPORTADORA TURISTICA BENFICA S.A | E20: 309000 | F20: =D20-E20+F19 -> 3657094.3
A21: 45208 | B21: Crédito em conta | C21: TRANSPORTADORA TUR BENFICA S A | D21: 152524 | F21: =D21-E21+F20 -> 3809618.3
A22: 45208 | B22: Gestão de caixa | E22: =(D21*0.005)+10 -> 772.62 | F22: =D22-E22+F21 -> 3808845.6
A23: 45209 | B23: Crédito em conta | C23: WALTER GONCALVES CUNHA | D23: 40000 | F23: =D23-E23+F22 -> 3848845.6
A24: 45209 | B24: Gestão de caixa | E24: =(D23*0.005)+10 -> 210 | F24: =D24-E24+F23 -> 3848635.6
A25: 45209 | B25: Transferência entre contas | C25: TRANSPORTADORA TURISTICA BENFICA S.A | E25: 276000 | F25: =D25-E25+F24 -> 3572635.6
A26: 45209 | B26: Crédito em conta | C26: SANCETUR - SANTA CECILIA TURISMO LTDA | D26: 12000 | F26: =D26-E26+F25 -> 3584635.6
A27: 45209 | B27: Gestão de caixa | E27: =(D26*0.005)+10 -> 70 | F27: =D27-E27+F26 -> 3584565.6
A28: 45209 | B28: Crédito em conta | C28: GUARIROBA BIOENERGIA LTDA | D28: 148110.22 | F28: =D28-E28+F27 -> 3732675.9
A29: 45209 | B29: Gestão de caixa | E29: =(D28*0.005)+10 -> 750.5511 | F29: =D29-E29+F28 -> 3731925.3
A30: 45209 | B30: Crédito em conta | C30: MOEMA BIOENERGIA S A | D30: 209326.27 | F30: =D30-E30+F29 -> 3941251.6
A31: 45209 | B31: Gestão de caixa | E31: =(D30*0.005)+10 -> 1056.6313 | F31: =D31-E31+F30 -> 3940195
A32: 45209 | B32: Transferência entre contas | C32: TRANSPORTADORA TURISTICA BENFICA S.A | E32: 495000 | F32: =D32-E32+F31 -> 3445195
A33: 45210 | B33: Crédito em conta | C33: OUROESTE BIOENERGIA LTDA | D33: 23689.39 | F33: =D33-E33+F32 -> 3468884.3
A34: 45210 | B34: Gestão de caixa | E34: =(D33*0.005)+10 -> 128.44695 | F34: =D34-E34+F33 -> 3468755.9
A35: 45210 | B35: Transferência entre contas | C35: TRANSPORTADORA TURISTICA BENFICA S.A | E35: 392000 | F35: =D35-E35+F34 -> 3076755.9
A36: 45215 | B36: Transferência entre contas | C36: TRANSPORTADORA TURISTICA BENFICA S.A | E36: 434000 | F36: =D36-E36+F35 -> 2642755.9
A37: 45215 | B37: Crédito em conta | C37: SCATENA AGENCIA DE VIAGENS E TURISMO EIR | D37: 11433.32 | F37: =D37-E37+F36 -> 2654189.2
A38: 45215 | B38: Gestão de caixa | E38: =(D37*0.005)+10 -> 67.1666 | F38: =D38-E38+F37 -> 2654122.1
A39: 45217 | B39: Transferência entre contas | C39: TRANSPORTADORA TURISTICA BENFICA S.A | E39: 86000 | F39: =D39-E39+F38 -> 2568122.1
A40: 45217 | B40: Crédito em conta | C40: 2 IRMAS TRANSPORTES LTDA | D40: 22500 | F40: =D40-E40+F39 -> 2590622.1
A41: 45217 | B41: Gestão de caixa | E41: =(D40*0.005)+10 -> 122.5 | F41: =D41-E41+F40 -> 2590499.6
A42: 45218 | B42: Transferência entre contas | C42: TRANSPORTADORA TURISTICA BENFICA S.A | E42: 10000 | F42: =D42-E42+F41 -> 2580499.6
A43: 45218 | B43: Crédito em conta | C43: BANCO DO BRASIL | D43: 43994.13 | F43: =D43-E43+F42 -> 2624493.7
A44: 45218 | B44: Gestão de caixa | E44: =(D43*0.005)+10 -> 229.97065 | F44: =D44-E44+F43 -> 2624263.7
A45: 45219 | B45: Transferência entre contas | C45: TRANSPORTADORA TURISTICA BENFICA S.A | E45: 57500 | F45: =D45-E45+F44 -> 2566763.7
A46: 45219 | B46: Transferência entre contas | C46: TRANSPORTADORA TURISTICA BENFICA S.A | E46: 69000 | F46: =D46-E46+F45 -> 2497763.7
A47: 45219 | B47: Crédito em conta | C47: ARENA FUTIBA II | D47: 10707.01 | F47: =D47-E47+F46 -> 2508470.7
A48: 45219 | B48: Gestão de caixa | E48: =(D47*0.005)+10 -> 63.53505 | F48: =D48-E48+F47 -> 2508407.2
A49: 45222 | B49: Crédito em conta | C49: TRANSPORTADORA TURISTICA BENFICA S.A | D49: 25000 | F49: =D49-E49+F48 -> 2533407.2
A50: 45222 | B50: Gestão de caixa | E50: =(D49*0.005)+10 -> 135 | F50: =D50-E50+F49 -> 2533272.2
A51: 45223 | B51: Transferência entre contas | C51: TRANSPORTADORA TURISTICA BENFICA S.A | E51: 11000 | F51: =D51-E51+F50 -> 2522272.2
A52: 45224 | B52: Transferência entre contas | C52: TRANSPORTADORA TURISTICA BENFICA S.A | E52: 30000 | F52: =D52-E52+F51 -> 2492272.2
A53: 45225 | B53: Crédito em conta | C53: PORTOBENS ADMINISTRADORA DE CO | D53: 149284.86 | F53: =D53-E53+F52 -> 2641557
A54: 45225 | B54: Gestão de caixa | E54: =(D53*0.005)+10 -> 756.4243 | F54: =D54-E54+F53 -> 2640800.6
A55: 45225 | B55: Crédito em conta | C55: PORTOBENS ADMINISTRADORA DE CO | D55: 151248.15 | F55: =D55-E55+F54 -> 2792048.8
A56: 45225 | B56: Gestão de caixa | E56: =(D55*0.005)+10 -> 766.24075 | F56: =D56-E56+F55 -> 2791282.5
A57: 45225 | B57: Crédito em conta | C57: PORTOBENS ADMINISTRADORA DE CO | D57: 147652.74 | F57: =D57-E57+F56 -> 2938935.3
A58: 45225 | B58: Gestão de caixa | E58: =(D57*0.005)+10 -> 748.2637 | F58: =D58-E58+F57 -> 2938187
A59: 45225 | B59: Crédito em conta | C59: PORTOBENS ADMINISTRADORA DE CO | D59: 413330.07 | F59: =D59-E59+F58 -> 3351517.1
A60: 45225 | B60: Gestão de caixa | E60: =(D59*0.005)+10 -> 2076.6503 | F60: =D60-E60+F59 -> 3349440.4
A61: 45226 | B61: Crédito em conta | C61: TRANSPORTADORA TUR BENFICA S A | D61: 9951.21 | F61: =D61-E61+F60 -> 3359391.6
A62: 45226 | B62: Gestão de caixa | E62: =(D61*0.005)+10 -> 59.75605 | F62: =D62-E62+F61 -> 3359331.9
A63: 45226 | B63: Crédito em conta | C63: TRANSPORTADORA TURISTICA BENFICA S.A | D63: 48000 | F63: =D63-E63+F62 -> 3407331.9
A64: 45226 | B64: Gestão de caixa | E64: =(D63*0.005)+10 -> 250 | F64: =D64-E64+F63 -> 3407081.9
A65: 45226 | B65: Crédito em conta | C65: AGROCANA A N H LTDA. | D65: 8000 | F65: =D65-E65+F64 -> 3415081.9
A66: 45226 | B66: Gestão de caixa | E66: =(D65*0.005)+10 -> 50 | F66: =D66-E66+F65 -> 3415031.9
A67: 45229 | B67: Ajuste de Saldo | E67: 0.01 | F67: =D67-E67+F66 -> 3415031.9
A68: 45229 | B68: Crédito em conta | C68: TRANSPORTADORA TUR BENFICA S A | D68: 21297.55 | F68: =D68-E68+F67 -> 3436329.4
A69: 45229 | B69: Gestão de caixa | E69: =(D68*0.005)+10 -> 116.48775 | F69: =D69-E69+F68 -> 3436212.9
A70: 45229 | B70: Transferência entre contas | C70: TRANSPORTADORA TURISTICA BENFICA S.A | E70: 161000 | F70: =D70-E70+F69 -> 3275212.9
A71: 45230 | B71: Crédito em conta | C71: TRANSPORTADORA TURISTICA BENFICA AS | D71: 771.92 | F71: =D71-E71+F70 -> 3275984.9
A72: 45230 | B72: Gestão de caixa | E72: =(D71*0.005)+10 -> 13.8596 | F72: =D72-E72+F71 -> 3275971
A73: 45230 | B73: Transferência entre contas | C73: TRANSPORTADORA TURISTICA BENFICA S.A | E73: 1000 | F73: =D73-E73+F72 -> 3274971
F74: =D74-E74+F73 -> 3274971
F75: =D75-E75+F74 -> 3274971
F76: =D76-E76+F75 -> 3274971
F77: =D77-E77+F76 -> 3274971
F78: =D78-E78+F77 -> 3274971
F79: =D79-E79+F78 -> 3274971
F80: =D80-E80+F79 -> 3274971
F81: =D81-E81+F80 -> 3274971
F82: =D82-E82+F81 -> 3274971
F83: =D83-E83+F82 -> 3274971
F84: =D84-E84+F83 -> 3274971
F85: =D85-E85+F84 -> 3274971
... F609: =D609-E609+F608 -> 3274971

Sheet Novembro2023
A2: EXTRATO DE MOVIMENTAÇÃO
A4: Banco | B4: LEPTA BANK (274) | C4: Agência | D4: 1 | E4: Conta | F4: 08198095-5
A5: Empresa | B5: TRANSP. TURISTICA BENFICA S.A | C5: Saldo Anterior | D5: =Outubro2023!F6 -> 3274971 | F5: Saldo Disponível
A6: CNPJ | B6: 59.275.289/0001-02 | C6: Totais (Entradas/Saídas) | D6: =SUM(D9:D609) -> 643484.69 | E6: =SUM(E9:E609) -> 607857.42 | F6: =F609 -> 3310598.3
A8: Data | B8: Histórico | C8: Complemento | D8: Créditos | E8: Débitos | F8: Saldo
A9: 45231 | B9: Tarifa de manutenção de conta | C9: TRANSPORTADORA TURISTICA BENFICA S.A - (Vinculada) | E9: 1500 | F9: =D9-E9+D5 -> 3273471
A10: 45231 | B10: Tarifa de manutenção da conta | C10: TED's, PIX e demais | E10: 380 | F10: =D10-E10+F9 -> 3273091
A11: 45231 | B11: Crédito em conta | C11: SILVANA DO NASCIMENTO RODRIGUES | D11: 25000 | F11: =D11-E11+F10 -> 3298091
A12: 45231 | B12: Gestão de caixa | E12: =(D11*0.005)+10 -> 135 | F12: =D12-E12+F11 -> 3297956
A13: 45231 | B13: Transferência entre contas | C13: TRANSPORTADORA TURISTICA BENFICA S.A | E13: 500 | F13: =D13-E13+F12 -> 3297456
A14: 45231 | B14: Crédito em conta | C14: ARD TRANSPORTES LTDA | D14: 10000 | F14: =D14-E14+F13 -> 3307456
A15: 45231 | B15: Gestão de caixa | E15: =(D14*0.005)+10 -> 60 | F15: =D15-E15+F14 -> 3307396
A16: 45233 | B16: Transferência entre contas | C16: TRANSPORTADORA TURISTICA BENFICA S.A | E16: 114000 | F16: =D16-E16+F15 -> 3193396
A17: 45233 | B17: Tarifa de manutenção de conta | C17: TRANSPORTADORA TURISTICA BENFICA S.A - (Empresa) | E17: 1500 | F17: =D17-E17+F16 -> 3191896
A18: 45236 | B18: Crédito em conta | C18: BB TRANSPORTE E TURISMO LTDA | D18: 90000 | F18: =D18-E18+F17 -> 3281896
A19: 45236 | B19: Gestão de caixa | E19: =(D18*0.005)+10 -> 460 | F19: =D19-E19+F18 -> 3281436
A20: 45236 | B20: Transferência entre contas | C20: TRANSPORTADORA TURISTICA BENFICA S.A | E20: 18500 | F20: =D20-E20+F19 -> 3262936
A21: 45236 | B21: Transferência entre contas | C21: TRANSPORTADORA TURISTICA BENFICA S.A | E21: 5800 | F21: =D21-E21+F20 -> 3257136
A22: 45237 | B22: Transferência entre contas | C22: TRANSPORTADORA TURISTICA BENFICA S.A | E22: 12000 | F22: =D22-E22+F21 -> 3245136
A23: 45238 | B23: Crédito em conta | C23: PATRIMONY ADMINISTRADORA DE BENS AS | D23: 152544 | F23: =D23-E23+F22 -> 3397680
A24: 45238 | B24: Gestão de caixa | E24: =(D23*0.005)+10 -> 772.72 | F24: =D24-E24+F23 -> 3396907.3
A25: 45238 | B25: Crédito em conta | C25: GUARIROBA BIOENERGIA LTDA | D25: 74445.38 | F25: =D25-E25+F24 -> 3471352.7
A26: 45238 | B26: Gestão de caixa | E26: =(D25*0.005)+10 -> 382.2269 | F26: =D26-E26+F25 -> 3470970.4
A27: 45238 | B27: Crédito em conta | C27: MOEMA BIOENERGIA S A | D27: 179372.93 | F27: =D27-E27+F26 -> 3650343.4
A28: 45238 | B28: Gestão de caixa | E28: =(D27*0.005)+10 -> 906.86465 | F28: =D28-E28+F27 -> 3649436.5
A29: 45239 | B29: Crédito em conta | C29: OUROESTE BIOENERGIA LTDA | D29: 11660.46 | F29: =D29-E29+F28 -> 3661097
A30: 45239 | B30: Gestão de caixa | E30: =(D29*0.005)+10 -> 68.3023 | F30: =D30-E30+F29 -> 3661028.6
A31: 45240 | B31: Crédito em conta | C31: SANCETUR - SANTA CECILIA TURISMO LTDA | D31: 12000 | F31: =D31-E31+F30 -> 3673028.6
A32: 45240 | B32: Gestão de caixa | E32: =(D31*0.005)+10 -> 70 | F32: =D32-E32+F31 -> 3672958.6
A33: 45240 | B33: Transferência entre contas | C33: TRANSPORTADORA TURISTICA BENFICA S.A | E33: 103000 | F33: =D33-E33+F32 -> 3569958.6
A34: 45244 | B34: Transferência entre contas | C34: TRANSPORTADORA TURISTICA BENFICA S.A | E34: 7000 | F34: =D34-E34+F33 -> 3562958.6
A35: 45246 | B35: Crédito em conta | C35: TED Recebida | D35: 8.77 | F35: =D35-E35+F34 -> 3562967.4
A36: 45246 | B36: Gestão de caixa | E36: =(D35*0.005)+10 -> 10.04385 | F36: =D36-E36+F35 -> 3562957.4
A37: 45247 | B37: Transferência entre contas | C37: TRANSPORTADORA TURISTICA BENFICA S.A | E37: 54000 | F37: =D37-E37+F36 -> 3508957.4
A38: 45247 | B38: Ajuste de Saldo | D38: 0.01 | F38: =D38-E38+F37 -> 3508957.4
A39: 45247 | B39: Transferência entre contas | C39: TRANSPORTADORA TURISTICA BENFICA S.A | E39: 1000 | F39: =D39-E39+F38 -> 3507957.4
A40: 45250 | B40: Crédito em conta | C40: ARENA FUTIBA II | D40: 10707.01 | F40: =D40-E40+F39 -> 3518664.4
A41: 45250 | B41: Gestão de caixa | E41: =(D40*0.005)+10 -> 63.53505 | F41: =D41-E41+F40 -> 3518600.9
A42: 45251 | B42: Transferência entre contas | C42: TRANSPORTADORA TURISTICA BENFICA S.A | E42: 81000 | F42: =D42-E42+F41 -> 3437600.9
A43: 45251 | B43: Crédito em conta | C43: SCATENA AGENCIA DE VIAGENS E TURISMO LTDA | D43: 7000 | F43: =D43-E43+F42 -> 3444600.9
A44: 45251 | B44: Gestão de caixa | E44: =(D43*0.005)+10 -> 45 | F44: =D44-E44+F43 -> 3444555.9
A45: 45253 | B45: Crédito em conta | C45: AGROCANA A N H LTDA | D45: 8000 | F45: =D45-E45+F44 -> 3452555.9
A46: 45253 | B46: Gestão de caixa | E46: =(D45*0.005)+10 -> 50 | F46: =D46-E46+F45 -> 3452505.9
A47: 45253 | B47: Crédito em conta | C47: SILVA & BEGHINI COMERCIO DE ONIBUS LTDA | D47: 20000 | F47: =D47-E47+F46 -> 3472505.9
A48: 45253 | B48: Gestão de caixa | E48: =(D47*0.005)+10 -> 110 | F48: =D48-E48+F47 -> 3472395.9
A49: 45254 | B49: Crédito em conta | C49: UNIVERSAL TURISMO LTDA-EPP | D49: 4500 | F49: =D49-E49+F48 -> 3476895.9
A50: 45254 | B50: Gestão de caixa | E50: =(D49*0.005)+10 -> 32.5 | F50: =D50-E50+F49 -> 3476863.4
A51: 45257 | B51: Crédito em conta | C51: TRANSPORTADORA TURIST SUZANO LTDA | D51: 31003.13 | F51: =D51-E51+F50 -> 3507866.5
A52: 45257 | B52: Gestão de caixa | E52: =(D51*0.005)+10 -> 165.01565 | F52: =D52-E52+F51 -> 3507701.5
A53: 45257 | B53: Transferência entre contas | C53: TRANSPORTADORA TURISTICA BENFICA S.A | E53: 21000 | F53: =D53-E53+F52 -> 3486701.5
A54: 45257 | B54: Transferência entre contas | C54: TRANSPORTADORA TURISTICA BENFICA S.A | E54: 6500 | F54: =D54-E54+F53 -> 3480201.5
A55: 45257 | B55: Crédito em conta | C55: TRANSPORTADORA TURISTICA BENFICA S.A | D55: 7243 | F55: =D55-E55+F54 -> 3487444.5
A56: 45257 | B56: Gestão de caixa | E56: =(D55*0.005)+10 -> 46.215 | F56: =D56-E56+F55 -> 3487398.3
A57: 45258 | B57: Transferência entre contas | C57: TRANSPORTADORA TURISTICA BENFICA S.A | E57: 1000 | F57: =D57-E57+F56 -> 3486398.3
A58: 45258 | B58: Transferência entre contas | C58: TRANSPORTADORA TURISTICA BENFICA S.A | E58: 10800 | F58: =D58-E58+F57 -> 3475598.3
A59: 45260 | B59: Transferência entre contas | C59: TRANSPORTADORA TURISTICA BENFICA S.A | E59: 164000 | F59: =D59-E59+F58 -> 3311598.3
A60: 45260 | B60: Transferência entre contas | C60: TRANSPORTADORA TURISTICA BENFICA S.A | E60: 1000 | F60: =D60-E60+F59 -> 3310598.3
F61: =D61-E61+F60 -> 3310598.3
F62: =D62-E62+F61 -> 3310598.3
F63: =D63-E63+F62 -> 3310598.3
F64: =D64-E64+F63 -> 3310598.3
F65: =D65-E65+F64 -> 3310598.3
F66: =D66-E66+F65 -> 3310598.3
F67: =D67-E67+F66 -> 3310598.3
F68: =D68-E68+F67 -> 3310598.3
F69: =D69-E69+F68 -> 3310598.3
F70: =D70-E70+F69 -> 3310598.3
F71: =D71-E71+F70 -> 3310598.3
F72: =D72-E72+F71 -> 3310598.3
... F609: =D609-E609+F608 -> 3310598.3

Sheet Dezembro2023
A2: EXTRATO DE MOVIMENTAÇÃO
A4: Banco | B4: LEPTA BANK (274) | C4: Agência | D4: 1 | E4: Conta | F4: 08198095-5
A5: Empresa | B5: TRANSP. TURISTICA BENFICA S.A | C5: Saldo Anterior | D5: =Novembro2023!F6 -> 3310598.3 | F5: Saldo Disponível
A6: CNPJ | B6: 59.275.289/0001-02 | C6: Totais (Entradas/Saídas) | D6: =SUM(D9:D609) -> 570482.81 | E6: =SUM(E9:E609) -> 655072.43 | F6: =F609 -> 3226008.6
A8: Data | B8: Histórico | C8: Complemento | D8: Créditos | E8: Débitos | F8: Saldo
A9: 45261 | B9: Tarifa de manutenção de conta | C9: TRANSPORTADORA TURISTICA BENFICA S.A - (Vinculada) | E9: 1500 | F9: =D9-E9+D5 -> 3309098.3
A10: 45261 | B10: Tarifa de manutenção da conta | C10: TED's, PIX e demais | E10: 320 | F10: =D10-E10+F9 -> 3308778.3
A11: 45264 | B11: Transferência entre contas | C11: TRANSPORTADORA TURISTICA BENFICA S.A | E11: 108000 | F11: =D11-E11+F10 -> 3200778.3
A12: 45264 | B12: Transferência entre contas | C12: TRANSPORTADORA TURISTICA BENFICA S.A | E12: 14000 | F12: =D12-E12+F11 -> 3186778.3
A13: 45267 | B13: Crédito em conta | C13: BB TRANSPORTE E TURISMO LTDA | D13: 90000 | F13: =D13-E13+F12 -> 3276778.3
A14: 45267 | B14: Gestão de caixa | E14: =(D13*0.005)+10 -> 460 | F14: =D14-E14+F13 -> 3276318.3
A15: 45267 | B15: Crédito em conta | C15: JOSE APARECIDO MENDES RAMOS | D15: 40000 | F15: =D15-E15+F14 -> 3316318.3
A16: 45267 | B16: Gestão de caixa | E16: =(D15*0.005)+10 -> 210 | F16: =D16-E16+F15 -> 3316108.3
A17: 45267 | B17: Transferência entre contas | C17: TRANSPORTADORA TURISTICA BENFICA S.A | E17: 31500 | F17: =D17-E17+F16 -> 3284608.3
A18: 45267 | B18: Transferência entre contas | C18: TRANSPORTADORA TURISTICA BENFICA S.A | E18: 3100 | F18: =D18-E18+F17 -> 3281508.3
A19: 45268 | B19: Ajuste de saldo | E19: 0.01 | F19: =D19-E19+F18 -> 3281508.2
A20: 45271 | B20: Transferência entre contas | C20: TRANSPORTADORA TURISTICA BENFICA S.A | E20: 77500 | F20: =D20-E20+F19 -> 3204008.2
A21: 45271 | B21: Transferência entre contas | C21: TRANSPORTADORA TURISTICA BENFICA S.A | E21: 2000 | F21: =D21-E21+F20 -> 3202008.2
A22: 45271 | B22: Crédito em conta | C22: SANCETUR - SANTA CECILIA TURISMO LTDA | D22: 6000 | F22: =D22-E22+F21 -> 3208008.2
A23: 45271 | B23: Gestão de caixa | E23: =(D22*0.005)+10 -> 40 | F23: =D23-E23+F22 -> 3207968.2
A24: 45272 | B24: Crédito em conta | C24: TRANSPORTADORA TUR BENFICA S A | D24: 161129.59 | F24: =D24-E24+F23 -> 3369097.8
A25: 45272 | B25: Gestão de caixa | E25: =(D24*0.005)+10 -> 815.64795 | F25: =D25-E25+F24 -> 3368282.2
A26: 45272 | B26: Tarifa de manutenção de conta | C26: TRANSPORTADORA TURISTICA BENFICA S.A - (Empresa) | E26: 1500 | F26: =D26-E26+F25 -> 3366782.2
A27: 45275 | B27: Crédito em conta | C27: TRANSPORTADORA TURISTICA BENFICA S.A | D27: 3500 | F27: =D27-E27+F26 -> 3370282.2
A28: 45275 | B28: Gestão de caixa | E28: =(D27*0.005)+10 -> 27.5 | F28: =D28-E28+F27 -> 3370254.7
A29: 45275 | B29: Crédito em conta | C29: TRANSPORTADORA TURISTICA BENFICA S.A | D29: 3000 | F29: =D29-E29+F28 -> 3373254.7
A30: 45275 | B30: Gestão de caixa | E30: =(D29*0.005)+10 -> 25 | F30: =D30-E30+F29 -> 3373229.7
A31: 45275 | B31: Crédito em conta | C31: ALESSANDRO R DOS SANTOS AGRICOLA E TRANSPORTE | D31: 7000 | F31: =D31-E31+F30 -> 3380229.7
A32: 45275 | B32: Gestão de caixa | E32: =(D31*0.005)+10 -> 45 | F32: =D32-E32+F31 -> 3380184.7
A33: 45275 | B33: Transferência entre contas | C33: TRANSPORTADORA TURISTICA BENFICA S.A | E33: 69000 | F33: =D33-E33+F32 -> 3311184.7
A34: 45275 | B34: Crédito em conta | C34: SCATENA AGENCIA DE VIAGENS E TURISMO LTDA | D34: 7000 | F34: =D34-E34+F33 -> 3318184.7
A35: 45275 | B35: Gestão de caixa | E35: =(D34*0.005)+10 -> 45 | F35: =D35-E35+F34 -> 3318139.7
A36: 45278 | B36: Crédito em conta | C36: DOCINI PROMOCAO DE VENDAS LTDA | D36: 24000 | F36: =D36-E36+F35 -> 3342139.7
A37: 45278 | B37: Gestão de caixa | E37: =(D36*0.005)+10 -> 130 | F37: =D37-E37+F36 -> 3342009.7
A38: 45278 | B38: Transferência entre contas | C38: TRANSPORTADORA TURISTICA BENFICA S.A | E38: 96000 | F38: =D38-E38+F37 -> 3246009.7
A39: 45278 | B39: Transferência entre contas | C39: TRANSPORTADORA TURISTICA BENFICA S.A | E39: 17000 | F39: =D39-E39+F38 -> 3229009.7
A40: 45279 | B40: Crédito em conta | C40: CELMA LINA DE ARAUJO ALMEIDA | D40: 20610 | F40: =D40-E40+F39 -> 3249619.7
A41: 45279 | B41: Gestão de caixa | E41: =(D40*0.005)+10 -> 113.05 | F41: =D41-E41+F40 -> 3249506.6
A42: 45279 | B42: Crédito em conta | C42: CELMA LINA DE ARAUJO ALMEIDA | D42: 3890 | F42: =D42-E42+F41 -> 3253396.6
A43: 45279 | B43: Gestão de caixa | E43: =(D42*0.005)+10 -> 29.45 | F43: =D43-E43+F42 -> 3253367.2
A44: 45279 | B44: Crédito em conta | C44: MERCABENCO MERCANTIL A. B. C. LTDA | D44: 8267.57 | F44: =D44-E44+F43 -> 3261634.8
A45: 45279 | B45: Gestão de caixa | E45: =(D44*0.005)+10 -> 51.33785 | F45: =D45-E45+F44 -> 3261583.4
A46: 45279 | B46: Crédito em conta | C46: AGROTERRA SERVICOS AGRICOLAS NOVO HORIZONTE LTDA | D46: 9000 | F46: =D46-E46+F45 -> 3270583.4
A47: 45279 | B47: Gestão de caixa | E47: =(D46*0.005)+10 -> 55 | F47: =D47-E47+F46 -> 3270528.4
A48: 45279 | B48: Crédito em conta | C48: AGROTERRA SERVICOS AGRICOLAS NOVO HORIZONTE LTDA | D48: 4500 | F48: =D48-E48+F47 -> 3275028.4
A49: 45279 | B49: Gestão de caixa | E49: =(D48*0.005)+10 -> 32.5 | F49: =D49-E49+F48 -> 3274995.9
A50: 45279 | B50: Crédito em conta | C50: MERCABENCO MERCANTIL A. B. C. LTDA | D50: 3550.15 | F50: =D50-E50+F49 -> 3278546.1
A51: 45279 | B51: Gestão de caixa | E51: =(D50*0.005)+10 -> 27.75075 | F51: =D51-E51+F50 -> 3278518.3
A52: 45279 | B52: Crédito em conta | C52: MERCABENCO MERCANTIL A. B. C. LTDA | D52: 2944.1 | F52: =D52-E52+F51 -> 3281462.4
A53: 45279 | B53: Gestão de caixa | E53: =(D52*0.005)+10 -> 24.7205 | F53: =D53-E53+F52 -> 3281437.7
A54: 45279 | B54: Crédito em conta | C54: MERCABENCO MERCANTIL A. B. C. LTDA | D54: 3355.7 | F54: =D54-E54+F53 -> 3284793.4
A55: 45279 | B55: Gestão de caixa | E55: =(D54*0.005)+10 -> 26.7785 | F55: =D55-E55+F54 -> 3284766.6
A56: 45279 | B56: Crédito em conta | C56: MERCABENCO MERCANTIL A. B. C. LTDA | D56: 3325.92 | F56: =D56-E56+F55 -> 3288092.5
A57: 45279 | B57: Gestão de caixa | E57: =(D56*0.005)+10 -> 26.6296 | F57: =D57-E57+F56 -> 3288065.9
A58: 45279 | B58: Crédito em conta | C58: MERCABENCO MERCANTIL A. B. C. LTDA | D58: 3165.6 | F58: =D58-E58+F57 -> 3291231.5
A59: 45279 | B59: Gestão de caixa | E59: =(D58*0.005)+10 -> 25.828 | F59: =D59-E59+F58 -> 3291205.7
A60: 45279 | B60: Ajuste de saldo | E60: 0.01 | F60: =D60-E60+F59 -> 3291205.7
A61: 45280 | B61: Crédito em conta | C61: ARENA FUTIBA II | D61: 10707.01 | F61: =D61-E61+F60 -> 3301912.7
A62: 45280 | B62: Gestão de caixa | E62: =(D61*0.005)+10 -> 63.53505 | F62: =D62-E62+F61 -> 3301849.2
A63: 45280 | B63: Crédito em conta | C63: MERCABENCO MERCANTIL A. B. C. LTDA | D63: 9320.83 | F63: =D63-E63+F62 -> 3311170
A64: 45280 | B64: Gestão de caixa | E64: =(D63*0.005)+10 -> 56.60415 | F64: =D64-E64+F63 -> 3311113.4
A65: 45280 | B65: Crédito em conta | C65: MERCABENCO MERCANTIL A. B. C. LTDA | D65: 18338.27 | F65: =D65-E65+F64 -> 3329451.6
A66: 45280 | B66: Gestão de caixa | E66: =(D65*0.005)+10 -> 101.69135 | F66: =D66-E66+F65 -> 3329350
A67: 45280 | B67: Crédito em conta | C67: MERCABENCO MERCANTIL A. B. C. LTDA | D67: 8877.77 | F67: =D67-E67+F66 -> 3338227.7
A68: 45280 | B68: Gestão de caixa | E68: =(D67*0.005)+10 -> 54.38885 | F68: =D68-E68+F67 -> 3338173.3
A69: 45280 | B69: Crédito em conta | C69: MERCABENCO MERCANTIL A. B. C. LTDA | D69: 23009.84 | F69: =D69-E69+F68 -> 3361183.2
A70: 45280 | B70: Gestão de caixa | E70: =(D69*0.005)+10 -> 125.0492 | F70: =D70-E70+F69 -> 3361058.1
A71: 45280 | B71: Crédito em conta | C71: MERCABENCO MERCANTIL A. B. C. LTDA | D71: 17385.81 | F71: =D71-E71+F70 -> 3378443.9
A72: 45280 | B72: Gestão de caixa | E72: =(D71*0.005)+10 -> 96.92905 | F72: =D72-E72+F71 -> 3378347
A73: 45280 | B73: Crédito em conta | C73: MERCABENCO MERCANTIL A. B. C. LTDA | D73: 13365.46 | F73: =D73-E73+F72 -> 3391712.5
A74: 45280 | B74: Gestão de caixa | E74: =(D73*0.005)+10 -> 76.8273 | F74: =D74-E74+F73 -> 3391635.6
A75: 45280 | B75: Transferência entre contas | C75: TRANSPORTADORA TURISTICA BENFICA S.A | E75: 38000 | F75: =D75-E75+F74 -> 3353635.6
A76: 45280 | B76: Ajuste de saldo | D76: 0.01 | F76: =D76-E76+F75 -> 3353635.7
A77: 45282 | B77: Transferência entre contas | C77: TRANSPORTADORA TURISTICA BENFICA S.A | E77: 42000 | F77: =D77-E77+F76 -> 3311635.7
A78: 45286 | B78: Crédito em conta | C78: METAL 2 INDUSTRIA E COMERCIO LTDA | D78: 10154.35 | F78: =D78-E78+F77 -> 3321790
A79: 45286 | B79: Gestão de caixa | E79: =(D78*0.005)+10 -> 60.77175 | F79: =D79-E79+F78 -> 3321729.2
A80: 45286 | B80: Crédito em conta | C80: TRANSPORTADORA TURISTICA BENFICA S.A | D80: 23000 | F80: =D80-E80+F79 -> 3344729.2
A81: 45286 | B81: Gestão de caixa | E81: =(D80*0.005)+10 -> 125 | F81: =D81-E81+F80 -> 3344604.2
A82: 45287 | B82: Crédito em conta | C82: TRANSPORTADORA TURIST SUZANO LTDA | D82: 31003.13 | F82: =D82-E82+F81 -> 3375607.4
A83: 45287 | B83: Gestão de caixa | E83: =(D82*0.005)+10 -> 165.01565 | F83: =D83-E83+F82 -> 3375442.3
A84: 45288 | B84: Transferência entre contas | C84: TRANSPORTADORA TURISTICA BENFICA S.A | E84: 150500 | F84: =D84-E84+F83 -> 3224942.3
A85: 45289 | B85: Crédito em conta | C85: TRANSPORTADORA TURISTICA BENFICA S.A | D85: 1081.7 | F85: =D85-E85+F84 -> 3226024
A86: 45289 | B86: Gestão de caixa | E86: =(D85*0.005)+10 -> 15.4085 | F86: =D86-E86+F85 -> 3226008.6
F87: =D87-E87+F86 -> 3226008.6
F88: =D88-E88+F87 -> 3226008.6
F89: =D89-E89+F88 -> 3226008.6
F90: =D90-E90+F89 -> 3226008.6
F91: =D91-E91+F90 -> 3226008.6
F92: =D92-E92+F91 -> 3226008.6
F93: =D93-E93+F92 -> 3226008.6
F94: =D94-E94+F93 -> 3226008.6
F95: =D95-E95+F94 -> 3226008.6
F96: =D96-E96+F95 -> 3226008.6
F97: =D97-E97+F96 -> 3226008.6
F98: =D98-E98+F97 -> 3226008.6
... F609: =D609-E609+F608 -> 3226008.6

Sheet Janeiro2024
A2: EXTRATO DE MOVIMENTAÇÃO
A4: Banco | B4: LEPTA BANK (274) | C4: Agência | D4: 1 | E4: Conta | F4: 08198095-5
A5: Empresa | B5: TRANSP. TURISTICA BENFICA S.A | C5: Saldo Anterior | D5: =Dezembro2023!F6 -> 3226008.6 | F5: Saldo Disponível
A6: CNPJ | B6: 59.275.289/0001-02 | C6: Totais (Entradas/Saídas) | D6: =SUM(D9:D609) -> 416748.21 | E6: =SUM(E9:E609) -> 710773.75 | F6: =F609 -> 2931983.1
A8: Data | B8: Histórico | C8: Complemento | D8: Créditos | E8: Débitos | F8: Saldo
A9: 45292 | B9: Tarifa de manutenção de conta | C9: TRANSPORTADORA TURISTICA BENFICA S.A - (Vinculada) | E9: 1500 | F9: =D9-E9+D5 -> 3224508.6
A10: 45292 | B10: Tarifa de manutenção da conta | C10: TED's, PIX e demais | E10: 240 | F10: =D10-E10+F9 -> 3224268.6
A11: 45295 | B11: Transferência entre contas | C11: TRANSPORTADORA TURISTICA BENFICA S.A | E11: 201200 | F11: =D11-E11+F10 -> 3023068.6
A12: 45295 | B12: Transferência entre contas | C12: TRANSPORTADORA TURISTICA BENFICA S.A | E12: 7100 | F12: =D12-E12+F11 -> 3015968.6
A13: 45295 | B13: Transferência entre contas | C13: TRANSPORTADORA TURISTICA BENFICA S.A | E13: 1500 | F13: =D13-E13+F12 -> 3014468.6
A14: 45299 | B14: Crédito em conta | C14: BB TRANSPORTE E TURISMO LTDA | D14: 90000 | F14: =D14-E14+F13 -> 3104468.6
A15: 45299 | B15: Gestão de caixa | E15: =(D14*0.005)+10 -> 460 | F15: =D15-E15+F14 -> 3104008.6
A16: 45299 | B16: Crédito em conta | C16: PATRIMONY ADMINISTRADORA DE BENS AS | D16: 159617.63 | F16: =D16-E16+F15 -> 3263626.3
A17: 45299 | B17: Gestão de caixa | E17: =(D16*0.005)+10 -> 808.08815 | F17: =D17-E17+F16 -> 3262818.2
A18: 45301 | B18: Transferência entre contas | C18: TRANSPORTADORA TURISTICA BENFICA S.A | E18: 83500 | F18: =D18-E18+F17 -> 3179318.2
A19: 45301 | B19: Tarifa de manutenção de conta | C19: TRANSPORTADORA TURISTICA BENFICA S.A - (Empresa) | E19: 1500 | F19: =D19-E19+F18 -> 3177818.2
A20: 45301 | B20: Crédito em conta | C20: SANCETUR SANTA CECILIA TURISMO LTDA | D20: 6000 | F20: =D20-E20+F19 -> 3183818.2
A21: 45301 | B21: Gestão de caixa | E21: =(D20*0.005)+10 -> 40 | F21: =D21-E21+F20 -> 3183778.2
A22: 45302 | B22: Transferência entre contas | C22: TRANSPORTADORA TURISTICA BENFICA S.A | E22: 4000 | F22: =D22-E22+F21 -> 3179778.2
A23: 45302 | B23: Ajuste de Saldo | E23: 0.01 | F23: =D23-E23+F22 -> 3179778.2
A24: 45306 | B24: Transferência entre contas | C24: TRANSPORTADORA TURISTICA BENFICA S.A | E24: 47000 | F24: =D24-E24+F23 -> 3132778.2
A25: 45307 | B25: Transferência entre contas | C25: TRANSPORTADORA TURISTICA BENFICA S.A | E25: 1000 | F25: =D25-E25+F24 -> 3131778.2
A26: 45307 | B26: Crédito em conta | C26: CELMA LINA DE ARAUJO ALMEIDA | D26: 4500 | F26: =D26-E26+F25 -> 3136278.2
A27: 45307 | B27: Gestão de caixa | E27: =(D26*0.005)+10 -> 32.5 | F27: =D27-E27+F26 -> 3136245.7
A28: 45309 | B28: Transferência entre contas | C28: TRANSPORTADORA TURISTICA BENFICA S.A | E28: 1000 | F28: =D28-E28+F27 -> 3135245.7
A29: 45309 | B29: Transferência entre contas | C29: TRANSPORTADORA TURISTICA BENFICA S.A | E29: 146100 | F29: =D29-E29+F28 -> 2989145.7
A30: 45309 | B30: Transferência entre contas | C30: TRANSPORTADORA TURISTICA BENFICA S.A | E30: 9500 | F30: =D30-E30+F29 -> 2979645.7
A31: 45311 | B31: Crédito em conta | C31: ARENA FUTIBA II | D31: 10707.01 | F31: =D31-E31+F30 -> 2990352.7
A32: 45311 | B32: Gestão de caixa | E32: =(D31*0.005)+10 -> 63.53505 | F32: =D32-E32+F31 -> 2990289.1
A33: 45313 | B33: Crédito em conta | C33: TRANSPORTADORA TURISTICA BENFICA S.A | D33: 16000 | F33: =D33-E33+F32 -> 3006289.1
A34: 45313 | B34: Gestão de caixa | E34: =(D33*0.005)+10 -> 90 | F34: =D34-E34+F33 -> 3006199.1
A35: 45313 | B35: Crédito em conta | C35: TRANSPORTADORA TURISTICA BENFICA AS | D35: 1400 | F35: =D35-E35+F34 -> 3007599.1
A36: 45313 | B36: Gestão de caixa | E36: =(D35*0.005)+10 -> 17 | F36: =D36-E36+F35 -> 3007582.1
A37: 45314 | B37: Transferência entre contas | C37: TRANSPORTADORA TURISTICA BENFICA S.A | E37: 4800 | F37: =D37-E37+F36 -> 3002782.1
A38: 45316 | B38: Crédito em conta | C38: METAL 2 INDUSTRIA E COMERCIO LTDA | D38: 10252.51 | F38: =D38-E38+F37 -> 3013034.7
A39: 45316 | B39: Gestão de caixa | E39: =(D38*0.005)+10 -> 61.26255 | F39: =D39-E39+F38 -> 3012973.4
A40: 45316 | B40: Transferência entre contas | C40: TRANSPORTADORA TURISTICA BENFICA S.A | E40: 24000 | F40: =D40-E40+F39 -> 2988973.4
A41: 45316 | B41: Transferência entre contas | C41: TRANSPORTADORA TURISTICA BENFICA S.A | E41: 7200 | F41: =D41-E41+F40 -> 2981773.4
A42: 45317 | B42: Crédito em conta | C42: DOCINI PROMOCAO DE VENDAS LTDA | D42: 600 | F42: =D42-E42+F41 -> 2982373.4
A43: 45317 | B43: Gestão de caixa | E43: =(D42*0.005)+10 -> 13 | F43: =D43-E43+F42 -> 2982360.4
A44: 45317 | B44: Transferência entre contas | C44: TRANSPORTADORA TURISTICA BENFICA S.A | E44: 8000 | F44: =D44-E44+F43 -> 2974360.4
A45: 45320 | B45: Crédito em conta | C45: TRANSPORTADORA TURISTICA BENFICA S.A | D45: 26000 | F45: =D45-E45+F44 -> 3000360.4
A46: 45320 | B46: Gestão de caixa | E46: =(D45*0.005)+10 -> 140 | F46: =D46-E46+F45 -> 3000220.4
A47: 45320 | B47: Crédito em conta | C47: JOANA MARIA DA COSTA SILV | D47: 39020 | F47: =D47-E47+F46 -> 3039240.4
A48: 45320 | B48: Gestão de caixa | E48: =(D47*0.005)+10 -> 205.1 | F48: =D48-E48+F47 -> 3039035.3
A49: 45320 | B49: Crédito em conta | C49: TRANSPORTADORA TURIST SUZANO LTDA | D49: 31003.13 | F49: =D49-E49+F48 -> 3070038.4
A50: 45320 | B50: Gestão de caixa | E50: =(D49*0.005)+10 -> 165.01565 | F50: =D50-E50+F49 -> 3069873.4
A51: 45321 | B51: Crédito em conta | C51: JOANA MARIA DA COSTA SILV | D51: 10000 | F51: =D51-E51+F50 -> 3079873.4
A52: 45321 | B52: Gestão de caixa | E52: =(D51*0.005)+10 -> 60 | F52: =D52-E52+F51 -> 3079813.4
A53: 45321 | B53: Crédito em conta | C53: JOANA MARIA DA COSTA SILV | D53: 10980 | F53: =D53-E53+F52 -> 3090793.4
A54: 45321 | B54: Gestão de caixa | E54: =(D53*0.005)+10 -> 64.9 | F54: =D54-E54+F53 -> 3090728.5
A55: 45321 | B55: Transferência entre contas | C55: TRANSPORTADORA TURISTICA BENFICA S.A | E55: 144800 | F55: =D55-E55+F54 -> 2945928.5
A56: 45321 | B56: Transferência entre contas | C56: TRANSPORTADORA TURISTICA BENFICA S.A | E56: 2000 | F56: =D56-E56+F55 -> 2943928.5
A57: 45322 | B57: Crédito em conta | C57: TRANSPORTADORA TURISTICA BENFICA AS | D57: 667.93 | F57: =D57-E57+F56 -> 2944596.4
A58: 45322 | B58: Gestão de caixa | E58: =(D57*0.005)+10 -> 13.33965 | F58: =D58-E58+F57 -> 2944583.1
A59: 45322 | B59: Transferência entre contas | C59: TRANSPORTADORA TURISTICA BENFICA S.A | E59: 12000 | F59: =D59-E59+F58 -> 2932583.1
A60: 45322 | B60: Transferência entre contas | C60: TRANSPORTADORA TURISTICA BENFICA S.A | E60: 600 | F60: =D60-E60+F59 -> 2931983.1
F61: =D61-E61+F60 -> 2931983.1
F62: =D62-E62+F61 -> 2931983.1
F63: =D63-E63+F62 -> 2931983.1
F64: =D64-E64+F63 -> 2931983.1
F65: =D65-E65+F64 -> 2931983.1
F66: =D66-E66+F65 -> 2931983.1
F67: =D67-E67+F66 -> 2931983.1
F68: =D68-E68+F67 -> 2931983.1
F69: =D69-E69+F68 -> 2931983.1
F70: =D70-E70+F69 -> 2931983.1
F71: =D71-E71+F70 -> 2931983.1
F72: =D72-E72+F71 -> 2931983.1
... F609: =D609-E609+F608 -> 2931983.1

Sheet Fevereiro2024
A2: EXTRATO DE MOVIMENTAÇÃO
A4: Banco | B4: LEPTA BANK (274) | C4: Agência | D4: 1 | E4: Conta | F4: 08198095-5
A5: Empresa | B5: TRANSP. TURISTICA BENFICA S.A | C5: Saldo Anterior | D5: =Janeiro2024!F6 -> 2931983.1 | F5: Saldo Disponível
A6: CNPJ | B6: 59.275.289/0001-02 | C6: Totais (Entradas/Saídas) | D6: =SUM(D9:D609) -> 838086.9 | E6: =SUM(E9:E609) -> 425210.44 | F6: =F609 -> 3344859.5
A8: Data | B8: Histórico | C8: Complemento | D8: Créditos | E8: Débitos | F8: Saldo
A9: 45323 | B9: Crédito em conta | C9: AGROTERRA SERVICOS AGRICOLAS NOVO HORIZONTE LTDA | D9: 5000 | F9: =D9-E9+D5 -> 2936983.1
A10: 45323 | B10: Gestão de caixa | E10: =(D9*0.005)+10 -> 35 | F10: =D10-E10+F9 -> 2936948.1
A11: 45323 | B11: Crédito em conta | C11: AGROTERRA SERVICOS AGRICOLAS NOVO HORIZONTE LTDA | D11: 14000 | F11: =D11-E11+F10 -> 2950948.1
A12: 45323 | B12: Gestão de caixa | E12: =(D11*0.005)+10 -> 80 | F12: =D12-E12+F11 -> 2950868.1
A13: 45323 | B13: Crédito em conta | C13: AGROTERRA SERVICOS AGRICOLAS NOVO HORIZONTE LTDA | D13: 4500 | F13: =D13-E13+F12 -> 2955368.1
A14: 45323 | B14: Gestão de caixa | E14: =(D13*0.005)+10 -> 32.5 | F14: =D14-E14+F13 -> 2955335.6
A15: 45323 | B15: Crédito em conta | C15: AGROTERRA SERVICOS AGRICOLAS NOVO HORIZONTE LTDA | D15: 9000 | F15: =D15-E15+F14 -> 2964335.6
A16: 45323 | B16: Gestão de caixa | E16: =(D15*0.005)+10 -> 55 | F16: =D16-E16+F15 -> 2964280.6
A17: 45323 | B17: Tarifa de manutenção de conta | C17: TRANSPORTADORA TURISTICA BENFICA S.A - (Vinculada) | E17: 1500 | F17: =D17-E17+F16 -> 2962780.6
A18: 45323 | B18: Tarifa de manutenção da conta | C18: TED's, PIX e demais | E18: 360 | F18: =D18-E18+F17 -> 2962420.6
A19: 45324 | B19: Transferência entre contas | C19: TRANSPORTADORA TURISTICA BENFICA S.A | E19: 500 | F19: =D19-E19+F18 -> 2961920.6
A20: 45327 | B20: Transferência entre contas | C20: TRANSPORTADORA TURISTICA BENFICA S.A | E20: 174000 | F20: =D20-E20+F19 -> 2787920.6
A21: 45327 | B21: Transferência entre contas | C21: TRANSPORTADORA TURISTICA BENFICA S.A | E21: 13500 | F21: =D21-E21+F20 -> 2774420.6
A22: 45328 | B22: Tarifa de manutenção de conta | C22: TRANSPORTADORA TURISTICA BENFICA S.A - (Empresa) | E22: 1500 | F22: =D22-E22+F21 -> 2772920.6
A23: 45329 | B23: Crédito em conta | C23: MARLI APARECIDA PEREIRA DE SOUZA - ME | D23: 95000 | F23: =D23-E23+F22 -> 2867920.6
A24: 45329 | B24: Gestão de caixa | E24: =(D23*0.005)+10 -> 485 | F24: =D24-E24+F23 -> 2867435.6
A25: 45329 | B25: Crédito em conta | C25: MARLI APARECIDA PEREIRA DE SOUZA - ME | D25: 96000 | F25: =D25-E25+F24 -> 2963435.6
A26: 45329 | B26: Gestão de caixa | E26: =(D25*0.005)+10 -> 490 | F26: =D26-E26+F25 -> 2962945.6
A27: 45329 | B27: Crédito em conta | C27: TRANSPORTADORA TURISTICA BENFICA S.A | D27: 102500 | F27: =D27-E27+F26 -> 3065445.6
A28: 45329 | B28: Gestão de caixa | E28: =(D27*0.005)+10 -> 522.5 | F28: =D28-E28+F27 -> 3064923.1
A29: 45329 | B29: Crédito em conta | C29: RENATO FERREIRA LIMA | D29: 1000 | F29: =D29-E29+F28 -> 3065923.1
A30: 45329 | B30: Gestão de caixa | E30: =(D29*0.005)+10 -> 15 | F30: =D30-E30+F29 -> 3065908.1
A31: 45330 | B31: Crédito em conta | C31: BB TRANSPORTE E TURISMO LTDA | D31: 90000 | F31: =D31-E31+F30 -> 3155908.1
A32: 45330 | B32: Gestão de caixa | E32: =(D31*0.005)+10 -> 460 | F32: =D32-E32+F31 -> 3155448.1
A33: 45330 | B33: Crédito em conta | C33: PATRIMONY ADMINISTRADORA DE BENS AS | D33: 149586.79 | F33: =D33-E33+F32 -> 3305034.9
A34: 45330 | B34: Gestão de caixa | E34: =(D33*0.005)+10 -> 757.93395 | F34: =D34-E34+F33 -> 3304276.9
A35: 45330 | B35: Crédito em conta | C35: EXPRESSO V B TRANSPORTES E TURISMO LTDA | D35: 96000 | F35: =D35-E35+F34 -> 3400276.9
A36: 45330 | B36: Gestão de caixa | E36: =(D35*0.005)+10 -> 490 | F36: =D36-E36+F35 -> 3399786.9
A37: 45331 | B37: Transferência entre contas | C37: TRANSPORTADORA TURISTICA BENFICA S.A | E37: 85500 | F37: =D37-E37+F36 -> 3314286.9
A38: 45336 | B38: Crédito em conta | C38: CELMA LINA DE ARAUJO ALMEIDA | D38: 4500 | F38: =D38-E38+F37 -> 3318786.9
A39: 45336 | B39: Gestão de caixa | E39: =(D38*0.005)+10 -> 32.5 | F39: =D39-E39+F38 -> 3318754.4
A40: 45337 | B40: Crédito em conta | C40: PAULINHA TRANSPORTES LTDA | D40: 16199 | F40: =D40-E40+F39 -> 3334953.4
A41: 45337 | B41: Gestão de caixa | E41: =(D40*0.005)+10 -> 90.995 | F41: =D41-E41+F40 -> 3334862.5
A42: 45338 | B42: Transferência entre contas | C42: TRANSPORTADORA TURISTICA BENFICA S.A | E42: 700 | F42: =D42-E42+F41 -> 3334162.5
A43: 45338 | B43: Crédito em conta | C43: RODAR TRANSPORTES LTDA | D43: 4500 | F43: =D43-E43+F42 -> 3338662.5
A44: 45338 | B44: Gestão de caixa | E44: =(D43*0.005)+10 -> 32.5 | F44: =D44-E44+F43 -> 3338630
A45: 45338 | B45: Transferência entre contas | C45: TRANSPORTADORA TURISTICA BENFICA S.A | E45: 300 | F45: =D45-E45+F44 -> 3338330
A46: 45338 | B46: Transferência entre contas | C46: TRANSPORTADORA TURISTICA BENFICA S.A | E46: 400 | F46: =D46-E46+F45 -> 3337930
A47: 45338 | B47: Crédito em conta | C47: CARLOS HENRIQUE COSTA 12185585630 | D47: 8000 | F47: =D47-E47+F46 -> 3345930
A48: 45338 | B48: Gestão de caixa | E48: =(D47*0.005)+10 -> 50 | F48: =D48-E48+F47 -> 3345880
A49: 45338 | B49: Transferência entre contas | C49: TRANSPORTADORA TURISTICA BENFICA S.A | E49: 37800 | F49: =D49-E49+F48 -> 3308080
A50: 45338 | B50: Transferência entre contas | C50: TRANSPORTADORA TURISTICA BENFICA S.A | E50: 8700 | F50: =D50-E50+F49 -> 3299380
A51: 45338 | B51: Crédito em conta | C51: ALESSANDRO R DOS SANTOS AGRICOLA E TRANSPORTE | D51: 5000 | F51: =D51-E51+F50 -> 3304380
A52: 45338 | B52: Gestão de caixa | E52: =(D51*0.005)+10 -> 35 | F52: =D52-E52+F51 -> 3304345
A53: 45341 | B53: Crédito em conta | C53: MIRIA DIAS SILVEIRA TUCI | D53: 2200 | F53: =D53-E53+F52 -> 3306545
A54: 45341 | B54: Gestão de caixa | E54: =(D53*0.005)+10 -> 21 | F54: =D54-E54+F53 -> 3306524
A55: 45341 | B55: Crédito em conta | C55: ARD TRANSPORTES LTDA | D55: 10000 | F55: =D55-E55+F54 -> 3316524
A56: 45341 | B56: Gestão de caixa | E56: =(D55*0.005)+10 -> 60 | F56: =D56-E56+F55 -> 3316464
A57: 45342 | B57: Crédito em conta | D57: 1858.17 | F57: =D57-E57+F56 -> 3318322.1
A58: 45342 | B58: Gestão de caixa | E58: =(D57*0.005)+10 -> 19.29085 | F58: =D58-E58+F57 -> 3318302.8
A59: 45342 | B59: Transferência entre contas | C59: TRANSPORTADORA TURISTICA BENFICA S.A | E59: 72800 | F59: =D59-E59+F58 -> 3245502.8
A60: 45342 | B60: Transferência entre contas | C60: TRANSPORTADORA TURISTICA BENFICA S.A | E60: 100 | F60: =D60-E60+F59 -> 3245402.8
A61: 45343 | B61: Crédito em conta | C61: ARENA FUTIBA II | D61: 10900 | F61: =D61-E61+F60 -> 3256302.8
A62: 45343 | B62: Gestão de caixa | E62: =(D61*0.005)+10 -> 64.5 | F62: =D62-E62+F61 -> 3256238.3
A63: 45344 | B63: Crédito em conta | C63: AGROTERRA SERVICOS AGRICOLAS NOVO HORIZONTE LTDA | D63: 14000 | F63: =D63-E63+F62 -> 3270238.3
A64: 45344 | B64: Gestão de caixa | E64: =(D63*0.005)+10 -> 80 | F64: =D64-E64+F63 -> 3270158.3
A65: 45345 | B65: Crédito em conta | C65: LEVEN T F T EIRELI | D65: 50000 | F65: =D65-E65+F64 -> 3320158.3
A66: 45345 | B66: Gestão de caixa | E66: =(D65*0.005)+10 -> 260 | F66: =D66-E66+F65 -> 3319898.3
A67: 45345 | B67: Transferência entre contas | C67: TRANSPORTADORA TURISTICA BENFICA S.A | E67: 23100 | F67: =D67-E67+F66 -> 3296798.3
A68: 45345 | B68: Crédito em conta | C68: SCATENA AGENCIA DE VIAGENS E TURISMO LTDA | D68: 7000 | F68: =D68-E68+F67 -> 3303798.3
A69: 45345 | B69: Gestão de caixa | E69: =(D68*0.005)+10 -> 45 | F69: =D69-E69+F68 -> 3303753.3
A70: 45348 | B70: Crédito em conta | C70: METAL 2 INDUSTRIA E COMERCIO LTDA | D70: 10339.81 | F70: =D70-E70+F69 -> 3314093.1
A71: 45348 | B71: Gestão de caixa | E71: =(D70*0.005)+10 -> 61.69905 | F71: =D71-E71+F70 -> 3314031.4
A72: 45349 | B72: Crédito em conta | C72: TRANSPORTADORA TURIST SUZANO LTDA | D72: 31003.13 | F72: =D72-E72+F71 -> 3345034.6
A73: 45349 | B73: Gestão de caixa | E73: =(D72*0.005)+10 -> 165.01565 | F73: =D73-E73+F72 -> 3344869.6
A74: 45351 | B74: Transferência entre contas | C74: TRANSPORTADORA TURISTICA BENFICA S.A | E74: 10 | F74: =D74-E74+F73 -> 3344859.6
A75: 45351 | B75: Ajuste de Saldo | E75: 0.01 | F75: =D75-E75+F74 -> 3344859.5
F76: =D76-E76+F75 -> 3344859.5
F77: =D77-E77+F76 -> 3344859.5
F78: =D78-E78+F77 -> 3344859.5
F79: =D79-E79+F78 -> 3344859.5
F80: =D80-E80+F79 -> 3344859.5
F81: =D81-E81+F80 -> 3344859.5
F82: =D82-E82+F81 -> 3344859.5
F83: =D83-E83+F82 -> 3344859.5
F84: =D84-E84+F83 -> 3344859.5
F85: =D85-E85+F84 -> 3344859.5
F86: =D86-E86+F85 -> 3344859.5
F87: =D87-E87+F86 -> 3344859.5
... F609: =D609-E609+F608 -> 3344859.5

Sheet Março2024
A2: EXTRATO DE MOVIMENTAÇÃO
A4: Banco | B4: LEPTA BANK (274) | C4: Agência | D4: 1 | E4: Conta | F4: 08198095-5
A5: Empresa | B5: TRANSP. TURISTICA BENFICA S.A | C5: Saldo Anterior | D5: =Fevereiro2024!F6 -> 3344859.5 | F5: Saldo Disponível
A6: CNPJ | B6: 59.275.289/0001-02 | C6: Totais (Entradas/Saídas) | D6: =SUM(D9:D609) -> 732260.65 | E6: =SUM(E9:E609) -> 796911.3 | F6: =F609 -> 3280208.9
A8: Data | B8: Histórico | C8: Complemento | D8: Créditos | E8: Débitos | F8: Saldo
A9: 45352 | B9: Tarifa de manutenção de conta | C9: TRANSPORTADORA TURISTICA BENFICA S.A - (Vinculada) | E9: 1500 | F9: =D9-E9+D5 -> 3343359.5
A10: 45352 | B10: Tarifa de manutenção da conta | C10: TED's, PIX e demais | E10: 240 | F10: =D10-E10+F9 -> 3343119.5
A11: 45352 | B11: Transferência entre contas | C11: TRANSPORTADORA TURISTICA BENFICA S.A | E11: 2000 | F11: =D11-E11+F10 -> 3341119.5
A12: 45352 | B12: Transferência entre contas | C12: TRANSPORTADORA TURISTICA BENFICA S.A | E12: 10000 | F12: =D12-E12+F11 -> 3331119.5
A13: 45352 | B13: Transferência entre contas | C13: TRANSPORTADORA TURISTICA BENFICA S.A | E13: 25000 | F13: =D13-E13+F12 -> 3306119.5
A14: 45352 | B14: Transferência entre contas | C14: TRANSPORTADORA TURISTICA BENFICA S.A | E14: 325000 | F14: =D14-E14+F13 -> 2981119.5
A15: 45355 | B15: Transferência entre contas | C15: TRANSPORTADORA TURISTICA BENFICA S.A | E15: 10000 | F15: =D15-E15+F14 -> 2971119.5
A16: 45355 | B16: Crédito em conta | C16: AGROTERRA SERVICOS AGRICOLAS NOVO HORIZONTE LTDA | D16: 4500 | F16: =D16-E16+F15 -> 2975619.5
A17: 45355 | B17: Gestão de caixa | E17: =(D16*0.005)+10 -> 32.5 | F17: =D17-E17+F16 -> 2975587
A18: 45355 | B18: Crédito em conta | C18: AGROTERRA SERVICOS AGRICOLAS NOVO HORIZONTE LTDA | D18: 5000 | F18: =D18-E18+F17 -> 2980587
A19: 45355 | B19: Gestão de caixa | E19: =(D18*0.005)+10 -> 35 | F19: =D19-E19+F18 -> 2980552
A20: 45355 | B20: Crédito em conta | C20: AGROTERRA SERVICOS AGRICOLAS NOVO HORIZONTE LTDA | D20: 9000 | F20: =D20-E20+F19 -> 2989552
A21: 45355 | B21: Gestão de caixa | E21: =(D20*0.005)+10 -> 55 | F21: =D21-E21+F20 -> 2989497
A22: 45357 | B22: Transferência entre contas | C22: TRANSPORTADORA TURISTICA BENFICA S.A | E22: 600 | F22: =D22-E22+F21 -> 2988897
A23: 45357 | B23: Crédito em conta | C23: BB TRANSPORTE E TURISMO LTDA | D23: 90000 | F23: =D23-E23+F22 -> 3078897
A24: 45357 | B24: Gestão de caixa | E24: =(D23*0.005)+10 -> 460 | F24: =D24-E24+F23 -> 3078437
A25: 45358 | B25: Transferência entre contas | C25: TRANSPORTADORA TURISTICA BENFICA S.A | E25: 28200 | F25: =D25-E25+F24 -> 3050237
A26: 45359 | B26: Crédito em conta | C26: Gois e Rossi | D26: 40000 | F26: =D26-E26+F25 -> 3090237
A27: 45359 | B27: Gestão de caixa | E27: =(D26*0.005)+10 -> 210 | F27: =D27-E27+F26 -> 3090027
A28: 45359 | B28: Crédito em conta | C28: PATRIMONY ADMINISTRADORA DE BENS AS | D28: 149586.79 | F28: =D28-E28+F27 -> 3239613.8
A29: 45359 | B29: Gestão de caixa | E29: =(D28*0.005)+10 -> 757.93395 | F29: =D29-E29+F28 -> 3238855.9
A30: 45362 | B30: Transferência entre contas | C30: TRANSPORTADORA TURISTICA BENFICA S.A | E30: 63000 | F30: =D30-E30+F29 -> 3175855.9
A31: 45363 | B31: Crédito em conta | C31: SILVANA N RODRIGUES | D31: 5000 | F31: =D31-E31+F30 -> 3180855.9
A32: 45363 | B32: Gestão de caixa | E32: =(D31*0.005)+10 -> 35 | F32: =D32-E32+F31 -> 3180820.9
A33: 45363 | B33: Crédito em conta | C33: PAULINHA TRANSPORTES LTDA | D33: 48000 | F33: =D33-E33+F32 -> 3228820.9
A34: 45363 | B34: Gestão de caixa | E34: =(D33*0.005)+10 -> 250 | F34: =D34-E34+F33 -> 3228570.9
A35: 45363 | B35: Crédito em conta | C35: CELMA LINA DE ARAUJO ALMEIDA | D35: 4416.67 | F35: =D35-E35+F34 -> 3232987.6
A36: 45363 | B36: Gestão de caixa | E36: =(D35*0.005)+10 -> 32.08335 | F36: =D36-E36+F35 -> 3232955.5
A37: 45366 | B37: Transferência entre contas | C37: TRANSPORTADORA TURISTICA BENFICA S.A | E37: 22000 | F37: =D37-E37+F36 -> 3210955.5
A38: 45369 | B38: Transferência entre contas | C38: TRANSPORTADORA TURISTICA BENFICA S.A | E38: 52000 | F38: =D38-E38+F37 -> 3158955.5
A39: 45369 | B39: Crédito em conta | C39: MIRIA DIAS SILVEIRA TUCI | D39: 2200 | F39: =D39-E39+F38 -> 3161155.5
A40: 45369 | B40: Gestão de caixa | E40: =(D39*0.005)+10 -> 21 | F40: =D40-E40+F39 -> 3161134.5
A41: 45370 | B41: Crédito em conta | C41: BANCO DO BRASIL | D41: 229445.5 | F41: =D41-E41+F40 -> 3390580
A42: 45370 | B42: Gestão de caixa | E42: =(D41*0.005)+10 -> 1157.2275 | F42: =D42-E42+F41 -> 3389422.8
A43: 45370 | B43: Crédito em conta | C43: LEVEN T F T EIRELI | D43: 8750 | F43: =D43-E43+F42 -> 3398172.8
A44: 45370 | B44: Gestão de caixa | E44: =(D43*0.005)+10 -> 53.75 | F44: =D44-E44+F43 -> 3398119
A45: 45371 | B45: Crédito em conta | C45: ARENA FUTIBA II | D45: 10900 | F45: =D45-E45+F44 -> 3409019
A46: 45371 | B46: Gestão de caixa | E46: =(D45*0.005)+10 -> 64.5 | F46: =D46-E46+F45 -> 3408954.5
A47: 45371 | B47: Transferência entre contas | C47: TRANSPORTADORA TURISTICA BENFICA S.A | E47: 30000 | F47: =D47-E47+F46 -> 3378954.5
A48: 45371 | B48: Crédito em conta | C48: AGROTERRA SERVICOS AGRICOLAS NOVO HORIZONTE LTDA | D48: 9000 | F48: =D48-E48+F47 -> 3387954.5
A49: 45371 | B49: Gestão de caixa | E49: =(D48*0.005)+10 -> 55 | F49: =D49-E49+F48 -> 3387899.5
A50: 45371 | B50: Crédito em conta | C50: AGROTERRA SERVICOS AGRICOLAS NOVO HORIZONTE LTDA | D50: 5000 | F50: =D50-E50+F49 -> 3392899.5
A51: 45371 | B51: Gestão de caixa | E51: =(D50*0.005)+10 -> 35 | F51: =D51-E51+F50 -> 3392864.5
A52: 45371 | B52: Crédito em conta | C52: AGROTERRA SERVICOS AGRICOLAS NOVO HORIZONTE LTDA | D52: 4500 | F52: =D52-E52+F51 -> 3397364.5
A53: 45371 | B53: Gestão de caixa | E53: =(D52*0.005)+10 -> 32.5 | F53: =D53-E53+F52 -> 3397332
A54: 45372 | B54: Transferência entre contas | C54: TRANSPORTADORA TURISTICA BENFICA S.A | E54: 13500 | F54: =D54-E54+F53 -> 3383832
A55: 45373 | B55: Crédito em conta | C55: INDUSTRIAS ARTEB LTDA | D55: 1567.01 | F55: =D55-E55+F54 -> 3385399
A56: 45373 | B56: Gestão de caixa | E56: =(D55*0.005)+10 -> 17.83505 | F56: =D56-E56+F55 -> 3385381.2
A57: 45373 | B57: Transferência entre contas | C57: TRANSPORTADORA TURISTICA BENFICA S.A | E57: 7100 | F57: =D57-E57+F56 -> 3378281.2
A58: 45373 | B58: Transferência entre contas | C58: TRANSPORTADORA TURISTICA BENFICA S.A | E58: 4900 | F58: =D58-E58+F57 -> 3373381.2
A59: 45373 | B59: Crédito em conta | C59: PERFICE DO BRASIL SERVICOS DE TRANSPORTE E LOGISTICA LTDA | D59: 60815 | F59: =D59-E59+F58 -> 3434196.2
A60: 45373 | B60: Gestão de caixa | E60: =(D59*0.005)+10 -> 314.075 | F60: =D60-E60+F59 -> 3433882.1
A61: 45376 | B61: Transferência entre contas | C61: TRANSPORTADORA TURISTICA BENFICA S.A | E61: 9500 | F61: =D61-E61+F60 -> 3424382.1
A62: 45376 | B62: Crédito em conta | C62: TRANSPORTADORA TURISTICA BENFICA S.A | D62: 3150 | F62: =D62-E62+F61 -> 3427532.1
A63: 45376 | B63: Gestão de caixa | E63: =(D62*0.005)+10 -> 25.75 | F63: =D63-E63+F62 -> 3427506.4
A64: 45376 | B64: Crédito em conta | C64: METAL 2 INDUSTRIA E COMERCIO LTDA | D64: 10426.55 | F64: =D64-E64+F63 -> 3437932.9
A65: 45376 | B65: Gestão de caixa | E65: =(D64*0.005)+10 -> 62.13275 | F65: =D65-E65+F64 -> 3437870.8
A66: 45378 | B66: Crédito em conta | C66: TRANSPORTADORA TURIST SUZANO LTDA | D66: 31003.13 | F66: =D66-E66+F65 -> 3468873.9
A67: 45378 | B67: Gestão de caixa | E67: =(D66*0.005)+10 -> 165.01565 | F67: =D67-E67+F66 -> 3468708.9
A68: 45379 | B68: Transferência entre contas | C68: TRANSPORTADORA TURISTICA BENFICA S.A | E68: 188500 | F68: =D68-E68+F67 -> 3280208.9
F69: =D69-E69+F68 -> 3280208.9
F70: =D70-E70+F69 -> 3280208.9
F71: =D71-E71+F70 -> 3280208.9
F72: =D72-E72+F71 -> 3280208.9
F73: =D73-E73+F72 -> 3280208.9
F74: =D74-E74+F73 -> 3280208.9
F75: =D75-E75+F74 -> 3280208.9
F76: =D76-E76+F75 -> 3280208.9
F77: =D77-E77+F76 -> 3280208.9
F78: =D78-E78+F77 -> 3280208.9
F79: =D79-E79+F78 -> 3280208.9
F80: =D80-E80+F79 -> 3280208.9
... F609: =D609-E609+F608 -> 3280208.9

Sheet Abril2024
A2: EXTRATO DE MOVIMENTAÇÃO
A4: Banco | B4: LEPTA BANK (274) | C4: Agência | D4: 1 | E4: Conta | F4: 08198095-5
A5: Empresa | B5: TRANSP. TURISTICA BENFICA S.A | C5: Saldo Anterior | D5: =Março2024!F6 -> 3280208.9 | F5: Saldo Disponível
A6: CNPJ | B6: 59.275.289/0001-02 | C6: Totais (Entradas/Saídas) | D6: =SUM(D9:D609) -> 423079.99 | E6: =SUM(E9:E609) -> 633735.4 | F6: =F609 -> 3069553.5
A8: Data | B8: Histórico | C8: Complemento | D8: Créditos | E8: Débitos | F8: Saldo
A9: 45383 | B9: Tarifa de manutenção de conta | C9: TRANSPORTADORA TURISTICA BENFICA S.A - (Vinculada) | E9: 1500 | F9: =D9-E9+D5 -> 3278708.9
A10: 45383 | B10: Tarifa de manutenção da conta | C10: TED's, PIX e demais | E10: 60 | F10: =D10-E10+F9 -> 3278648.9
A11: 45383 | B11: Transferência entre contas | C11: TRANSPORTADORA TURISTICA BENFICA S.A | E11: 3100 | F11: =D11-E11+F10 -> 3275548.9
A12: 45384 | B12: Transferência entre contas | C12: TRANSPORTADORA TURISTICA BENFICA S.A | E12: 2000 | F12: =D12-E12+F11 -> 3273548.9
A13: 45386 | B13: Transferência entre contas | C13: TRANSPORTADORA TURISTICA BENFICA S.A | E13: 193000 | F13: =D13-E13+F12 -> 3080548.9
A14: 45386 | B14: Transferência entre contas | C14: TRANSPORTADORA TURISTICA BENFICA S.A | E14: 13300 | F14: =D14-E14+F13 -> 3067248.9
A15: 45387 | B15: Crédito em conta | C15: BB TRANSPORTE E TURISMO LTDA | D15: 90000 | F15: =D15-E15+F14 -> 3157248.9
A16: 45387 | B16: Gestão de caixa | E16: =(D15*0.005)+10 -> 460 | F16: =D16-E16+F15 -> 3156788.9
A17: 45387 | B17: Transferência entre contas | C17: TRANSPORTADORA TURISTICA BENFICA S.A | E17: 300 | F17: =D17-E17+F16 -> 3156488.9
A18: 45390 | B18: Crédito em conta | C18: PATRIMONY ADMINISTRADORA DE BENS AS | D18: 180230.49 | F18: =D18-E18+F17 -> 3336719.4
A19: 45390 | B19: Gestão de caixa | E19: =(D18*0.005)+10 -> 911.15245 | F19: =D19-E19+F18 -> 3335808.2
A20: 45390 | B20: Transferência entre contas | C20: TRANSPORTADORA TURISTICA BENFICA S.A | E20: 1100 | F20: =D20-E20+F19 -> 3334708.2
A21: 45392 | B21: Crédito em conta | C21: PAULINHA TRANSPORTES LTDA | D21: 48000 | F21: =D21-E21+F20 -> 3382708.2
A22: 45392 | B22: Gestão de caixa | E22: =(D21*0.005)+10 -> 250 | F22: =D22-E22+F21 -> 3382458.2
A23: 45392 | B23: Crédito em conta | C23: Celma Lina de Araujo Almeida | D23: 4416.7 | F23: =D23-E23+F22 -> 3386874.9
A24: 45392 | B24: Gestão de caixa | E24: =(D23*0.005)+10 -> 32.0835 | F24: =D24-E24+F23 -> 3386842.9
A25: 45392 | B25: Transferência entre contas | C25: TRANSPORTADORA TURISTICA BENFICA S.A | E25: 81350 | F25: =D25-E25+F24 -> 3305492.9
A26: 45397 | B26: Transferência entre contas | C26: TRANSPORTADORA TURISTICA BENFICA S.A | E26: 57000 | F26: =D26-E26+F25 -> 3248492.9
A27: 45398 | B27: Transferência entre contas | C27: TRANSPORTADORA TURISTICA BENFICA S.A | E27: 900 | F27: =D27-E27+F26 -> 3247592.9
A28: 45398 | B28: Transferência entre contas | C28: TRANSPORTADORA TURISTICA BENFICA S.A | E28: 850 | F28: =D28-E28+F27 -> 3246742.9
A29: 45398 | B29: Crédito em conta | C29: MIRIA DIAS SILVEIRA TUCI | D29: 2200 | F29: =D29-E29+F28 -> 3248942.9
A30: 45398 | B30: Gestão de caixa | E30: =(D29*0.005)+10 -> 21 | F30: =D30-E30+F29 -> 3248921.9
A31: 45400 | B31: Transferência entre contas | C31: TRANSPORTADORA TURISTICA BENFICA S.A | E31: 47000 | F31: =D31-E31+F30 -> 3201921.9
A32: 45401 | B32: Crédito em conta | C32: AGROTERRA SERVICOS AGRICOLAS NOVO HORIZONTE LTDA | D32: 4500 | F32: =D32-E32+F31 -> 3206421.9
A33: 45401 | B33: Gestão de caixa | E33: =(D32*0.005)+10 -> 32.5 | F33: =D33-E33+F32 -> 3206389.4
A34: 45401 | B34: Crédito em conta | C34: AGROTERRA SERVICOS AGRICOLAS NOVO HORIZONTE LTDA | D34: 9000 | F34: =D34-E34+F33 -> 3215389.4
A35: 45401 | B35: Gestão de caixa | E35: =(D34*0.005)+10 -> 55 | F35: =D35-E35+F34 -> 3215334.4
A36: 45401 | B36: Crédito em conta | C36: AGROTERRA SERVICOS AGRICOLAS NOVO HORIZONTE LTDA | D36: 5000 | F36: =D36-E36+F35 -> 3220334.4
A37: 45401 | B37: Gestão de caixa | E37: =(D36*0.005)+10 -> 35 | F37: =D37-E37+F36 -> 3220299.4
A38: 45402 | B38: Crédito em conta | C38: ARENA FUTIBA II | D38: 10900 | F38: =D38-E38+F37 -> 3231199.4
A39: 45402 | B39: Gestão de caixa | E39: =(D38*0.005)+10 -> 64.5 | F39: =D39-E39+F38 -> 3231134.9
A40: 45404 | B40: Transferência entre contas | C40: TRANSPORTADORA TURISTICA BENFICA S.A | E40: 16000 | F40: =D40-E40+F39 -> 3215134.9
A41: 45404 | B41: Crédito em conta | C41: INDUSTRIAS ARTEB LTDA | D41: 195.6 | F41: =D41-E41+F40 -> 3215330.5
A42: 45404 | B42: Gestão de caixa | E42: =(D41*0.005)+10 -> 10.978 | F42: =D42-E42+F41 -> 3215319.5
A43: 45405 | B43: Crédito em conta | C43: CARLOS HENRIQUE COSTA | D43: 6000 | F43: =D43-E43+F42 -> 3221319.5
A44: 45405 | B44: Gestão de caixa | E44: =(D43*0.005)+10 -> 40 | F44: =D44-E44+F43 -> 3221279.5
A45: 45406 | B45: Crédito em conta | C45: SCATENA AGENCIA DE VIAGENS E TURISMO LTDA | D45: 7000 | F45: =D45-E45+F44 -> 3228279.5
A46: 45406 | B46: Gestão de caixa | E46: =(D45*0.005)+10 -> 45 | F46: =D46-E46+F45 -> 3228234.5
A47: 45407 | B47: Crédito em conta | C47: ADEMILSON DE JESUS MENDES | D47: 4115 | F47: =D47-E47+F46 -> 3232349.5
A48: 45407 | B48: Gestão de caixa | E48: =(D47*0.005)+10 -> 30.575 | F48: =D48-E48+F47 -> 3232318.9
A49: 45407 | B49: Transferência entre contas | C49: TRANSPORTADORA TURISTICA BENFICA S.A | E49: 16000 | F49: =D49-E49+F48 -> 3216318.9
A50: 45407 | B50: Crédito em conta | C50: METAL 2 INDUSTRIA E COMERCIO LTDA | D50: 10519.07 | F50: =D50-E50+F49 -> 3226838
A51: 45407 | B51: Gestão de caixa | E51: =(D50*0.005)+10 -> 62.59535 | F51: =D51-E51+F50 -> 3226775.4
A52: 45408 | B52: Transferência entre contas | C52: TRANSPORTADORA TURISTICA BENFICA S.A | E52: 3000 | F52: =D52-E52+F51 -> 3223775.4
A53: 45411 | B53: Transferência entre contas | C53: TRANSPORTADORA TURISTICA BENFICA S.A | E53: 195000 | F53: =D53-E53+F52 -> 3028775.4
A54: 45411 | B54: Crédito em conta | C54: BENFICA CARGAS E LOGISTICA S.A | D54: 10000 | F54: =D54-E54+F53 -> 3038775.4
A55: 45411 | B55: Gestão de caixa | E55: =(D54*0.005)+10 -> 60 | F55: =D55-E55+F54 -> 3038715.4
A56: 45411 | B56: Crédito em conta | C56: TRANSPORTADORA TURIST SUZANO LTDA | D56: 31003.13 | F56: =D56-E56+F55 -> 3069718.5
A57: 45411 | B57: Gestão de caixa | E57: =(D56*0.005)+10 -> 165.01565 | F57: =D57-E57+F56 -> 3069553.5
F58: =D58-E58+F57 -> 3069553.5
F59: =D59-E59+F58 -> 3069553.5
F60: =D60-E60+F59 -> 3069553.5
F61: =D61-E61+F60 -> 3069553.5
F62: =D62-E62+F61 -> 3069553.5
F63: =D63-E63+F62 -> 3069553.5
F64: =D64-E64+F63 -> 3069553.5
F65: =D65-E65+F64 -> 3069553.5
F66: =D66-E66+F65 -> 3069553.5
F67: =D67-E67+F66 -> 3069553.5
F68: =D68-E68+F67 -> 3069553.5
F69: =D69-E69+F68 -> 3069553.5
... F609: =D609-E609+F608 -> 3069553.5

Sheet Maio2024
A2: EXTRATO DE MOVIMENTAÇÃO
A4: Banco | B4: LEPTA BANK (274) | C4: Agência | D4: 1 | E4: Conta | F4: 08198095-5
A5: Empresa | B5: TRANSP. TURISTICA BENFICA S.A | C5: Saldo Anterior | D5: =Abril2024!F6 -> 3069553.5 | F5: Saldo Disponível
A6: CNPJ | B6: 59.275.289/0001-02 | C6: Totais (Entradas/Saídas) | D6: =SUM(D9:D609) -> 590747.43 | E6: =SUM(E9:E609) -> 673343.74 | F6: =F609 -> 2986957.2
A8: Data | B8: Histórico | C8: Complemento | D8: Créditos | E8: Débitos | F8: Saldo
A9: 45413 | B9: Tarifa de manutenção de conta | C9: TRANSPORTADORA TURISTICA BENFICA S.A - (Vinculada) | E9: 1500 | F9: =D9-E9+D5 -> 3068053.5
A10: 45413 | B10: Tarifa de manutenção da conta | C10: TED's, PIX e demais | E10: 160 | F10: =D10-E10+F9 -> 3067893.5
A11: 45414 | B11: Transferência entre contas | C11: TRANSPORTADORA TURISTICA BENFICA S.A | E11: 2000 | F11: =D11-E11+F10 -> 3065893.5
A12: 45415 | B12: Transferência entre contas | C12: TRANSPORTADORA TURISTICA BENFICA S.A | E12: 200150 | F12: =D12-E12+F11 -> 2865743.5
A13: 45415 | B13: Transferência entre contas | C13: TRANSPORTADORA TURISTICA BENFICA S.A | E13: 5200 | F13: =D13-E13+F12 -> 2860543.5
A14: 45415 | B14: Crédito em conta | C14: PERFICE DO BRASIL SERVICOS DE TRANSPORTE E LOGISTICA LTDA | D14: 60815 | F14: =D14-E14+F13 -> 2921358.5
A15: 45415 | B15: Gestão de caixa | E15: =(D14*0.005)+10 -> 314.075 | F15: =D15-E15+F14 -> 2921044.4
A16: 45418 | B16: Transferência entre contas | C16: TRANSPORTADORA TURISTICA BENFICA S.A | E16: 36000 | F16: =D16-E16+F15 -> 2885044.4
A17: 45419 | B17: Crédito em conta | C17: BB TRANSPORTE E TURISMO LTDA | D17: 90000 | F17: =D17-E17+F16 -> 2975044.4
A18: 45419 | B18: Gestão de caixa | E18: =(D17*0.005)+10 -> 460 | F18: =D18-E18+F17 -> 2974584.4
A19: 45419 | B19: Transferência entre contas | C19: TRANSPORTADORA TURISTICA BENFICA S.A | E19: 3200 | F19: =D19-E19+F18 -> 2971384.4
A20: 45420 | B20: Crédito em conta | C20: PATRIMONY ADMINISTRADORA DE BENS AS | D20: 159624 | F20: =D20-E20+F19 -> 3131008.4
A21: 45420 | B21: Gestão de caixa | E21: =(D20*0.005)+10 -> 808.12 | F21: =D21-E21+F20 -> 3130200.3
A22: 45422 | B22: Crédito em conta | C22: CELMA LINA DE ARAUJO ALMEIDA | D22: 4416.7 | F22: =D22-E22+F21 -> 3134617
A23: 45422 | B23: Gestão de caixa | E23: =(D22*0.005)+10 -> 32.0835 | F23: =D23-E23+F22 -> 3134584.9
A24: 45422 | B24: Transferência entre contas | C24: TRANSPORTADORA TURISTICA BENFICA S.A | E24: 40000 | F24: =D24-E24+F23 -> 3094584.9
A25: 45422 | B25: Crédito em conta | C25: PAULINHA TRANSPORTES LTDA | D25: 48000 | F25: =D25-E25+F24 -> 3142584.9
A26: 45422 | B26: Gestão de caixa | E26: =(D25*0.005)+10 -> 250 | F26: =D26-E26+F25 -> 3142334.9
A27: 45425 | B27: Crédito em conta | C27: TRANSPORTADORA TURISTICA BENFICA AS | D27: 360 | F27: =D27-E27+F26 -> 3142694.9
A28: 45425 | B28: Gestão de caixa | E28: =(D27*0.005)+10 -> 11.8 | F28: =D28-E28+F27 -> 3142683.1
A29: 45427 | B29: Transferência entre contas | C29: TRANSPORTADORA TURISTICA BENFICA S.A | E29: 22000 | F29: =D29-E29+F28 -> 3120683.1
A30: 45429 | B30: Crédito em conta | C30: MIRIA DIAS SILVEIRA TUCI | D30: 2200 | F30: =D30-E30+F29 -> 3122883.1
A31: 45429 | B31: Gestão de caixa | E31: =(D30*0.005)+10 -> 21 | F31: =D31-E31+F30 -> 3122862.1
A32: 45429 | B32: Transferência entre contas | C32: TRANSPORTADORA TURISTICA BENFICA S.A | E32: 10000 | F32: =D32-E32+F31 -> 3112862.1
A33: 45432 | B33: Crédito em conta | C33: AGROTERRA SERVICOS AGRICOLAS NOVO HORIZONTE LTDA | D33: 4500 | F33: =D33-E33+F32 -> 3117362.1
A34: 45432 | B34: Gestão de caixa | E34: =(D33*0.005)+10 -> 32.5 | F34: =D34-E34+F33 -> 3117329.6
A35: 45432 | B35: Crédito em conta | C35: AGROTERRA SERVICOS AGRICOLAS NOVO HORIZONTE LTDA | D35: 9000 | F35: =D35-E35+F34 -> 3126329.6
A36: 45432 | B36: Gestão de caixa | E36: =(D35*0.005)+10 -> 55 | F36: =D36-E36+F35 -> 3126274.6
A37: 45432 | B37: Crédito em conta | C37: AGROTERRA SERVICOS AGRICOLAS NOVO HORIZONTE LTDA | D37: 5000 | F37: =D37-E37+F36 -> 3131274.6
A38: 45432 | B38: Gestão de caixa | E38: =(D37*0.005)+10 -> 35 | F38: =D38-E38+F37 -> 3131239.6
A39: 45432 | B39: Transferência entre contas | C39: TRANSPORTADORA TURISTICA BENFICA S.A | E39: 93000 | F39: =D39-E39+F38 -> 3038239.6
A40: 45432 | B40: Crédito em conta | C40: ARENA FUTIBA II | D40: 10900 | F40: =D40-E40+F39 -> 3049139.6
A41: 45432 | B41: Gestão de caixa | E41: =(D40*0.005)+10 -> 64.5 | F41: =D41-E41+F40 -> 3049075.1
A42: 45433 | B42: Crédito em conta | C42: BENFICA CARGAS E LOGISTICA S.A | D42: 12000 | F42: =D42-E42+F41 -> 3061075.1
A43: 45433 | B43: Gestão de caixa | E43: =(D42*0.005)+10 -> 70 | F43: =D43-E43+F42 -> 3061005.1
A44: 45434 | B44: Crédito em conta | C44: INDUSTRIAS ARTEB LTDA | D44: 194.08 | F44: =D44-E44+F43 -> 3061199.2
A45: 45434 | B45: Gestão de caixa | E45: =(D44*0.005)+10 -> 10.9704 | F45: =D45-E45+F44 -> 3061188.2
A46: 45434 | B46: Crédito em conta | C46: VLADEMIR CASSAGUERA JUNIOR | D46: 98000 | F46: =D46-E46+F45 -> 3159188.2
A47: 45434 | B47: Gestão de caixa | E47: =(D46*0.005)+10 -> 500 | F47: =D47-E47+F46 -> 3158688.2
A48: 45434 | B48: Crédito em conta | C48: REGINA CELIA DA CRUZ RODRIGUES | D48: 40000 | F48: =D48-E48+F47 -> 3198688.2
A49: 45434 | B49: Gestão de caixa | E49: =(D48*0.005)+10 -> 210 | F49: =D49-E49+F48 -> 3198478.2
A50: 45436 | B50: Transferência entre contas | C50: TRANSPORTADORA TURISTICA BENFICA S.A | E50: 17000 | F50: =D50-E50+F49 -> 3181478.2
A51: 45439 | B51: Crédito em conta | C51: TRANSPORTADORA TURIST SUZANO LTDA | D51: 31003.13 | F51: =D51-E51+F50 -> 3212481.3
A52: 45439 | B52: Gestão de caixa | E52: =(D51*0.005)+10 -> 165.01565 | F52: =D52-E52+F51 -> 3212316.3
A53: 45439 | B53: Transferência entre contas | C53: TRANSPORTADORA TURISTICA BENFICA S.A | E53: 11000 | F53: =D53-E53+F52 -> 3201316.3
A54: 45439 | B54: Crédito em conta | C54: ADEMILSON DE JESUS MENDES | D54: 4115 | F54: =D54-E54+F53 -> 3205431.3
A55: 45439 | B55: Gestão de caixa | E55: =(D54*0.005)+10 -> 30.575 | F55: =D55-E55+F54 -> 3205400.8
A56: 45440 | B56: Transferência entre contas | C56: TRANSPORTADORA TURISTICA BENFICA S.A | E56: 229000 | F56: =D56-E56+F55 -> 2976400.8
A57: 45443 | B57: Crédito em conta | C57: METAL 2 INDUSTRIA E COMERCIO LTDA | D57: 10619.52 | F57: =D57-E57+F56 -> 2987020.3
A58: 45443 | B58: Gestão de caixa | E58: =(D57*0.005)+10 -> 63.0976 | F58: =D58-E58+F57 -> 2986957.2
F59: =D59-E59+F58 -> 2986957.2
F60: =D60-E60+F59 -> 2986957.2
F61: =D61-E61+F60 -> 2986957.2
F62: =D62-E62+F61 -> 2986957.2
F63: =D63-E63+F62 -> 2986957.2
F64: =D64-E64+F63 -> 2986957.2
F65: =D65-E65+F64 -> 2986957.2
F66: =D66-E66+F65 -> 2986957.2
F67: =D67-E67+F66 -> 2986957.2
F68: =D68-E68+F67 -> 2986957.2
F69: =D69-E69+F68 -> 2986957.2
F70: =D70-E70+F69 -> 2986957.2
... F609: =D609-E609+F608 -> 2986957.2

Sheet Junho2024
A2: EXTRATO DE MOVIMENTAÇÃO
A4: Banco | B4: LEPTA BANK (274) | C4: Agência | D4: 1 | E4: Conta | F4: 08198095-5
A5: Empresa | B5: TRANSP. TURISTICA BENFICA S.A | C5: Saldo Anterior | D5: =Maio2024!F6 -> 2986957.2 | F5: Saldo Disponível
A6: CNPJ | B6: 59.275.289/0001-02 | C6: Totais (Entradas/Saídas) | D6: =SUM(D9:D609) -> 875163.12 | E6: =SUM(E9:E609) -> 725655.82 | F6: =F609 -> 3136464.5
A8: Data | B8: Histórico | C8: Complemento | D8: Créditos | E8: Débitos | F8: Saldo
A9: 45444 | B9: Tarifa de manutenção de conta | C9: TRANSPORTADORA TURISTICA BENFICA S.A - (Vinculada) | E9: 1500 | F9: =D9-E9+D5 -> 2985457.2
A10: 45444 | B10: Tarifa de manutenção da conta | C10: TED's, PIX e demais | E10: 50 | F10: =D10-E10+F9 -> 2985407.2
A11: 45446 | B11: Transferência entre contas | C11: TRANSPORTADORA TURISTICA BENFICA S.A | E11: 2000 | F11: =D11-E11+F10 -> 2983407.2
A12: 45446 | B12: Transferência entre contas | C12: TRANSPORTADORA TURISTICA BENFICA S.A | E12: 7000 | F12: =D12-E12+F11 -> 2976407.2
A13: 45446 | B13: Crédito em conta | C13: PERFICE DO BRASIL SERVICOS DE TRANSPORTE E LOGISTICA LTDA | D13: 58800 | F13: =D13-E13+F12 -> 3035207.2
A14: 45446 | B14: Gestão de caixa | E14: =(D13*0.005)+10 -> 304 | F14: =D14-E14+F13 -> 3034903.2
A15: 45446 | B15: Crédito em conta | C15: PINHO SALUM E POSSEBON AD | D15: 226335.52 | F15: =D15-E15+F14 -> 3261238.7
A16: 45446 | B16: Gestão de caixa | E16: =(D15*0.005)+10 -> 1141.6776 | F16: =D16-E16+F15 -> 3260097
A17: 45446 | B17: Crédito em conta | C17: PINHO SALUM E POSSEBON AD | D17: 93894.7 | F17: =D17-E17+F16 -> 3353991.7
A18: 45446 | B18: Gestão de caixa | E18: =(D17*0.005)+10 -> 479.4735 | F18: =D18-E18+F17 -> 3353512.2
A19: 45447 | B19: Transferência entre contas | C19: TRANSPORTADORA TURISTICA BENFICA S.A | E19: 200000 | F19: =D19-E19+F18 -> 3153512.2
A20: 45448 | B20: Crédito em conta | C20: WEST SERVICE TRANSPORTES E LOCADORA DE VEICULOS LTDA ME | D20: 20000 | F20: =D20-E20+F19 -> 3173512.2
A21: 45448 | B21: Gestão de caixa | E21: =(D20*0.005)+10 -> 110 | F21: =D21-E21+F20 -> 3173402.2
A22: 45449 | B22: Crédito em conta | C22: BB TRANSPORTE E TURISMO LTDA | D22: 90000 | F22: =D22-E22+F21 -> 3263402.2
A23: 45449 | B23: Gestão de caixa | E23: =(D22*0.005)+10 -> 460 | F23: =D23-E23+F22 -> 3262942.2
A24: 45449 | B24: Transferência entre contas | C24: TRANSPORTADORA TURISTICA BENFICA S.A | E24: 74000 | F24: =D24-E24+F23 -> 3188942.2
A25: 45449 | B25: Crédito em conta | C25: SCATENA AGENCIA DE VIAGENS T. LTDA | D25: 7000 | F25: =D25-E25+F24 -> 3195942.2
A26: 45449 | B26: Gestão de caixa | E26: =(D25*0.005)+10 -> 45 | F26: =D26-E26+F25 -> 3195897.2
A27: 45450 | B27: Transferência entre contas | C27: TRANSPORTADORA TURISTICA BENFICA S.A | E27: 5000 | F27: =D27-E27+F26 -> 3190897.2
A28: 45450 | B28: Transferência entre contas | C28: TRANSPORTADORA TURISTICA BENFICA S.A | E28: 5000 | F28: =D28-E28+F27 -> 3185897.2
A29: 45453 | B29: Crédito em conta | C29: PAULINHA TRANSPORTES LTDA | D29: 48000 | F29: =D29-E29+F28 -> 3233897.2
A30: 45453 | B30: Gestão de caixa | E30: =(D29*0.005)+10 -> 250 | F30: =D30-E30+F29 -> 3233647.2
A31: 45453 | B31: Crédito em conta | C31: PATRIMONY ADMINISTRADORA DE BENS SA | D31: 188462.65 | F31: =D31-E31+F30 -> 3422109.9
A32: 45453 | B32: Gestão de caixa | E32: =(D31*0.005)+10 -> 952.31325 | F32: =D32-E32+F31 -> 3421157.6
A33: 45453 | B33: Crédito em conta | C33: WEST SERVICE TRANSPORTES E LOCADORA DE VEICULOS LTDA ME | D33: 10000 | F33: =D33-E33+F32 -> 3431157.6
A34: 45453 | B34: Gestão de caixa | E34: =(D33*0.005)+10 -> 60 | F34: =D34-E34+F33 -> 3431097.6
A35: 45454 | B35: Crédito em conta | C35: CELMA LINA DE ARAUJO ALMEIDA | D35: 4416.7 | F35: =D35-E35+F34 -> 3435514.3
A36: 45454 | B36: Gestão de caixa | E36: =(D35*0.005)+10 -> 32.0835 | F36: =D36-E36+F35 -> 3435482.2
A37: 45455 | B37: Transferência entre contas | C37: TRANSPORTADORA TURISTICA BENFICA S.A | E37: 5000 | F37: =D37-E37+F36 -> 3430482.2
A38: 45457 | B38: Transferência entre contas | C38: TRANSPORTADORA TURISTICA BENFICA S.A | E38: 21000 | F38: =D38-E38+F37 -> 3409482.2
A39: 45457 | B39: Crédito em conta | C39: JUSSANIA NASCIMENTO DA SILVA | D39: 30000 | F39: =D39-E39+F38 -> 3439482.2
A40: 45457 | B40: Gestão de caixa | E40: =(D39*0.005)+10 -> 160 | F40: =D40-E40+F39 -> 3439322.2
A41: 45460 | B41: Transferência entre contas | C41: TRANSPORTADORA TURISTICA BENFICA S.A | E41: 1000 | F41: =D41-E41+F40 -> 3438322.2
A42: 45460 | B42: Transferência entre contas | C42: TRANSPORTADORA TURISTICA BENFICA S.A | E42: 37000 | F42: =D42-E42+F41 -> 3401322.2
A43: 45460 | B43: Crédito em conta | C43: MIRIA DIAS SILVEIRA TUCI | D43: 2200 | F43: =D43-E43+F42 -> 3403522.2
A44: 45460 | B44: Gestão de caixa | E44: =(D43*0.005)+10 -> 21 | F44: =D44-E44+F43 -> 3403501.2
A45: 45460 | B45: Crédito em conta | C45: TRANSPORTADORA TURISTICA BENFICA S.A | D45: 200 | F45: =D45-E45+F44 -> 3403701.2
A46: 45460 | B46: Gestão de caixa | E46: =(D45*0.005)+10 -> 11 | F46: =D46-E46+F45 -> 3403690.2
A47: 45461 | B47: Ajuste de saldo | D47: 0.01 | F47: =D47-E47+F46 -> 3403690.2
A48: 45462 | B48: Transferência entre contas | C48: TRANSPORTADORA TURISTICA BENFICA S.A | E48: 79000 | F48: =D48-E48+F47 -> 3324690.2
A49: 45462 | B49: Crédito em conta | C49: TRANSPORTADORA TURISTICA BENFICA S.A | D49: 16300 | F49: =D49-E49+F48 -> 3340990.2
A50: 45462 | B50: Gestão de caixa | E50: =(D49*0.005)+10 -> 91.5 | F50: =D50-E50+F49 -> 3340898.7
A51: 45463 | B51: Crédito em conta | C51: ARENA FUTIBA II | D51: 10900 | F51: =D51-E51+F50 -> 3351798.7
A52: 45463 | B52: Gestão de caixa | E52: =(D51*0.005)+10 -> 64.5 | F52: =D52-E52+F51 -> 3351734.2
A53: 45464 | B53: Transferência entre contas | C53: TRANSPORTADORA TURISTICA BENFICA S.A | E53: 1000 | F53: =D53-E53+F52 -> 3350734.2
A54: 45467 | B54: Crédito em conta | C54: JESUITO FRANCISCO COST | D54: 10000 | F54: =D54-E54+F53 -> 3360734.2
A55: 45467 | B55: Gestão de caixa | E55: =(D54*0.005)+10 -> 60 | F55: =D55-E55+F54 -> 3360674.2
A56: 45467 | B56: Crédito em conta | C56: JESUITO FRANCISCO COST | D56: 5000 | F56: =D56-E56+F55 -> 3365674.2
A57: 45467 | B57: Gestão de caixa | E57: =(D56*0.005)+10 -> 35 | F57: =D57-E57+F56 -> 3365639.2
A58: 45467 | B58: Crédito em conta | C58: INDUSTRIAS ARTEB LTDA | D58: 194.77 | F58: =D58-E58+F57 -> 3365834
A59: 45467 | B59: Gestão de caixa | E59: =(D58*0.005)+10 -> 10.97385 | F59: =D59-E59+F58 -> 3365823
A60: 45468 | B60: Crédito em conta | C60: METAL 2 INDUSTRIA E COMERCIO LTDA | D60: 10690.64 | F60: =D60-E60+F59 -> 3376513.6
A61: 45468 | B61: Gestão de caixa | E61: =(D60*0.005)+10 -> 63.4532 | F61: =D61-E61+F60 -> 3376450.2
A62: 45468 | B62: Transferência entre contas | C62: TRANSPORTADORA TURISTICA BENFICA S.A | E62: 42000 | F62: =D62-E62+F61 -> 3334450.2
A63: 45468 | B63: Crédito em conta | C63: TRANSPORTADORA TURISTICA BENFICA S.A | D63: 650 | F63: =D63-E63+F62 -> 3335100.2
A64: 45468 | B64: Gestão de caixa | E64: =(D63*0.005)+10 -> 13.25 | F64: =D64-E64+F63 -> 3335086.9
A65: 45469 | B65: Transferência entre contas | C65: TRANSPORTADORA TURISTICA BENFICA S.A | E65: 2500 | F65: =D65-E65+F64 -> 3332586.9
A66: 45470 | B66: Transferência entre contas | C66: TRANSPORTADORA TURISTICA BENFICA S.A | E66: 238000 | F66: =D66-E66+F65 -> 3094586.9
A67: 45470 | B67: Crédito em conta | C67: TRANSPORTADORA TURIST SUZANO LTDA | D67: 31003.13 | F67: =D67-E67+F66 -> 3125590.1
A68: 45470 | B68: Gestão de caixa | E68: =(D67*0.005)+10 -> 165.01565 | F68: =D68-E68+F67 -> 3125425.1
A69: 45471 | B69: Crédito em conta | C69: ADEMILSON DE JESUS MENDES | D69: 4115 | F69: =D69-E69+F68 -> 3129540.1
A70: 45471 | B70: Gestão de caixa | E70: =(D69*0.005)+10 -> 30.575 | F70: =D70-E70+F69 -> 3129509.5
A71: 45471 | B71: Crédito em conta | C71: SCATENA A V T EIRELI | D71: 7000 | F71: =D71-E71+F70 -> 3136509.5
A72: 45471 | B72: Gestão de caixa | E72: =(D71*0.005)+10 -> 45 | F72: =D72-E72+F71 -> 3136464.5
F73: =D73-E73+F72 -> 3136464.5
F74: =D74-E74+F73 -> 3136464.5
F75: =D75-E75+F74 -> 3136464.5
F76: =D76-E76+F75 -> 3136464.5
F77: =D77-E77+F76 -> 3136464.5
F78: =D78-E78+F77 -> 3136464.5
F79: =D79-E79+F78 -> 3136464.5
F80: =D80-E80+F79 -> 3136464.5
F81: =D81-E81+F80 -> 3136464.5
F82: =D82-E82+F81 -> 3136464.5
F83: =D83-E83+F82 -> 3136464.5
F84: =D84-E84+F83 -> 3136464.5
... F609: =D609-E609+F608 -> 3136464.5

Sheet Julho2024
A2: EXTRATO DE MOVIMENTAÇÃO
A4: Banco | B4: LEPTA BANK (274) | C4: Agência | D4: 1 | E4: Conta | F4: 08198095-5
A5: Empresa | B5: TRANSP. TURISTICA BENFICA S.A | C5: Saldo Anterior | D5: =Junho2024!F6 -> 3136464.5 | F5: Saldo Disponível
A6: CNPJ | B6: 59.275.289/0001-02 | C6: Totais (Entradas/Saídas) | D6: =SUM(D9:D608) -> 890434.61 | E6: =SUM(E9:E608) -> 1393972.2 | F6: =F608 -> 2632926.9
A8: Data | B8: Histórico | C8: Complemento | D8: Créditos | E8: Débitos | F8: Saldo
A9: 45474 | B9: Tarifa de manutenção de conta | C9: TRANSPORTADORA TURISTICA BENFICA S.A - (Vinculada) | E9: 1500 | F9: =D9-E9+D5 -> 3134964.5
A10: 45474 | B10: Tarifa de manutenção da conta | C10: TED's, PIX e demais | E10: 280 | F10: =D10-E10+F9 -> 3134684.5
A11: 45477 | B11: Transferência entre contas | C11: TRANSPORTADORA TURISTICA BENFICA S.A | E11: 217000 | F11: =D11-E11+F10 -> 2917684.5
A12: 45478 | B12: Crédito em conta | C12: BB TRANSPORTE E TURISMO LTDA | D12: 90000 | F12: =D12-E12+F11 -> 3007684.5
A13: 45478 | B13: Gestão de caixa | E13: =(D12*0.005)+10 -> 460 | F13: =D13-E13+F12 -> 3007224.5
A14: 45478 | B14: Crédito em conta | C14: DOCINI PROMOCAO DE VENDAS LTDA | D14: 3000 | F14: =D14-E14+F13 -> 3010224.5
A15: 45478 | B15: Gestão de caixa | E15: =(D14*0.005)+10 -> 25 | F15: =D15-E15+F14 -> 3010199.5
A16: 45481 | B16: Crédito em conta | C16: PATRIMONY ADMINISTRADORA DE BENS AS | D16: 188462.65 | F16: =D16-E16+F15 -> 3198662.1
A17: 45481 | B17: Gestão de caixa | E17: =(D16*0.005)+10 -> 952.31325 | F17: =D17-E17+F16 -> 3197709.8
A18: 45483 | B18: Crédito em conta | C18: BB TRANSPORTE E TURISMO LTDA | D18: 360000 | F18: =D18-E18+F17 -> 3557709.8
A19: 45483 | B19: Gestão de caixa | E19: =(D18*0.005)+10 -> 1810 | F19: =D19-E19+F18 -> 3555899.8
A20: 45483 | B20: Crédito em conta | C20: CELMA LINA DE ARAUJO ALMEIDA | D20: 4416.7 | F20: =D20-E20+F19 -> 3560316.5
A21: 45483 | B21: Gestão de caixa | E21: =(D20*0.005)+10 -> 32.0835 | F21: =D21-E21+F20 -> 3560284.4
A22: 45483 | B22: Transferência entre contas | C22: TRANSPORTADORA TURISTICA BENFICA S.A | E22: 280000 | F22: =D22-E22+F21 -> 3280284.4
A23: 45484 | B23: Crédito em conta | C23: PAULINHA TRANSPORTES LTDA | D23: 48000 | F23: =D23-E23+F22 -> 3328284.4
A24: 45484 | B24: Gestão de caixa | E24: =(D23*0.005)+10 -> 250 | F24: =D24-E24+F23 -> 3328034.4
A25: 45484 | B25: Crédito em conta | C25: DOCINI PROMOCAO DE VENDAS LTDA | D25: 8000 | F25: =D25-E25+F24 -> 3336034.4
A26: 45484 | B26: Gestão de caixa | E26: =(D25*0.005)+10 -> 50 | F26: =D26-E26+F25 -> 3335984.4
A27: 45484 | B27: Transferência entre contas | C27: TRANSPORTADORA TURISTICA BENFICA S.A | E27: 113000 | F27: =D27-E27+F26 -> 3222984.4
A28: 45485 | B28: Transferência entre contas | C28: TRANSPORTADORA TURISTICA BENFICA S.A | E28: 128000 | F28: =D28-E28+F27 -> 3094984.4
A29: 45487 | B29: Tarifa de conta | E29: 70 | F29: =D29-E29+F28 -> 3094914.4
A30: 45488 | B30: Transferência entre contas | C30: TRANSPORTADORA TURISTICA BENFICA S.A | E30: 42870 | F30: =D30-E30+F29 -> 3052044.4
A31: 45488 | B31: Crédito em conta | C31: MIRIA DIAS SILVEIRA TUCI | D31: 2200 | F31: =D31-E31+F30 -> 3054244.4
A32: 45488 | B32: Gestão de caixa | E32: =(D31*0.005)+10 -> 21 | F32: =D32-E32+F31 -> 3054223.4
A33: 45488 | B33: Crédito em conta | C33: TRANSPORTADORA TURISTICA BENFICA S.A | D33: 170 | F33: =D33-E33+F32 -> 3054393.4
A34: 45488 | B34: Gestão de caixa | E34: =(D33*0.005)+10 -> 10.85 | F34: =D34-E34+F33 -> 3054382.6
A35: 45489 | B35: Tarifa de conta | E35: 10 | F35: =D35-E35+F34 -> 3054372.6
A36: 45491 | B36: Transferência entre contas | C36: TRANSPORTADORA TURISTICA BENFICA S.A | E36: 49500 | F36: =D36-E36+F35 -> 3004872.6
A37: 45491 | B37: Crédito em conta | C37: TRANSPORTADORA TURISTICA BENFICA S.A | D37: 1100 | F37: =D37-E37+F36 -> 3005972.6
A38: 45491 | B38: Gestão de caixa | E38: =(D37*0.005)+10 -> 15.5 | F38: =D38-E38+F37 -> 3005957.1
A39: 45492 | B39: Tarifa de conta | E39: 20 | F39: =D39-E39+F38 -> 3005937.1
A40: 45493 | B40: Crédito em conta | C40: ARENA FUTIBA II | D40: 10900 | F40: =D40-E40+F39 -> 3016837.1
A41: 45493 | B41: Gestão de caixa | E41: =(D40*0.005)+10 -> 64.5 | F41: =D41-E41+F40 -> 3016772.6
A42: 45495 | B42: Transferência entre contas | C42: TRANSPORTADORA TURISTICA BENFICA S.A | E42: 19000 | F42: =D42-E42+F41 -> 2997772.6
A43: 45495 | B43: Crédito em conta | C43: INDUSTRIAS ARTEB LTDA | D43: 193.28 | F43: =D43-E43+F42 -> 2997965.9
A44: 45495 | B44: Gestão de caixa | E44: =(D43*0.005)+10 -> 10.9664 | F44: =D44-E44+F43 -> 2997954.9
A45: 45496 | B45: Tarifa de conta | E45: 10 | F45: =D45-E45+F44 -> 2997944.9
A46: 45497 | B46: Tarifa de conta | E46: 10 | F46: =D46-E46+F45 -> 2997934.9
A47: 45497 | B47: Transferência entre contas | C47: TRANSPORTADORA TURISTICA BENFICA S.A | E47: 47000 | F47: =D47-E47+F46 -> 2950934.9
A48: 45498 | B48: Tarifa de conta | E48: 10 | F48: =D48-E48+F47 -> 2950924.9
A49: 45498 | B49: Crédito em conta | C49: ADEMILSON DE JESUS MENDES | D49: 4150 | F49: =D49-E49+F48 -> 2955074.9
A50: 45498 | B50: Gestão de caixa | E50: =(D49*0.005)+10 -> 30.75 | F50: =D50-E50+F49 -> 2955044.2
A51: 45498 | B51: Transferência entre contas | C51: TRANSPORTADORA TURISTICA BENFICA S.A | E51: 35000 | F51: =D51-E51+F50 -> 2920044.2
A52: 45498 | B52: Crédito em conta | C52: METAL 2 INDUSTRIA E COMERCIO LTDA | D52: 10783.38 | F52: =D52-E52+F51 -> 2930827.5
A53: 45498 | B53: Gestão de caixa | E53: =(D52*0.005)+10 -> 63.9169 | F53: =D53-E53+F52 -> 2930763.6
A54: 45499 | B54: Tarifa de conta | E54: 20 | F54: =D54-E54+F53 -> 2930743.6
A55: 45502 | B55: Crédito em conta | C55: TRANSPORTADORA TURIST SUZANO LTDA | D55: 31003.13 | F55: =D55-E55+F54 -> 2961746.7
A56: 45502 | B56: Gestão de caixa | E56: =(D55*0.005)+10 -> 165.01565 | F56: =D56-E56+F55 -> 2961581.7
A57: 45502 | B57: Transferência entre contas | C57: TRANSPORTADORA TURISTICA BENFICA S.A | E57: 456000 | F57: =D57-E57+F56 -> 2505581.7
A58: 45503 | B58: Tarifa de conta | E58: 20 | F58: =D58-E58+F57 -> 2505561.7
A59: 45503 | B59: Crédito em conta | C59: LORINALDO DA SILVA FERREIRA | D59: 10000 | F59: =D59-E59+F58 -> 2515561.7
A60: 45503 | B60: Gestão de caixa | E60: =(D59*0.005)+10 -> 60 | F60: =D60-E60+F59 -> 2515501.7
A61: 45503 | B61: Crédito em conta | C61: PERFICE DO BRASIL SERVICOS DE TRANSPORTE E LOGISTICA LTDA | D61: 58800 | F61: =D61-E61+F60 -> 2574301.7
A62: 45503 | B62: Gestão de caixa | E62: =(D61*0.005)+10 -> 304 | F62: =D62-E62+F61 -> 2573997.7
A63: 45504 | B63: Tarifa de conta | E63: 10 | F63: =D63-E63+F62 -> 2573987.7
A64: 45504 | B64: Crédito em conta | C64: TRANSPORTADORA TURISTICA BENFICA SA | D64: 455.47 | F64: =D64-E64+F63 -> 2574443.2
A65: 45504 | B65: Gestão de caixa | E65: =(D64*0.005)+10 -> 12.27735 | F65: =D65-E65+F64 -> 2574430.9
A66: 45504 | B66: Crédito em conta | C66: PERFICE DO BRASIL SERVICOS DE TRANSPORTE E LOGISTICA LTDA | D66: 58800 | F66: =D66-E66+F65 -> 2633230.9
A67: 45504 | B67: Gestão de caixa | E67: =(D66*0.005)+10 -> 304 | F67: =D67-E67+F66 -> 2632926.9
F68: =D68-E68+F67 -> 2632926.9
F69: =D69-E69+F68 -> 2632926.9
F70: =D70-E70+F69 -> 2632926.9
F71: =D71-E71+F70 -> 2632926.9
F72: =D72-E72+F71 -> 2632926.9
F73: =D73-E73+F72 -> 2632926.9
F74: =D74-E74+F73 -> 2632926.9
F75: =D75-E75+F74 -> 2632926.9
F76: =D76-E76+F75 -> 2632926.9
F77: =D77-E77+F76 -> 2632926.9
F78: =D78-E78+F77 -> 2632926.9
F79: =D79-E79+F78 -> 2632926.9
... F608: =D608-E608+F607 -> 2632926.9

Sheet Agosto2024
A2: EXTRATO DE MOVIMENTAÇÃO
A4: Banco | B4: LEPTA BANK (274) | C4: Agência | D4: 1 | E4: Conta | F4: 08198095-5
A5: Empresa | B5: TRANSP. TURISTICA BENFICA S.A | C5: Saldo Anterior | D5: =Julho2024!F6 -> 2632926.9 | F5: Saldo Disponível
A6: CNPJ | B6: 59.275.289/0001-02 | C6: Totais (Entradas/Saídas) | D6: =SUM(D9:D607) -> 794189.73 | E6: =SUM(E9:E607) -> 1109210.9 | F6: =F607 -> 2317905.7
A8: Data | B8: Histórico | C8: Complemento | D8: Créditos | E8: Débitos | F8: Saldo
A9: 45505 | B9: Tarifa de conta | E9: 1510 | F9: =D9-E9+D5 -> 2631416.9
A10: 45506 | B10: Tarifa de conta | E10: 10 | F10: =D10-E10+F9 -> 2631406.9
A11: 45506 | B11: Transferência entre contas | C11: TRANSPORTADORA TURISTICA BENFICA S.A | E11: 203800 | F11: =D11-E11+F10 -> 2427606.9
A12: 45506 | B12: Transferência entre contas | C12: TRANSPORTADORA TURISTICA BENFICA S.A | E12: 2500 | F12: =D12-E12+F11 -> 2425106.9
A13: 45507 | B13: Tarifa de conta | E13: 20 | F13: =D13-E13+F12 -> 2425086.9
A14: 45510 | B14: Crédito em conta | C14: BB TRANSPORTE E TURISMO LTDA | D14: 90000 | F14: =D14-E14+F13 -> 2515086.9
A15: 45510 | B15: Gestão de caixa | E15: =(D14*0.005)+10 -> 460 | F15: =D15-E15+F14 -> 2514626.9
A16: 45511 | B16: Tarifa de conta | E16: 10 | F16: =D16-E16+F15 -> 2514616.9
A17: 45512 | B17: Crédito em conta | C17: PATRIMONY ADMINISTRADORA DE BENS SA | D17: 188462.65 | F17: =D17-E17+F16 -> 2703079.6
A18: 45512 | B18: Gestão de caixa | E18: =(D17*0.005)+10 -> 952.31325 | F18: =D18-E18+F17 -> 2702127.3
A19: 45513 | B19: Tarifa de conta | E19: 10 | F19: =D19-E19+F18 -> 2702117.3
A20: 45513 | B20: Transferência entre contas | C20: TRANSPORTADORA TURISTICA BENFICA S.A | E20: 13000 | F20: =D20-E20+F19 -> 2689117.3
A21: 45514 | B21: Tarifa de conta | E21: 10 | F21: =D21-E21+F20 -> 2689107.3
A22: 45516 | B22: Transferência entre contas | C22: TRANSPORTADORA TURISTICA BENFICA S.A | E22: 102000 | F22: =D22-E22+F21 -> 2587107.3
A23: 45517 | B23: Tarifa de conta | E23: 10 | F23: =D23-E23+F22 -> 2587097.3
A24: 45517 | B24: Crédito em conta | C24: Celma Lina de Araujo Almeida | D24: 4416.7 | F24: =D24-E24+F23 -> 2591514
A25: 45517 | B25: Gestão de caixa | E25: =(D24*0.005)+10 -> 32.0835 | F25: =D25-E25+F24 -> 2591481.9
A26: 45518 | B26: Tarifa de conta | E26: 10 | F26: =D26-E26+F25 -> 2591471.9
A27: 45519 | B27: Transferência entre contas | C27: TRANSPORTADORA TURISTICA BENFICA S.A | E27: 42000 | F27: =D27-E27+F26 -> 2549471.9
A28: 45520 | B28: Tarifa de conta | E28: 10 | F28: =D28-E28+F27 -> 2549461.9
A29: 45523 | B29: Crédito em conta | C29: MIRIA DIAS SILVEIRA TUCI | D29: 2200 | F29: =D29-E29+F28 -> 2551661.9
A30: 45523 | B30: Gestão de caixa | E30: =(D29*0.005)+10 -> 21 | F30: =D30-E30+F29 -> 2551640.9
A31: 45523 | B31: Transferência entre contas | C31: TRANSPORTADORA TURISTICA BENFICA S.A | E31: 70000 | F31: =D31-E31+F30 -> 2481640.9
A32: 45524 | B32: Tarifa de conta | E32: 20 | F32: =D32-E32+F31 -> 2481620.9
A33: 45524 | B33: Crédito em conta | C33: SILVA & BEGHINI COMERCIO DE ONIBUS LTDA | D33: 6000 | F33: =D33-E33+F32 -> 2487620.9
A34: 45524 | B34: Gestão de caixa | E34: =(D33*0.005)+10 -> 40 | F34: =D34-E34+F33 -> 2487580.9
A35: 45524 | B35: Crédito em conta | C35: SILVA & BEGHINI COMERCIO DE ONIBUS LTDA | D35: 6500 | F35: =D35-E35+F34 -> 2494080.9
A36: 45524 | B36: Gestão de caixa | E36: =(D35*0.005)+10 -> 42.5 | F36: =D36-E36+F35 -> 2494038.4
A37: 45524 | B37: Crédito em conta | C37: SILVA & BEGHINI COMERCIO DE ONIBUS LTDA | D37: 6000 | F37: =D37-E37+F36 -> 2500038.4
A38: 45524 | B38: Gestão de caixa | E38: =(D37*0.005)+10 -> 40 | F38: =D38-E38+F37 -> 2499998.4
A39: 45524 | B39: Crédito em conta | C39: SILVA & BEGHINI COMERCIO DE ONIBUS LTDA | D39: 6000 | F39: =D39-E39+F38 -> 2505998.4
A40: 45524 | B40: Gestão de caixa | E40: =(D39*0.005)+10 -> 40 | F40: =D40-E40+F39 -> 2505958.4
A41: 45524 | B41: Crédito em conta | C41: SILVA & BEGHINI COMERCIO DE ONIBUS LTDA | D41: 5000 | F41: =D41-E41+F40 -> 2510958.4
A42: 45524 | B42: Gestão de caixa | E42: =(D41*0.005)+10 -> 35 | F42: =D42-E42+F41 -> 2510923.4
A43: 45524 | B43: Crédito em conta | C43: SILVA & BEGHINI COMERCIO DE ONIBUS LTDA | D43: 20000 | F43: =D43-E43+F42 -> 2530923.4
A44: 45524 | B44: Gestão de caixa | E44: =(D43*0.005)+10 -> 110 | F44: =D44-E44+F43 -> 2530813.4
A45: 45524 | B45: Crédito em conta | C45: SILVA & BEGHINI COMERCIO DE ONIBUS LTDA | D45: 6000 | F45: =D45-E45+F44 -> 2536813.4
A46: 45524 | B46: Gestão de caixa | E46: =(D45*0.005)+10 -> 40 | F46: =D46-E46+F45 -> 2536773.4
A47: 45524 | B47: Crédito em conta | C47: LUIZ PAULO DIAS MACHADO | D47: 8750 | F47: =D47-E47+F46 -> 2545523.4
A48: 45524 | B48: Gestão de caixa | E48: =(D47*0.005)+10 -> 53.75 | F48: =D48-E48+F47 -> 2545469.6
A49: 45524 | B49: Crédito em conta | C49: ARENA FUTIBA II | D49: 10900 | F49: =D49-E49+F48 -> 2556369.6
A50: 45524 | B50: Gestão de caixa | E50: =(D49*0.005)+10 -> 64.5 | F50: =D50-E50+F49 -> 2556305.1
A51: 45525 | B51: Tarifa de conta | E51: 10 | F51: =D51-E51+F50 -> 2556295.1
A52: 45525 | B52: Crédito em conta | C52: LEVEN T F T EIRELI | D52: 8750 | F52: =D52-E52+F51 -> 2565045.1
A53: 45525 | B53: Gestão de caixa | E53: =(D52*0.005)+10 -> 53.75 | F53: =D53-E53+F52 -> 2564991.4
A54: 45526 | B54: Tarifa de conta | E54: 10 | F54: =D54-E54+F53 -> 2564981.4
A55: 45526 | B55: Transferência entre contas | C55: TRANSPORTADORA TURISTICA BENFICA S.A | E55: 2000 | F55: =D55-E55+F54 -> 2562981.4
A56: 45526 | B56: Crédito em conta | C56: INDUSTRIAS ARTEB LTDA | D56: 193.94 | F56: =D56-E56+F55 -> 2563175.3
A57: 45526 | B57: Gestão de caixa | E57: =(D56*0.005)+10 -> 10.9697 | F57: =D57-E57+F56 -> 2563164.3
A58: 45527 | B58: Tarifa de conta | E58: 20 | F58: =D58-E58+F57 -> 2563144.3
A59: 45527 | B59: Crédito em conta | C59: LUIZ PAULO DIAS MACHADO | D59: 517 | F59: =D59-E59+F58 -> 2563661.3
A60: 45527 | B60: Gestão de caixa | E60: =(D59*0.005)+10 -> 12.585 | F60: =D60-E60+F59 -> 2563648.8
A61: 45527 | B61: Transferência entre contas | C61: TRANSPORTADORA TURISTICA BENFICA S.A | E61: 65000 | F61: =D61-E61+F60 -> 2498648.8
A62: 45528 | B62: Tarifa de conta | E62: 20 | F62: =D62-E62+F61 -> 2498628.8
A63: 45530 | B63: Crédito em conta | C63: BB TRANSPORTE E TURISMO LTDA | D63: 362619.38 | F63: =D63-E63+F62 -> 2861248.1
A64: 45530 | B64: Gestão de caixa | E64: =(D63*0.005)+10 -> 1823.0969 | F64: =D64-E64+F63 -> 2859425
A65: 45530 | B65: Crédito em conta | C65: METAL 2 INDUSTRIA E COMERCIO LTDA | D65: 10876.93 | F65: =D65-E65+F64 -> 2870302
A66: 45530 | B66: Gestão de caixa | E66: =(D65*0.005)+10 -> 64.38465 | F66: =D66-E66+F65 -> 2870237.6
A67: 45530 | B67: Transferência entre contas | C67: TRANSPORTADORA TURISTICA BENFICA S.A | E67: 208000 | F67: =D67-E67+F66 -> 2662237.6
A68: 45531 | B68: Tarifa de conta | E68: 20 | F68: =D68-E68+F67 -> 2662217.6
A69: 45531 | B69: Transferência entre contas | C69: TRANSPORTADORA TURISTICA BENFICA S.A | E69: 124500 | F69: =D69-E69+F68 -> 2537717.6
A70: 45531 | B70: Crédito em conta | C70: SILVA & BEGHINI COMERCIO DE ONIBUS LTDA | D70: 20000 | F70: =D70-E70+F69 -> 2557717.6
A71: 45531 | B71: Gestão de caixa | E71: =(D70*0.005)+10 -> 110 | F71: =D71-E71+F70 -> 2557607.6
A72: 45531 | B72: Crédito em conta | C72: TRANSPORTADORA TURISTICA SUZANO | D72: 31003.13 | F72: =D72-E72+F71 -> 2588610.7
A73: 45531 | B73: Gestão de caixa | E73: =(D72*0.005)+10 -> 165.01565 | F73: =D73-E73+F72 -> 2588445.7
A74: 45532 | B74: Tarifa de conta | E74: 20 | F74: =D74-E74+F73 -> 2588425.7
A75: 45532 | B75: Transferência entre contas | C75: TRANSPORTADORA TURISTICA BENFICA S.A | E75: 10000 | F75: =D75-E75+F74 -> 2578425.7
A76: 45532 | B76: Tarifa de conta | E76: 10 | F76: =D76-E76+F75 -> 2578415.7
A77: 45534 | B77: Transferência entre contas | C77: TRANSPORTADORA TURISTICA BENFICA S.A | E77: 259000 | F77: =D77-E77+F76 -> 2319415.7
A78: 45534 | B78: Tarifa de conta | E78: 10 | F78: =D78-E78+F77 -> 2319405.7
A79: 45535 | B79: Tarifa de conta | E79: 1500 | F79: =D79-E79+F78 -> 2317905.7
F80: =D80-E80+F79 -> 2317905.7
F81: =D81-E81+F80 -> 2317905.7
F82: =D82-E82+F81 -> 2317905.7
F83: =D83-E83+F82 -> 2317905.7
F84: =D84-E84+F83 -> 2317905.7
F85: =D85-E85+F84 -> 2317905.7
F86: =D86-E86+F85 -> 2317905.7
F87: =D87-E87+F86 -> 2317905.7
F88: =D88-E88+F87 -> 2317905.7
F89: =D89-E89+F88 -> 2317905.7
F90: =D90-E90+F89 -> 2317905.7
F91: =D91-E91+F90 -> 2317905.7
... F607: =D607-E607+F606 -> 2317905.7

Sheet Setembro2024
A2: EXTRATO DE MOVIMENTAÇÃO
A4: Banco | B4: LEPTA BANK (274) | C4: Agência | D4: 1 | E4: Conta | F4: 08198095-5
A5: Empresa | B5: TRANSP. TURISTICA BENFICA S.A | C5: Saldo Anterior | D5: =Agosto2024!F6 -> 2317905.7 | F5: Saldo Disponível
A6: CNPJ | B6: 59.275.289/0001-02 | C6: Totais (Entradas/Saídas) | D6: =SUM(D9:D608) -> 681193.35 | E6: =SUM(E9:E608) -> 1101356 | F6: =F608 -> 1897743.1
A8: Data | B8: Histórico | C8: Complemento | D8: Créditos | E8: Débitos | F8: Saldo
A9: 45537 | B9: Crédito em conta | C9: TRANSPORTADORA TURISTICA BENFICA AS | D9: 455.47 | F9: =D9-E9+D5 -> 2318361.2
A10: 45537 | B10: Gestão de caixa | E10: =(D9*0.005)+10 -> 12.27735 | F10: =D10-E10+F9 -> 2318348.9
A11: 45537 | B11: Crédito em conta | C11: LORINALDO DA SILVA FERREIRA | D11: 10000 | F11: =D11-E11+F10 -> 2328348.9
A12: 45537 | B12: Gestão de caixa | E12: =(D11*0.005)+10 -> 60 | F12: =D12-E12+F11 -> 2328288.9
A13: 45537 | B13: Tarifa de conta | E13: 10 | F13: =D13-E13+F12 -> 2328278.9
A14: 45538 | B14: Transferência entre contas | C14: TRANSPORTADORA TURISTICA BENFICA S.A | E14: 30000 | F14: =D14-E14+F13 -> 2298278.9
A15: 45538 | B15: Tarifa de conta | E15: 10 | F15: =D15-E15+F14 -> 2298268.9
A16: 45539 | B16: Transferência entre contas | C16: TRANSPORTADORA TURISTICA BENFICA S.A | E16: 216000 | F16: =D16-E16+F15 -> 2082268.9
A17: 45539 | B17: Tarifa de conta | E17: 10 | F17: =D17-E17+F16 -> 2082258.9
A18: 45541 | B18: Crédito em conta | C18: BB TRANSPORTE E TURISMO LTDA | D18: 90000 | F18: =D18-E18+F17 -> 2172258.9
A19: 45541 | B19: Gestão de caixa | E19: =(D18*0.005)+10 -> 460 | F19: =D19-E19+F18 -> 2171798.9
A20: 45541 | B20: Transferência entre contas | C20: TRANSPORTADORA TURISTICA BENFICA S.A | E20: 3500 | F20: =D20-E20+F19 -> 2168298.9
A21: 45541 | B21: Tarifa de conta | E21: 20 | F21: =D21-E21+F20 -> 2168278.9
A22: 45544 | B22: Crédito em conta | C22: PATRIMONY ADMINISTRADORA DE BENS AS | D22: 188462.65 | F22: =D22-E22+F21 -> 2356741.5
A23: 45544 | B23: Gestão de caixa | E23: =(D22*0.005)+10 -> 952.31325 | F23: =D23-E23+F22 -> 2355789.2
A24: 45544 | B24: Crédito em conta | C24: TRANSPORTADORA TURISTICA BENFICA S.A | D24: 8000 | F24: =D24-E24+F23 -> 2363789.2
A25: 45544 | B25: Gestão de caixa | E25: =(D24*0.005)+10 -> 50 | F25: =D25-E25+F24 -> 2363739.2
A26: 45544 | B26: Tarifa de conta | E26: 10 | F26: =D26-E26+F25 -> 2363729.2
A27: 45545 | B27: Transferência entre contas | C27: TRANSPORTADORA TURISTICA BENFICA S.A | E27: 40000 | F27: =D27-E27+F26 -> 2323729.2
A28: 45545 | B28: Transferência entre contas | C28: TRANSPORTADORA TURISTICA BENFICA S.A | E28: 27100 | F28: =D28-E28+F27 -> 2296629.2
A29: 45545 | B29: Tarifa de conta | E29: 20 | F29: =D29-E29+F28 -> 2296609.2
A30: 45548 | B30: Crédito em conta | C30: LEVEN T F T EIRELI | D30: 4500 | F30: =D30-E30+F29 -> 2301109.2
A31: 45548 | B31: Gestão de caixa | E31: =(D30*0.005)+10 -> 32.5 | F31: =D31-E31+F30 -> 2301076.7
A32: 45551 | B32: Crédito em conta | C32: MIRIA DIAS SILVEIRA TUCI | D32: 2200 | F32: =D32-E32+F31 -> 2303276.7
A33: 45551 | B33: Gestão de caixa | E33: =(D32*0.005)+10 -> 21 | F33: =D33-E33+F32 -> 2303255.7
A34: 45551 | B34: Transferência entre contas | C34: TRANSPORTADORA TURISTICA BENFICA S.A | E34: 39000 | F34: =D34-E34+F33 -> 2264255.7
A35: 45551 | B35: Tarifa de conta | E35: 20 | F35: =D35-E35+F34 -> 2264235.7
A36: 45554 | B36: Crédito em conta | C36: LUIZ PAULO DIAS MACHADO | D36: 9267.13 | F36: =D36-E36+F35 -> 2273502.9
A37: 45554 | B37: Gestão de caixa | E37: =(D36*0.005)+10 -> 56.33565 | F37: =D37-E37+F36 -> 2273446.5
A38: 45554 | B38: Transferência entre contas | C38: TRANSPORTADORA TURISTICA BENFICA S.A | E38: 60500 | F38: =D38-E38+F37 -> 2212946.5
A39: 45554 | B39: Tarifa de conta | E39: 20 | F39: =D39-E39+F38 -> 2212926.5
A40: 45555 | B40: Crédito em conta | C40: CARLA MARIA JULIANO LOPES | D40: 2000 | F40: =D40-E40+F39 -> 2214926.5
A41: 45555 | B41: Gestão de caixa | E41: =(D40*0.005)+10 -> 20 | F41: =D41-E41+F40 -> 2214906.5
A42: 45555 | B42: Crédito em conta | C42: ARENA FUTIBA II | D42: 10900 | F42: =D42-E42+F41 -> 2225806.5
A43: 45555 | B43: Gestão de caixa | E43: =(D42*0.005)+10 -> 64.5 | F43: =D43-E43+F42 -> 2225742
A44: 45558 | B44: Crédito em conta | C44: INDUSTRIAS ARTEB LTDA | D44: 193.52 | F44: =D44-E44+F43 -> 2225935.5
A45: 45558 | B45: Gestão de caixa | E45: =(D44*0.005)+10 -> 10.9676 | F45: =D45-E45+F44 -> 2225924.6
A46: 45558 | B46: Tarifa de conta | E46: 20 | F46: =D46-E46+F45 -> 2225904.6
A47: 45560 | B47: Crédito em conta | C47: - | D47: 435.47 | F47: =D47-E47+F46 -> 2226340
A48: 45560 | B48: Gestão de caixa | E48: =(D47*0.005)+10 -> 12.17735 | F48: =D48-E48+F47 -> 2226327.9
A49: 45560 | B49: Transferência entre contas | C49: TRANSPORTADORA TURISTICA BENFICA S.A | E49: 97000 | F49: =D49-E49+F48 -> 2129327.9
A50: 45560 | B50: Tarifa de conta | E50: 20 | F50: =D50-E50+F49 -> 2129307.9
A51: 45561 | B51: Crédito em conta | C51: BB TRANSPORTE E TURISMO LTDA | D51: 323375.98 | F51: =D51-E51+F50 -> 2452683.9
A52: 45561 | B52: Gestão de caixa | E52: =(D51*0.005)+10 -> 1626.8799 | F52: =D52-E52+F51 -> 2451057
A53: 45561 | B53: Crédito em conta | C53: TRANSPORTADORA TURISTICA BENFICA S.A | D53: 400 | F53: =D53-E53+F52 -> 2451457
A54: 45561 | B54: Gestão de caixa | E54: =(D53*0.005)+10 -> 12 | F54: =D54-E54+F53 -> 2451445
A55: 45561 | B55: Transferência entre contas | C55: TRANSPORTADORA TURISTICA BENFICA S.A | E55: 328000 | F55: =D55-E55+F54 -> 2123445
A56: 45561 | B56: Tarifa de conta | E56: 20 | F56: =D56-E56+F55 -> 2123425
A57: 45562 | B57: Crédito em conta | C57: TRANSPORTADORA TURISTICA SUZANO | D57: 31003.13 | F57: =D57-E57+F56 -> 2154428.1
A58: 45562 | B58: Gestão de caixa | E58: =(D57*0.005)+10 -> 165.01565 | F58: =D58-E58+F57 -> 2154263.1
A59: 45562 | B59: Tarifa de conta | E59: 10 | F59: =D59-E59+F58 -> 2154253.1
A60: 45565 | B60: Transferência entre contas | C60: TRANSPORTADORA TURISTICA BENFICA S.A | E60: 255000 | F60: =D60-E60+F59 -> 1899253.1
A61: 45565 | B61: Tarifa de conta | E61: 1510 | F61: =D61-E61+F60 -> 1897743.1
F62: =D62-E62+F61 -> 1897743.1
F63: =D63-E63+F62 -> 1897743.1
F64: =D64-E64+F63 -> 1897743.1
F65: =D65-E65+F64 -> 1897743.1
F66: =D66-E66+F65 -> 1897743.1
F67: =D67-E67+F66 -> 1897743.1
F68: =D68-E68+F67 -> 1897743.1
F69: =D69-E69+F68 -> 1897743.1
F70: =D70-E70+F69 -> 1897743.1
F71: =D71-E71+F70 -> 1897743.1
F72: =D72-E72+F71 -> 1897743.1
F73: =D73-E73+F72 -> 1897743.1
... F608: =D608-E608+F607 -> 1897743.1

Sheet Outubro2024
A2: EXTRATO DE MOVIMENTAÇÃO
A4: Banco | B4: LEPTA BANK (274) | C4: Agência | D4: 1 | E4: Conta | F4: 08198095-5
A5: Empresa | B5: TRANSP. TURISTICA BENFICA S.A | C5: Saldo Anterior | D5: =Setembro2024!F6 -> 1897743.1 | F5: Saldo Disponível
A6: CNPJ | B6: 59.275.289/0001-02 | C6: Totais (Entradas/Saídas) | D6: =SUM(D9:D607) -> 788083.15 | E6: =SUM(E9:E607) -> 978280.42 | F6: =F607 -> 1707545.8
A8: Data | B8: Histórico | C8: Complemento | D8: Créditos | E8: Débitos | F8: Saldo
A9: 45566 | B9: Crédito em conta | C9: TRANSPORTADORA TURISTICA BENFICA AS | D9: 7650 | F9: =D9-E9+D5 -> 1905393.1
A10: 45566 | B10: Gestão de caixa | E10: =(D9*0.005)+10 -> 48.25 | F10: =D10-E10+F9 -> 1905344.8
A11: 45566 | B11: Crédito em conta | C11: METAL 2 INDUSTRIA E COMERCIO LTDA | D11: 10989.32 | F11: =D11-E11+F10 -> 1916334.2
A12: 45566 | B12: Gestão de caixa | E12: =(D11*0.005)+10 -> 64.9466 | F12: =D12-E12+F11 -> 1916269.2
A13: 45566 | B13: Tarifa de conta | E13: 10 | F13: =D13-E13+F12 -> 1916259.2
A14: 45567 | B14: Transferência entre contas | C14: TRANSPORTADORA TURISTICA BENFICA S.A | E14: 7000 | F14: =D14-E14+F13 -> 1909259.2
A15: 45567 | B15: Tarifa de conta | E15: 10 | F15: =D15-E15+F14 -> 1909249.2
A16: 45568 | B16: Transferência entre contas | C16: TRANSPORTADORA TURISTICA BENFICA S.A | E16: 199000 | F16: =D16-E16+F15 -> 1710249.2
A17: 45568 | B17: Tarifa de conta | E17: 10 | F17: =D17-E17+F16 -> 1710239.2
A18: 45569 | B18: Crédito em conta | C18: LORINALDO DA SILVA FERREIRA | D18: 10000 | F18: =D18-E18+F17 -> 1720239.2
A19: 45569 | B19: Gestão de caixa | E19: =(D18*0.005)+10 -> 60 | F19: =D19-E19+F18 -> 1720179.2
A20: 45569 | B20: Tarifa de conta | E20: 10 | F20: =D20-E20+F19 -> 1720169.2
A21: 45572 | B21: Crédito em conta | C21: BB TRANSPORTE E TURISMO LTDA | D21: 90000 | F21: =D21-E21+F20 -> 1810169.2
A22: 45572 | B22: Gestão de caixa | E22: =(D21*0.005)+10 -> 460 | F22: =D22-E22+F21 -> 1809709.2
A23: 45572 | B23: Tarifa de conta | E23: 10 | F23: =D23-E23+F22 -> 1809699.2
A24: 45573 | B24: Crédito em conta | C24: PATRIMONY ADMINISTRADORA DE BENS AS | D24: 188462.65 | F24: =D24-E24+F23 -> 1998161.9
A25: 45573 | B25: Gestão de caixa | E25: =(D24*0.005)+10 -> 952.31325 | F25: =D25-E25+F24 -> 1997209.5
A26: 45573 | B26: Tarifa de conta | E26: 10 | F26: =D26-E26+F25 -> 1997199.5
A27: 45574 | B27: Crédito em conta | C27: LEVEN T F T EIRELI | D27: 4250 | F27: =D27-E27+F26 -> 2001449.5
A28: 45574 | B28: Gestão de caixa | E28: =(D27*0.005)+10 -> 31.25 | F28: =D28-E28+F27 -> 2001418.3
A29: 45574 | B29: Tarifa de conta | E29: 10 | F29: =D29-E29+F28 -> 2001408.3
A30: 45575 | B30: Transferência entre contas | C30: TRANSPORTADORA TURISTICA BENFICA S.A | E30: 85000 | F30: =D30-E30+F29 -> 1916408.3
A31: 45575 | B31: Tarifa de conta | E31: 10 | F31: =D31-E31+F30 -> 1916398.3
A32: 45576 | B32: Crédito em conta | C32: SILVA & BEGHINI COMERCIO DE ONIBUS LTDA | D32: 6000 | F32: =D32-E32+F31 -> 1922398.3
A33: 45576 | B33: Gestão de caixa | E33: =(D32*0.005)+10 -> 40 | F33: =D33-E33+F32 -> 1922358.3
A34: 45576 | B34: Crédito em conta | C34: SILVA & BEGHINI COMERCIO DE ONIBUS LTDA | D34: 5000 | F34: =D34-E34+F33 -> 1927358.3
A35: 45576 | B35: Gestão de caixa | E35: =(D34*0.005)+10 -> 35 | F35: =D35-E35+F34 -> 1927323.3
A36: 45576 | B36: Tarifa de conta | E36: 10 | F36: =D36-E36+F35 -> 1927313.3
A37: 45579 | B37: Crédito em conta | C37: SILVA & BEGHINI COMERCIO DE ONIBUS LTDA | D37: 6000 | F37: =D37-E37+F36 -> 1933313.3
A38: 45579 | B38: Gestão de caixa | E38: =(D37*0.005)+10 -> 40 | F38: =D38-E38+F37 -> 1933273.3
A39: 45579 | B39: Crédito em conta | C39: SILVA & BEGHINI COMERCIO DE ONIBUS LTDA | D39: 6000 | F39: =D39-E39+F38 -> 1939273.3
A40: 45579 | B40: Gestão de caixa | E40: =(D39*0.005)+10 -> 40 | F40: =D40-E40+F39 -> 1939233.3
A41: 45579 | B41: Crédito em conta | C41: SILVA & BEGHINI COMERCIO DE ONIBUS LTDA | D41: 20000 | F41: =D41-E41+F40 -> 1959233.3
A42: 45579 | B42: Gestão de caixa | E42: =(D41*0.005)+10 -> 110 | F42: =D42-E42+F41 -> 1959123.3
A43: 45579 | B43: Crédito em conta | C43: SILVA & BEGHINI COMERCIO DE ONIBUS LTDA | D43: 20000 | F43: =D43-E43+F42 -> 1979123.3
A44: 45579 | B44: Gestão de caixa | E44: =(D43*0.005)+10 -> 110 | F44: =D44-E44+F43 -> 1979013.3
A45: 45579 | B45: Tarifa de conta | E45: 10 | F45: =D45-E45+F44 -> 1979003.3
A46: 45580 | B46: Transferência entre contas | C46: TRANSPORTADORA TURISTICA BENFICA S.A | E46: 24300 | F46: =D46-E46+F45 -> 1954703.3
A47: 45580 | B47: Tarifa de conta | E47: 10 | F47: =D47-E47+F46 -> 1954693.3
A48: 45582 | B48: Crédito em conta | C48: MIRIA DIAS SILVEIRA TUCI | D48: 2200 | F48: =D48-E48+F47 -> 1956893.3
A49: 45582 | B49: Gestão de caixa | E49: =(D48*0.005)+10 -> 21 | F49: =D49-E49+F48 -> 1956872.3
A50: 45582 | B50: Crédito em conta | C50: LUIZ PAULO DIAS MACHADO | D50: 4634 | F50: =D50-E50+F49 -> 1961506.3
A51: 45582 | B51: Gestão de caixa | E51: =(D50*0.005)+10 -> 33.17 | F51: =D51-E51+F50 -> 1961473.1
A52: 45582 | B52: Tarifa de conta | E52: 10 | F52: =D52-E52+F51 -> 1961463.1
A53: 45583 | B53: Crédito em conta | C53: JESUITO FRANCISCO COSTA | D53: 6150 | F53: =D53-E53+F52 -> 1967613.1
A54: 45583 | B54: Gestão de caixa | E54: =(D53*0.005)+10 -> 40.75 | F54: =D54-E54+F53 -> 1967572.4
A55: 45583 | B55: Transferência entre contas | C55: TRANSPORTADORA TURISTICA BENFICA S.A | E55: 16500 | F55: =D55-E55+F54 -> 1951072.4
A56: 45583 | B56: Tarifa de conta | E56: 20 | F56: =D56-E56+F55 -> 1951052.4
A57: 45586 | B57: Crédito em conta | C57: ARENA FUTIBA II | D57: 10900 | F57: =D57-E57+F56 -> 1961952.4
A58: 45586 | B58: Gestão de caixa | E58: =(D57*0.005)+10 -> 64.5 | F58: =D58-E58+F57 -> 1961887.9
A59: 45586 | B59: Transferência entre contas | C59: TRANSPORTADORA TURISTICA BENFICA S.A | E59: 6800 | F59: =D59-E59+F58 -> 1955087.9
A60: 45586 | B60: Tarifa de conta | E60: 20 | F60: =D60-E60+F59 -> 1955067.9
A61: 45587 | B61: Crédito em conta | C61: INDUSTRIAS ARTEB LTDA | D61: 192.07 | F61: =D61-E61+F60 -> 1955259.9
A62: 45587 | B62: Gestão de caixa | E62: =(D61*0.005)+10 -> 10.96035 | F62: =D62-E62+F61 -> 1955249
A63: 45587 | B63: Tarifa de conta | E63: 10 | F63: =D63-E63+F62 -> 1955239
A64: 45588 | B64: Transferência entre contas | C64: TRANSPORTADORA TURISTICA BENFICA S.A | E64: 8400 | F64: =D64-E64+F63 -> 1946839
A65: 45588 | B65: Tarifa de conta | E65: 10 | F65: =D65-E65+F64 -> 1946829
A66: 45589 | B66: Transferência entre contas | C66: TRANSPORTADORA TURISTICA BENFICA S.A | E66: 43500 | F66: =D66-E66+F65 -> 1903329
A67: 45589 | B67: Tarifa de conta | E67: 10 | F67: =D67-E67+F66 -> 1903319
A68: 45590 | B68: Crédito em conta | C68: BB TRANSPORTE E TURISMO LTDA | D68: 349411.69 | F68: =D68-E68+F67 -> 2252730.7
A69: 45590 | B69: Gestão de caixa | E69: =(D68*0.005)+10 -> 1757.0584 | F69: =D69-E69+F68 -> 2250973.6
A70: 45590 | B70: Transferência entre contas | C70: TRANSPORTADORA TURISTICA BENFICA S.A | E70: 310900 | F70: =D70-E70+F69 -> 1940073.6
A71: 45590 | B71: Tarifa de conta | E71: 20 | F71: =D71-E71+F70 -> 1940053.6
A72: 45593 | B72: Crédito em conta | C72: TRANSPORTADORA TURISTICA SUZANO LTDA | D72: 31003.13 | F72: =D72-E72+F71 -> 1971056.7
A73: 45593 | B73: Gestão de caixa | E73: =(D72*0.005)+10 -> 165.01565 | F73: =D73-E73+F72 -> 1970891.7
A74: 45593 | B74: Tarifa de conta | E74: 10 | F74: =D74-E74+F73 -> 1970881.7
A75: 45594 | B75: Transferência entre contas | C75: TRANSPORTADORA TURISTICA BENFICA S.A | E75: 271000 | F75: =D75-E75+F74 -> 1699881.7
A76: 45594 | B76: Tarifa de conta | E76: 10 | F76: =D76-E76+F75 -> 1699871.7
A77: 45595 | B77: Crédito em conta | C77: TED RECEBIDA | D77: 9240.29 | F77: =D77-E77+F76 -> 1709112
A78: 45595 | B78: Gestão de caixa | E78: =(D77*0.005)+10 -> 56.20145 | F78: =D78-E78+F77 -> 1709055.8
A79: 45596 | B79: Tarifa de conta | E79: 10 | F79: =D79-E79+F78 -> 1709045.8
A80: 45596 | B80: Tarifa de conta | E80: 1500 | F80: =D80-E80+F79 -> 1707545.8
F81: =D81-E81+F80 -> 1707545.8
F82: =D82-E82+F81 -> 1707545.8
F83: =D83-E83+F82 -> 1707545.8
F84: =D84-E84+F83 -> 1707545.8
F85: =D85-E85+F84 -> 1707545.8
F86: =D86-E86+F85 -> 1707545.8
F87: =D87-E87+F86 -> 1707545.8
F88: =D88-E88+F87 -> 1707545.8
F89: =D89-E89+F88 -> 1707545.8
F90: =D90-E90+F89 -> 1707545.8
F91: =D91-E91+F90 -> 1707545.8
F92: =D92-E92+F91 -> 1707545.8
... F607: =D607-E607+F606 -> 1707545.8

Sheet Novembro2024
A2: EXTRATO DE MOVIMENTAÇÃO
A4: Banco | B4: LEPTA BANK (274) | C4: Agência | D4: 1 | E4: Conta | F4: 08198095-5
A5: Empresa | B5: TRANSP. TURISTICA BENFICA S.A | C5: Saldo Anterior | D5: =Outubro2024!F6 -> 1707545.8 | F5: Saldo Disponível
A6: CNPJ | B6: 59.275.289/0001-02 | C6: Totais (Entradas/Saídas) | D6: =SUM(D9:D607) -> 907233.64 | E6: =SUM(E9:E607) -> 1049708.9 | F6: =F607 -> 1565070.5
A8: Data | B8: Histórico | C8: Complemento | D8: Créditos | E8: Débitos | F8: Saldo
A9: 45597 | B9: Crédito em conta | C9: TRANSPORTADORA TURISTICA BENFICA AS | D9: 144.15 | F9: =D9-E9+D5 -> 1707690
A10: 45597 | B10: Gestão de caixa | E10: =(D9*0.005)+10 -> 10.72075 | F10: =D10-E10+F9 -> 1707679.2
A11: 45597 | B11: Transferência entre contas | C11: TRANSPORTADORA TURISTICA BENFICA S.A | E11: 233000 | F11: =D11-E11+F10 -> 1474679.2
A12: 45597 | B12: Crédito em conta | C12: METAL 2 INDUSTRIA E COMERCIO LTDA | D12: 11091.3 | F12: =D12-E12+F11 -> 1485770.5
A13: 45597 | B13: Gestão de caixa | E13: =(D12*0.005)+10 -> 65.4565 | F13: =D13-E13+F12 -> 1485705.1
A14: 45597 | B14: Crédito em conta | C14: MPS SOARES TRANSPORTE LTDA | D14: 8000 | F14: =D14-E14+F13 -> 1493705.1
A15: 45597 | B15: Gestão de caixa | E15: =(D14*0.005)+10 -> 50 | F15: =D15-E15+F14 -> 1493655.1
A16: 45597 | B16: Tarifa de conta | E16: 20 | F16: =D16-E16+F15 -> 1493635.1
A17: 45600 | B17: Crédito em conta | C17: LUIZ PAULO DIAS MACHADO | D17: 4634 | F17: =D17-E17+F16 -> 1498269.1
A18: 45600 | B18: Gestão de caixa | E18: =(D17*0.005)+10 -> 33.17 | F18: =D18-E18+F17 -> 1498235.9
A19: 45600 | B19: Tarifa de conta | E19: 10 | F19: =D19-E19+F18 -> 1498225.9
A20: 45601 | B20: Crédito em conta | C20: LORINALDO DA SILVA FERREIRA | D20: 10000 | F20: =D20-E20+F19 -> 1508225.9
A21: 45601 | B21: Gestão de caixa | E21: =(D20*0.005)+10 -> 60 | F21: =D21-E21+F20 -> 1508165.9
A22: 45601 | B22: Transferência entre contas | C22: TRANSPORTADORA TURISTICA BENFICA S.A | E22: 2400 | F22: =D22-E22+F21 -> 1505765.9
A23: 45601 | B23: Tarifa de conta | E23: 20 | F23: =D23-E23+F22 -> 1505745.9
A24: 45603 | B24: Crédito em conta | C24: BB TRANSPORTE E TURISMO LTDA | D24: 90000 | F24: =D24-E24+F23 -> 1595745.9
A25: 45603 | B25: Gestão de caixa | E25: =(D24*0.005)+10 -> 460 | F25: =D25-E25+F24 -> 1595285.9
A26: 45603 | B26: Tarifa de conta | E26: 10 | F26: =D26-E26+F25 -> 1595275.9
A27: 45604 | B27: Crédito em conta | C27: PATRIMONY ADMINISTRADORA DE BENS AS | D27: 188462.65 | F27: =D27-E27+F26 -> 1783738.6
A28: 45604 | B28: Gestão de caixa | E28: =(D27*0.005)+10 -> 952.31325 | F28: =D28-E28+F27 -> 1782786.3
A29: 45604 | B29: Transferência entre contas | C29: TRANSPORTADORA TURISTICA BENFICA S.A | E29: 9500 | F29: =D29-E29+F28 -> 1773286.3
A30: 45604 | B30: Tarifa de conta | E30: 20 | F30: =D30-E30+F29 -> 1773266.3
A31: 45607 | B31: Transferência entre contas | C31: TRANSPORTADORA TURISTICA BENFICA S.A | E31: 64600 | F31: =D31-E31+F30 -> 1708666.3
A32: 45607 | B32: Crédito em conta | C32: VESPER TRANSPORTES LTDA | D32: 12833.33 | F32: =D32-E32+F31 -> 1721499.6
A33: 45607 | B33: Gestão de caixa | E33: =(D32*0.005)+10 -> 74.16665 | F33: =D33-E33+F32 -> 1721425.4
A34: 45607 | B34: Tarifa de conta | E34: 10 | F34: =D34-E34+F33 -> 1721415.4
A35: 45608 | B35: Tarifa de conta | E35: 10 | F35: =D35-E35+F34 -> 1721405.4
A36: 45610 | B36: Transferência entre contas | C36: TRANSPORTADORA TURISTICA BENFICA S.A | E36: 19000 | F36: =D36-E36+F35 -> 1702405.4
A37: 45610 | B37: Tarifa de conta | E37: 10 | F37: =D37-E37+F36 -> 1702395.4
A38: 45614 | B38: Transferência entre contas | C38: TRANSPORTADORA TURISTICA BENFICA S.A | E38: 31000 | F38: =D38-E38+F37 -> 1671395.4
A39: 45614 | B39: Crédito em conta | C39: SILVA & BEGHINI COMERCIO DE ONIBUS LTDA | D39: 55208.92 | F39: =D39-E39+F38 -> 1726604.3
A40: 45614 | B40: Gestão de caixa | E40: =(D39*0.005)+10 -> 286.0446 | F40: =D40-E40+F39 -> 1726318.3
A41: 45614 | B41: Crédito em conta | C41: MIRIA DIAS SILVEIRA TUCI | D41: 2200 | F41: =D41-E41+F40 -> 1728518.3
A42: 45614 | B42: Gestão de caixa | E42: =(D41*0.005)+10 -> 21 | F42: =D42-E42+F41 -> 1728497.3
A43: 45614 | B43: Tarifa de conta | E43: 20 | F43: =D43-E43+F42 -> 1728477.3
A44: 45615 | B44: Transferência entre contas | C44: TRANSPORTADORA TURISTICA BENFICA S.A | E44: 54000 | F44: =D44-E44+F43 -> 1674477.3
A45: 45615 | B45: Tarifa de conta | E45: 10 | F45: =D45-E45+F44 -> 1674467.3
A46: 45616 | B46: Crédito em conta | C46: ARENA FUTIBA II | D46: 10900 | F46: =D46-E46+F45 -> 1685367.3
A47: 45616 | B47: Gestão de caixa | E47: =(D46*0.005)+10 -> 64.5 | F47: =D47-E47+F46 -> 1685302.8
A48: 45617 | B48: Crédito em conta | C48: INDUSTRIAS ARTEB LTDA | D48: 192.69 | F48: =D48-E48+F47 -> 1685495.5
A49: 45617 | B49: Gestão de caixa | E49: =(D48*0.005)+10 -> 10.96345 | F49: =D49-E49+F48 -> 1685484.5
A50: 45617 | B50: Transferência entre contas | C50: TRANSPORTADORA TURISTICA BENFICA S.A | E50: 14850 | F50: =D50-E50+F49 -> 1670634.5
A51: 45617 | B51: Tarifa de conta | E51: 20 | F51: =D51-E51+F50 -> 1670614.5
A52: 45618 | B52: Transferência entre contas | C52: TRANSPORTADORA TURISTICA BENFICA S.A | E52: 6700 | F52: =D52-E52+F51 -> 1663914.5
A53: 45618 | B53: Tarifa de conta | E53: 10 | F53: =D53-E53+F52 -> 1663904.5
A54: 45621 | B54: Transferência entre contas | C54: TRANSPORTADORA TURISTICA BENFICA S.A | E54: 23000 | F54: =D54-E54+F53 -> 1640904.5
A55: 45621 | B55: Crédito em conta | C55: METAL 2 INDUSTRIA E COMERCIO LTDA | D55: 11155.83 | F55: =D55-E55+F54 -> 1652060.4
A56: 45621 | B56: Gestão de caixa | E56: =(D55*0.005)+10 -> 65.77915 | F56: =D56-E56+F55 -> 1651994.6
A57: 45621 | B57: Tarifa de conta | E57: 20 | F57: =D57-E57+F56 -> 1651974.6
A58: 45622 | B58: Crédito em conta | C58: DOCINI PROMOCAO DE VENDAS LTDA | D58: 2600 | F58: =D58-E58+F57 -> 1654574.6
A59: 45622 | B59: Gestão de caixa | E59: 65.77915 | F59: =D59-E59+F58 -> 1654508.8
A60: 45622 | B60: Tarifa de conta | E60: 10 | F60: =D60-E60+F59 -> 1654498.8
A61: 45623 | B61: Crédito em conta | C61: TRANSPORTADORA TURISTICA SUZANO LTDA | D61: 31003.13 | F61: =D61-E61+F60 -> 1685501.9
A62: 45623 | B62: Gestão de caixa | E62: =(D61*0.005)+10 -> 165.01565 | F62: =D62-E62+F61 -> 1685336.9
A63: 45623 | B63: Crédito em conta | C63: BB TRANSPORTE E TURISMO LTDA | D63: 468807.64 | F63: =D63-E63+F62 -> 2154144.5
A64: 45623 | B64: Gestão de caixa | E64: =(D63*0.005)+10 -> 2354.0382 | F64: =D64-E64+F63 -> 2151790.5
A65: 45624 | B65: Transferência entre contas | C65: TRANSPORTADORA TURISTICA BENFICA S.A | E65: 585200 | F65: =D65-E65+F64 -> 1566590.5
A66: 45624 | B66: Tarifa de conta | E66: 20 | F66: =D66-E66+F65 -> 1566570.5
A67: 45626 | B67: Tarifa de conta | E67: 1500 | F67: =D67-E67+F66 -> 1565070.5
F68: =D68-E68+F67 -> 1565070.5
F69: =D69-E69+F68 -> 1565070.5
F70: =D70-E70+F69 -> 1565070.5
F71: =D71-E71+F70 -> 1565070.5
F72: =D72-E72+F71 -> 1565070.5
F73: =D73-E73+F72 -> 1565070.5
F74: =D74-E74+F73 -> 1565070.5
F75: =D75-E75+F74 -> 1565070.5
F76: =D76-E76+F75 -> 1565070.5
F77: =D77-E77+F76 -> 1565070.5
F78: =D78-E78+F77 -> 1565070.5
F79: =D79-E79+F78 -> 1565070.5
... F607: =D607-E607+F606 -> 1565070.5

Sheet Dezembro2024 
A2: EXTRATO DE MOVIMENTAÇÃO
A4: Banco | B4: LEPTA BANK (274) | C4: Agência | D4: 1 | E4: Conta | F4: 08198095-5
A5: Empresa | B5: TRANSP. TURISTICA BENFICA S.A | C5: Saldo Anterior | D5: =Novembro2024!F6 -> 1565070.5 | F5: Saldo Disponível
A6: CNPJ | B6: 59.275.289/0001-02 | C6: Totais (Entradas/Saídas) | D6: =SUM(D9:D607) -> 804841.2 | E6: =SUM(E9:E607) -> 1085564.2 | F6: =F607 -> 1284347.5
A8: Data | B8: Histórico | C8: Complemento | D8: Créditos | E8: Débitos | F8: Saldo
A9: 45628 | B9: Transferência entre contas | C9: TRANSPORTADORA TURISTICA BENFICA S.A | E9: 7000 | F9: =D9-E9+D5 -> 1558070.5
A10: 45628 | B10: Crédito em conta | C10: MPS SOARES TRANSPORTE LTDA | D10: 8000 | F10: =D10-E10+F9 -> 1566070.5
A11: 45628 | B11: Gestão de caixa | E11: =(D10*0.005)+10 -> 50 | F11: =D11-E11+F10 -> 1566020.5
A12: 45628 | B12: Tarifa de conta | E12: 20 | F12: =D12-E12+F11 -> 1566000.5
A13: 45629 | B13: Transferência entre contas | C13: TRANSPORTADORA TURISTICA BENFICA S.A | E13: 206700 | F13: =D13-E13+F12 -> 1359300.5
A14: 45629 | B14: Tarifa de conta | E14: 10 | F14: =D14-E14+F13 -> 1359290.5
A15: 45630 | B15: Crédito em conta | C15: SILVA & BEGHINI COMERCIO DE ONIBUS LTDA | D15: 5000 | F15: =D15-E15+F14 -> 1364290.5
A16: 45630 | B16: Gestão de caixa | E16: =(D15*0.005)+10 -> 35 | F16: =D16-E16+F15 -> 1364255.5
A17: 45630 | B17: Crédito em conta | C17: BENFICA CARGAS E LOGISTICA S.A | D17: 10 | F17: =D17-E17+F16 -> 1364265.5
A18: 45630 | B18: Gestão de caixa | E18: =(D17*0.005)+10 -> 10.05 | F18: =D18-E18+F17 -> 1364255.5
A19: 45630 | B19: Tarifa de conta | E19: 10 | F19: =D19-E19+F18 -> 1364245.5
A20: 45631 | B20: Crédito em conta | C20: BB TRANSPORTE E TURISMO LTDA | D20: 90000 | F20: =D20-E20+F19 -> 1454245.5
A21: 45631 | B21: Gestão de caixa | E21: =(D20*0.005)+10 -> 460 | F21: =D21-E21+F20 -> 1453785.5
A22: 45631 | B22: Transferência entre contas | C22: TRANSPORTADORA TURISTICA BENFICA S.A | E22: 14500 | F22: =D22-E22+F21 -> 1439285.5
A23: 45631 | B23: Tarifa de conta | E23: 20 | F23: =D23-E23+F22 -> 1439265.5
A24: 45632 | B24: Crédito em conta | C24: GILBERTO DOS SANTOS SILVA | D24: 350 | F24: =D24-E24+F23 -> 1439615.5
A25: 45632 | B25: Gestão de caixa | E25: =(D24*0.005)+10 -> 11.75 | F25: =D25-E25+F24 -> 1439603.7
A26: 45635 | B26: Transferência entre contas | C26: TRANSPORTADORA TURISTICA BENFICA S.A | E26: 1600 | F26: =D26-E26+F25 -> 1438003.7
A27: 45635 | B27: Crédito em conta | C27: PATRIMONY ADMINISTRADORA DE BENS AS | D27: 196878.62 | F27: =D27-E27+F26 -> 1634882.3
A28: 45635 | B28: Gestão de caixa | E28: =(D27*0.005)+10 -> 994.3931 | F28: =D28-E28+F27 -> 1633887.9
A29: 45635 | B29: Tarifa de conta | E29: 30 | F29: =D29-E29+F28 -> 1633857.9
A30: 45636 | B30: Crédito em conta | C30: GILBERTO DOS SANTOS SILVA | D30: 350 | F30: =D30-E30+F29 -> 1634207.9
A31: 45636 | B31: Gestão de caixa | E31: =(D30*0.005)+10 -> 11.75 | F31: =D31-E31+F30 -> 1634196.2
A32: 45636 | B32: Transferência entre contas | C32: TRANSPORTADORA TURISTICA BENFICA S.A | E32: 77100 | F32: =D32-E32+F31 -> 1557096.2
A33: 45636 | B33: Crédito em conta | C33: LORINALDO DA SILVA FERREIRA | D33: 10000 | F33: =D33-E33+F32 -> 1567096.2
A34: 45636 | B34: Gestão de caixa | E34: =(D33*0.005)+10 -> 60 | F34: =D34-E34+F33 -> 1567036.2
A35: 45636 | B35: Crédito em conta | C35: VESPER TRANSPORTES LTDA | D35: 10000 | F35: =D35-E35+F34 -> 1577036.2
A36: 45636 | B36: Gestão de caixa | E36: =(D35*0.005)+10 -> 60 | F36: =D36-E36+F35 -> 1576976.2
A37: 45636 | B37: Tarifa de conta | E37: 20 | F37: =D37-E37+F36 -> 1576956.2
A38: 45637 | B38: Tarifa de conta | E38: 10 | F38: =D38-E38+F37 -> 1576946.2
A39: 45639 | B39: Transferência entre contas | C39: TRANSPORTADORA TURISTICA BENFICA S.A | E39: 2200 | F39: =D39-E39+F38 -> 1574746.2
A40: 45639 | B40: Tarifa de conta | E40: 10 | F40: =D40-E40+F39 -> 1574736.2
A41: 45642 | B41: Crédito em conta | C41: SILVA & BEGHINI COMERCIO DE ONIBUS LTDA | D41: 30591.08 | F41: =D41-E41+F40 -> 1605327.3
A42: 45642 | B42: Gestão de caixa | E42: =(D41*0.005)+10 -> 162.9554 | F42: =D42-E42+F41 -> 1605164.3
A43: 45642 | B43: Transferência entre contas | C43: TRANSPORTADORA TURISTICA BENFICA S.A | E43: 49800 | F43: =D43-E43+F42 -> 1555364.3
A44: 45642 | B44: Tarifa de conta | E44: 20 | F44: =D44-E44+F43 -> 1555344.3
A45: 45643 | B45: Crédito em conta | C45: MIRIA DIAS SILVEIRA TUCI | D45: 2200 | F45: =D45-E45+F44 -> 1557544.3
A46: 45643 | B46: Gestão de caixa | E46: =(D45*0.005)+10 -> 21 | F46: =D46-E46+F45 -> 1557523.3
A47: 45643 | B47: Transferência entre contas | C47: TRANSPORTADORA TURISTICA BENFICA S.A | E47: 2300 | F47: =D47-E47+F46 -> 1555223.3
A48: 45643 | B48: Crédito em conta | C48: SILVA & BEGHINI COMERCIO DE ONIBUS LTDA | D48: 7200 | F48: =D48-E48+F47 -> 1562423.3
A49: 45643 | B49: Gestão de caixa | E49: =(D48*0.005)+10 -> 46 | F49: =D49-E49+F48 -> 1562377.3
A50: 45643 | B50: Tarifa de conta | E50: 20 | F50: =D50-E50+F49 -> 1562357.3
A51: 45645 | B51: Crédito em conta | C51: INDUSTRIAS ARTEB LTDA | D51: 191.27 | F51: =D51-E51+F50 -> 1562548.6
A52: 45645 | B52: Gestão de caixa | E52: =(D51*0.005)+10 -> 10.95635 | F52: =D52-E52+F51 -> 1562537.6
A53: 45645 | B53: Transferência entre contas | C53: TRANSPORTADORA TURISTICA BENFICA S.A | E53: 117800 | F53: =D53-E53+F52 -> 1444737.6
A54: 45645 | B54: Tarifa de conta | E54: 20 | F54: =D54-E54+F53 -> 1444717.6
A55: 45646 | B55: Crédito em conta | C55: ARENA FUTIBA II | D55: 10900 | F55: =D55-E55+F54 -> 1455617.6
A56: 45646 | B56: Gestão de caixa | E56: =(D55*0.005)+10 -> 64.5 | F56: =D56-E56+F55 -> 1455553.1
A57: 45646 | B57: Tarifa de conta | E57: 10 | F57: =D57-E57+F56 -> 1455543.1
A58: 45650 | B58: Crédito em conta | C58: BB TRANSPORTE E TURISMO LTDA | D58: 390411.59 | F58: =D58-E58+F57 -> 1845954.7
A59: 45650 | B59: Gestão de caixa | E59: =(D58*0.005)+10 -> 1962.058 | F59: =D59-E59+F58 -> 1843992.7
A60: 45650 | B60: Transferência entre contas | C60: TRANSPORTADORA TURISTICA BENFICA S.A | E60: 331000 | F60: =D60-E60+F59 -> 1512992.7
A61: 45650 | B61: Tarifa de conta | E61: 20 | F61: =D61-E61+F60 -> 1512972.7
A62: 45652 | B62: Crédito em conta | C62: METAL 2 INDUSTRIA E COMERCIO LTDA | D62: 11262.86 | F62: =D62-E62+F61 -> 1524235.5
A63: 45652 | B63: Gestão de caixa | E63: =(D62*0.005)+10 -> 66.3143 | F63: =D63-E63+F62 -> 1524169.2
A64: 45652 | B64: Transferência entre contas | C64: TRANSPORTADORA TURISTICA BENFICA S.A | E64: 269600 | F64: =D64-E64+F63 -> 1254569.2
A65: 45652 | B65: Tarifa de conta | E65: 20 | F65: =D65-E65+F64 -> 1254549.2
A66: 45653 | B66: Crédito em conta | C66: TRANSPORTADORA TURISTICA SUZANO LTDA | D66: 31003.13 | F66: =D66-E66+F65 -> 1285552.3
A67: 45653 | B67: Gestão de caixa | E67: =(D66*0.005)+10 -> 165.01565 | F67: =D67-E67+F66 -> 1285387.3
A68: 45653 | B68: Tarifa de conta | E68: 10 | F68: =D68-E68+F67 -> 1285377.3
A69: 45656 | B69: Crédito em conta | C69: TRANSPORTADORA TURISTICA BENFICA AS | D69: 492.65 | F69: =D69-E69+F68 -> 1285870
A70: 45656 | B70: Gestão de caixa | E70: =(D69*0.005)+10 -> 12.46325 | F70: =D70-E70+F69 -> 1285857.5
A71: 45657 | B71: Tarifa de conta | E71: 10 | F71: =D71-E71+F70 -> 1285847.5
A72: 45657 | B72: Tarifa de conta | E72: 1500 | F72: =D72-E72+F71 -> 1284347.5
A73: 45657 | B73: Ajuste de Saldo | E73: 0.03 | F73: =D73-E73+F72 -> 1284347.5
F74: =D74-E74+F73 -> 1284347.5
F75: =D75-E75+F74 -> 1284347.5
F76: =D76-E76+F75 -> 1284347.5
F77: =D77-E77+F76 -> 1284347.5
F78: =D78-E78+F77 -> 1284347.5
F79: =D79-E79+F78 -> 1284347.5
F80: =D80-E80+F79 -> 1284347.5
F81: =D81-E81+F80 -> 1284347.5
F82: =D82-E82+F81 -> 1284347.5
F83: =D83-E83+F82 -> 1284347.5
F84: =D84-E84+F83 -> 1284347.5
F85: =D85-E85+F84 -> 1284347.5
... F607: =D607-E607+F606 -> 1284347.5

Sheet Janeiro2025
A2: EXTRATO DE MOVIMENTAÇÃO
A4: Banco | B4: LEPTA BANK (274) | C4: Agência | D4: 1 | E4: Conta | F4: 08198095-5
A5: Empresa | B5: TRANSP. TURISTICA BENFICA S.A | C5: Saldo Anterior | D5: ='Dezembro2024 '!F6 -> 1284347.5 | F5: Saldo Disponível
A6: CNPJ | B6: 59.275.289/0001-02 | C6: Totais (Entradas/Saídas) | D6: =SUM(D9:D607) -> 765053.51 | E6: =SUM(E9:E607) -> 1052355.3 | F6: =F607 -> 997045.71
A8: Data | B8: Histórico | C8: Complemento | D8: Créditos | E8: Débitos | F8: Saldo
A9: 45659 | B9: Crédito em conta | C9: TRANSPORTADORA TURISTICA SUZANO LTDA | D9: 8000 | F9: =D9-E9+D5 -> 1292347.5
A10: 45659 | B10: Gestão de caixa | E10: =(D9*0.005)+10 -> 50 | F10: =D10-E10+F9 -> 1292297.5
A11: 45659 | B11: Transferência entre contas | C11: TRANSPORTADORA TURISTICA BENFICA S.A | E11: 2000 | F11: =D11-E11+F10 -> 1290297.5
A12: 45660 | B12: Transferência entre contas | C12: TRANSPORTADORA TURISTICA BENFICA S.A | E12: 210000 | F12: =D12-E12+F11 -> 1080297.5
A13: 45660 | B13: Gestão de caixa | E13: =(D12*0.005)+10 -> 10 | F13: =D13-E13+F12 -> 1080287.5
A14: 45664 | B14: Crédito em conta | C14: BB TRANSPORTE E TURISMO LTDA | D14: 90000 | F14: =D14-E14+F13 -> 1170287.5
A15: 45664 | B15: Gestão de caixa | E15: =(D14*0.005)+10 -> 460 | F15: =D15-E15+F14 -> 1169827.5
A16: 45665 | B16: Crédito em conta | C16: PATRIMONY ADMINISTRADORA DE BENS AS | D16: 198414.29 | F16: =D16-E16+F15 -> 1368241.8
A17: 45665 | B17: Gestão de caixa | E17: =(D16*0.005)+10 -> 1002.0715 | F17: =D17-E17+F16 -> 1367239.7
A18: 45667 | B18: Crédito em conta | C18: GILBERTO DO SANTOS DA SILVA | D18: 350 | F18: =D18-E18+F17 -> 1367589.7
A19: 45667 | B19: Gestão de caixa | E19: =(D18*0.005)+10 -> 11.75 | F19: =D19-E19+F18 -> 1367577.9
A20: 45667 | B20: Transferência entre contas | C20: TRANSPORTADORA TURISTICA BENFICA S.A EM RECUPERACAO JUDICIAL | E20: 75300 | F20: =D20-E20+F19 -> 1292277.9
A21: 45667 | B21: Crédito em conta | C21: TRANSPORTADORA TURISTICA BENFICA S.A | D21: 3800 | F21: =D21-E21+F20 -> 1296077.9
A22: 45667 | B22: Gestão de caixa | E22: =(D21*0.005)+10 -> 29 | F22: =D22-E22+F21 -> 1296048.9
A23: 45667 | B23: Crédito em conta | C23: VESPER TRANSPORTES LTDA | D23: 10000 | F23: =D23-E23+F22 -> 1306048.9
A24: 45667 | B24: Gestão de caixa | E24: =(D23*0.005)+10 -> 60 | F24: =D24-E24+F23 -> 1305988.9
A25: 45671 | B25: Crédito em conta | C25: LORINALDO DA SILVA FERREIRA | D25: 10000 | F25: =D25-E25+F24 -> 1315988.9
A26: 45671 | B26: Gestão de caixa | E26: =(D25*0.005)+10 -> 60 | F26: =D26-E26+F25 -> 1315928.9
A27: 45672 | B27: Transferência entre contas | C27: TRANSPORTADORA TURISTICA BENFICA S.A | E27: 32500 | F27: =D27-E27+F26 -> 1283428.9
A28: 45673 | B28: Crédito em conta | C28: MIRIA DIAS SILVEIRA TUCI | D28: 2200 | F28: =D28-E28+F27 -> 1285628.9
A29: 45673 | B29: Gestão de caixa | E29: =(D28*0.5%)+10 -> 21 | F29: =D29-E29+F28 -> 1285607.9
A30: 45673 | B30: Ajuste de saldo | D30: 0.01 | F30: =D30-E30+F29 -> 1285608
A31: 45674 | B31: Transferência entre contas | C31: TRANSPORTADORA TURISTICA BENFICA S.A | E31: 76000 | F31: =D31-E31+F30 -> 1209608
A32: 45677 | B32: Crédito em conta | C32: ARENA FUTIBA II | D32: 10900 | F32: =D32-E32+F31 -> 1220508
A33: 45677 | B33: Gestão de caixa | E33: =(D32*0.5%)+10 -> 64.5 | F33: =D33-E33+F32 -> 1220443.5
A34: 45678 | B34: Crédito em conta | C34: LEANDRO PEREIRA DOS SANTOS | D34: 2650 | F34: =D34-E34+F33 -> 1223093.5
A35: 45678 | B35: Gestão de caixa | E35: =(D34*0.5%)+10 -> 23.25 | F35: =D35-E35+F34 -> 1223070.2
A36: 45679 | B36: Crédito em conta | C36: INDUSTRIAS ARTEB LTDA | D36: 191.86 | F36: =D36-E36+F35 -> 1223262.1
A37: 45679 | B37: Gestão de caixa | E37: =(D36*0.5%)+10 -> 10.9593 | F37: =D37-E37+F36 -> 1223251.1
A38: 45681 | B38: Transferência entre contas | C38: TRANSPORTADORA TURISTICA BENFICA S.A | E38: 54500 | F38: =D38-E38+F37 -> 1168751.1
A39: 45681 | B39: Ajuste de saldo | E39: 0.01 | F39: =D39-E39+F38 -> 1168751.1
A40: 45681 | B40: Tarifa de conta | E40: 10 | F40: =D40-E40+F39 -> 1168741.1
A41: 45684 | B41: Crédito em conta | C41: BB TRANSPORTE E TURISMO LTDA | D41: 383152.11 | F41: =D41-E41+F40 -> 1551893.2
A42: 45684 | B42: Gestão de caixa | E42: =(D41*0.5%)+10 -> 1925.7605 | F42: =D42-E42+F41 -> 1549967.4
A43: 45684 | B43: Crédito em conta | C43: TRANSPORTADORA TURISTICA SUZANO LTDA | D43: 31003.13 | F43: =D43-E43+F42 -> 1580970.6
A44: 45684 | B44: Gestão de caixa | E44: =(D43*0.5%)+10 -> 165.01565 | F44: =D44-E44+F43 -> 1580805.6
A45: 45684 | B45: Transferência entre contas | C45: TRANSPORTADORA TURISTICA BENFICA | E45: 15000 | F45: =D45-E45+F44 -> 1565805.6
A46: 45684 | B46: Tarifa de conta | E46: 10 | F46: =D46-E46+F45 -> 1565795.6
A47: 45685 | B47: Crédito em conta | C47: LUIZ PAULO DIAS MACHADO | D47: 1500 | F47: =D47-E47+F46 -> 1567295.6
A48: 45685 | B48: Gestão de caixa | E48: =(D47*0.5%)+10 -> 17.5 | F48: =D48-E48+F47 -> 1567278.1
A49: 45685 | B49: Transferência entre contas | C49: TRANSPORTADORA TURISTICA BENFICA S.A | E49: 333300 | F49: =D49-E49+F48 -> 1233978.1
A50: 45685 | B50: Tarifa de conta | E50: 20 | F50: =D50-E50+F49 -> 1233958.1
A51: 45960 | B51: Transferência entre contas | C51: TRANSPORTADORA TURISTICA BENFICA S.A | E51: 248200 | F51: =D51-E51+F50 -> 985758.06
A52: 45960 | B52: Tarifa de conta | E52: 10 | F52: =D52-E52+F51 -> 985748.06
A53: 45961 | B53: Crédito em conta | C53: LUIZ PAULO DIAS MACHADO | D53: 1500 | F53: =D53-E53+F52 -> 987248.06
A54: 45961 | B54: Gestão de caixa | E54: =(D53*0.5%)+10 -> 17.5 | F54: =D54-E54+F53 -> 987230.56
A55: 45961 | B55: Crédito em conta | C55: METAL 2 INDUSTRIA E COMERCIO LTDA | D55: 11392.11 | F55: =D55-E55+F54 -> 998622.67
A56: 45961 | B56: Gestão de caixa | E56: =(D55*0.5%)+10 -> 66.96055 | F56: =D56-E56+F55 -> 998555.71
A57: 45961 | B57: Tarifa de conta | E57: 1510 | F57: =D57-E57+F56 -> 997045.71
F58: =D58-E58+F57 -> 997045.71
F59: =D59-E59+F58 -> 997045.71
F60: =D60-E60+F59 -> 997045.71
F61: =D61-E61+F60 -> 997045.71
F62: =D62-E62+F61 -> 997045.71
F63: =D63-E63+F62 -> 997045.71
F64: =D64-E64+F63 -> 997045.71
F65: =D65-E65+F64 -> 997045.71
F66: =D66-E66+F65 -> 997045.71
F67: =D67-E67+F66 -> 997045.71
F68: =D68-E68+F67 -> 997045.71
F69: =D69-E69+F68 -> 997045.71
... F607: =D607-E607+F606 -> 997045.71

Sheet Fevereiro2025
A2: EXTRATO DE MOVIMENTAÇÃO
A4: Banco | B4: LEPTA BANK (274) | C4: Agência | D4: 1 | E4: Conta | F4: 08198095-5
A5: Empresa | B5: TRANSP. TURISTICA BENFICA S.A | C5: Saldo Anterior | D5: =Janeiro2025!F6 -> 997045.71 | F5: Saldo Disponível
A6: CNPJ | B6: 59.275.289/0001-02 | C6: Totais (Entradas/Saídas) | D6: =SUM(D9:D610) -> 768648.56 | E6: =SUM(E9:E610) -> 1066183.3 | F6: =F610 -> 699511.02
A8: Data | B8: Histórico | C8: Complemento | D8: Créditos | E8: Débitos | F8: Saldo
A9: 45691 | B9: Transferência entre contas | E9: 4700 | F9: =D9-E9+D5 -> 992345.71
A10: 45691 | B10: Crédito em conta | C10: TRANSPORTADORA TURISTICA BENFICA | D10: 492.65 | F10: =D10-E10+F9 -> 992838.36
A11: 45691 | B11: Gestão de caixa | E11: =(0.5%*D10)+10 -> 12.46325 | F11: =D11-E11+F10 -> 992825.9
A12: 45691 | B12: Crédito em conta | C12: MPS SOARES TRANSPORTE LTDA | D12: 8000 | F12: =D12-E12+F11 -> 1000825.9
A13: 45691 | B13: Gestão de caixa | E13: =(0.5%*D12)+10 -> 50 | F13: =D13-E13+F12 -> 1000775.9
A14: 45691 | B14: Crédito em conta | C14: ADRIELI GOMES MENDES | D14: 1115 | F14: =D14-E14+F13 -> 1001890.9
A15: 45691 | B15: Gestão de caixa | E15: =(0.5%*D14)+10 -> 15.575 | F15: =D15-E15+F14 -> 1001875.3
A16: 45691 | B16: Tarifa de conta | E16: 20 | F16: =D16-E16+F15 -> 1001855.3
A17: 45692 | B17: Transferência entre contas | C17: TRANSPORTADORA TURISTICA BENFICA | E17: 100 | F17: =D17-E17+F16 -> 1001755.3
A18: 45692 | B18: Tarifa de conta | C18: TRANSPORTADORA TURISTICA BENFICA | E18: 10 | F18: =D18-E18+F17 -> 1001745.3
A19: 45693 | B19: Transferência entre contas | C19: TRANSPORTADORA TURISTICA BENFICA | E19: 12350 | F19: =D19-E19+F18 -> 989395.32
A20: 45693 | B20: Transferência entre contas | C20: TRANSPORTADORA TURISTICA BENFICA | E20: 197050 | F20: =D20-E20+F19 -> 792345.32
A21: 45693 | B21: Tarifa de conta | E21: 40 | F21: =D21-E21+F20 -> 792305.32
A22: 45694 | B22: Crédito em conta | C22: BB TRANSPORTE E TURISMO LTDA | D22: 90000 | F22: =D22-E22+F21 -> 882305.32
A23: 45694 | B23: Gestão de caixa | E23: =(0.5%*D22)+10 -> 460 | F23: =D23-E23+F22 -> 881845.32
A24: 45694 | B24: Transferência entre contas | C24: TRANSPORTADORA TURISTICA BENFICA | E24: 10 | F24: =D24-E24+F23 -> 881835.32
A25: 45694 | B25: Tarifa de conta | E25: 30 | F25: =D25-E25+F24 -> 881805.32
A26: 45695 | B26: Transferência entre contas | C26: TRANSPORTADORA TURISTICA BENFICA | E26: 10 | F26: =D26-E26+F25 -> 881795.32
A27: 45695 | B27: Transferência entre contas | C27: TRANSPORTADORA TURISTICA BENFICA | E27: 76610 | F27: =D27-E27+F26 -> 805185.32
A28: 45695 | B28: Tarifa de conta | E28: 40 | F28: =D28-E28+F27 -> 805145.32
A29: 45698 | B29: Crédito em conta | C29: PATRIMONY ADMINISTRADORA DE BENS AS | D29: 197646.45 | F29: =D29-E29+F28 -> 1002791.8
A30: 45698 | B30: Gestão de caixa | E30: =(0.5%*D29)+10 -> 998.23225 | F30: =D30-E30+F29 -> 1001793.5
A31: 45698 | B31: Crédito em conta | C31: GILBERTO DOS SANTOS SILVA | D31: 350 | F31: =D31-E31+F30 -> 1002143.5
A32: 45698 | B32: Gestão de caixa | E32: =(0.5%*D31)+10 -> 11.75 | F32: =D32-E32+F31 -> 1002131.8
A33: 45698 | B33: Crédito em conta | C33: LORINALDO DA SILVA FERREIRA | D33: 10000 | F33: =D33-E33+F32 -> 1012131.8
A34: 45698 | B34: Gestão de caixa | E34: =(0.5%*D33)+10 -> 60 | F34: =D34-E34+F33 -> 1012071.8
A35: 45698 | B35: Tarifa de conta | E35: 10 | F35: =D35-E35+F34 -> 1012061.8
A36: 45699 | B36: Transferência entre contas | C36: TRANSPORTADORA TURISTICA BENFICA | E36: 120 | F36: =D36-E36+F35 -> 1011941.8
A37: 45699 | B37: Transferência entre contas | C37: TRANSPORTADORA TURISTICA BENFICA | E37: 1500 | F37: =D37-E37+F36 -> 1010441.8
A38: 45699 | B38: Tarifa de conta | E38: 40 | F38: =D38-E38+F37 -> 1010401.8
A39: 45701 | B39: Transferência entre contas | C39: TRANSPORTADORA TURISTICA BENFICA | E39: 100 | F39: =D39-E39+F38 -> 1010301.8
A40: 45701 | B40: Transferência entre contas | C40: TRANSPORTADORA TURISTICA BENFICA | E40: 34600 | F40: =D40-E40+F39 -> 975701.79
A41: 45702 | B41: Tarifa de conta | E41: 40 | F41: =D41-E41+F40 -> 975661.79
A42: 45705 | B42: Transferência entre contas | C42: TRANSPORTADORA TURISTICA BENFICA | E42: 940 | F42: =D42-E42+F41 -> 974721.79
A43: 45705 | B43: Transferência entre contas | C43: TRANSPORTADORA TURISTICA BENFICA | E43: 100 | F43: =D43-E43+F42 -> 974621.79
A44: 45705 | B44: Transferência entre contas | C44: TRANSPORTADORA TURISTICA BENFICA | E44: 20800 | F44: =D44-E44+F43 -> 953821.79
A45: 45705 | B45: Tarifa de conta | E45: 50 | F45: =D45-E45+F44 -> 953771.79
A46: 45706 | B46: Crédito em conta | C46: MIRIA DIAS SILVEIRA TUCI | D46: 2200 | F46: =D46-E46+F45 -> 955971.79
A47: 45706 | B47: Gestão de caixa | E47: =(0.5%*D46)+10 -> 21 | F47: =D47-E47+F46 -> 955950.79
A48: 45706 | B48: Tarifa de conta | E48: 10 | F48: =D48-E48+F47 -> 955940.79
A49: 45707 | B49: Transferência entre contas | C49: TRANSPORTADORA TURISTICA BENFICA | E49: 20 | F49: =D49-E49+F48 -> 955920.79
A50: 45707 | B50: Transferência entre contas | C50: TRANSPORTADORA TURISTICA BENFICA | E50: 54720 | F50: =D50-E50+F49 -> 901200.79
A51: 45707 | B51: Crédito em conta | C51: VESPER TRANSPORTES LTDA | D51: 10000 | F51: =D51-E51+F50 -> 911200.79
A52: 45707 | B52: Gestão de caixa | E52: =(0.5%*D51)+10 -> 60 | F52: =D52-E52+F51 -> 911140.79
A53: 45707 | B53: Tarifa de conta | E53: 50 | F53: =D53-E53+F52 -> 911090.79
A54: 45708 | B54: Crédito em conta | C54: ALEXANDRE RAPHAEL MARINO | D54: 270 | F54: =D54-E54+F53 -> 911360.79
A55: 45708 | B55: Gestão de caixa | E55: =(0.5%*D54)+10 -> 11.35 | F55: =D55-E55+F54 -> 911349.44
A56: 45708 | B56: Crédito em conta | C56: ARENA FUTIBA II | D56: 10900 | F56: =D56-E56+F55 -> 922249.44
A57: 45708 | B57: Gestão de caixa | E57: =(0.5%*D56)+10 -> 64.5 | F57: =D57-E57+F56 -> 922184.94
A58: 45709 | B58: Tarifa de conta | E58: 10 | F58: =D58-E58+F57 -> 922174.94
A59: 45709 | B59: Crédito em conta | C59: ISX ATACADO E DISTRIBUICAO LTDA | D59: 24000 | F59: =D59-E59+F58 -> 946174.94
A60: 45709 | B60: Gestão de caixa | E60: =(0.5%*D59)+10 -> 130 | F60: =D60-E60+F59 -> 946044.94
A61: 45709 | B61: Crédito em conta | C61: INDUSTRIAS ARTEB LTDA | D61: 191.44 | F61: =D61-E61+F60 -> 946236.38
A62: 45709 | B62: Gestão de caixa | E62: =(0.5%*D61)+10 -> 10.9572 | F62: =D62-E62+F61 -> 946225.42
A63: 45709 | B63: Tarifa de conta | E63: 10 | F63: =D63-E63+F62 -> 946215.42
A64: 45712 | B64: Transferência entre contas | C64: TRANSPORTADORA TURISTICA BENFICA | E64: 10 | F64: =D64-E64+F63 -> 946205.42
A65: 45712 | B65: Crédito em conta | C65: BB TRANSPORTE E TURISMO LTDA | D65: 382479.89 | F65: =D65-E65+F64 -> 1328685.3
A66: 45712 | B66: Gestão de caixa | E66: =(0.5%*D65)+10 -> 1922.3995 | F66: =D66-E66+F65 -> 1326762.9
A67: 45712 | B67: Tarifa de conta | E67: 30 | F67: =D67-E67+F66 -> 1326732.9
A68: 45713 | B68: Transferência entre contas | C68: TRANSPORTADORA TURISTICA BENFICA | E68: 10 | F68: =D68-E68+F67 -> 1326722.9
A69: 45713 | B69: Transferência entre contas | C69: TRANSPORTADORA TURISTICA BENFICA | E69: 1100 | F69: =D69-E69+F68 -> 1325622.9
A70: 45713 | B70: Transferência entre contas | C70: TRANSPORTADORA TURISTICA BENFICA | E70: 401950 | F70: =D70-E70+F69 -> 923672.91
A71: 45713 | B71: Transferência entre contas | C71: TRANSPORTADORA TURISTICA BENFICA | E71: 1000 | F71: =D71-E71+F70 -> 922672.91
A72: 45713 | B72: Tarifa de conta | E72: 80 | F72: =D72-E72+F71 -> 922592.91
